Workbook
Name Slicer_Month_Proper: #N/A
Name Slicer_Type__Income_Expense: #N/A

Sheet Data
A1: Date | B1: Details | C1: Debit | D1: Credit | E1: Balance | F1: Month | G1: Type (Income/Expense) | H1: Category | I1: Amount | J1: Month(Proper) | K1: Amount(Positive)
A2: 45748 | B2: EMPLOYER DEP Sa lary of Mar | D2: 114008 | E2: 115118.18 | F2: =TEXT(Account_Data[[#This Row],[Date]],"mmm-yyyy") -> Apr-2025 | G2: =IF(Account_Data[[#This Row],[Credit]]>0,"Income","Expense") -> Income | H2: =IF(AND(Account_Data[[#This Row],[Credit]]>0,ISNUMBER(SEARCH("TFR",Account_Data[[#This Row],[Details]])),Account_Data[[#This Row],[Credit]]>=200000),"Loan Taken", IF(AND(Account_Data[[#This Row],[Debit]]>0,OR(ISNUMBER(SEARCH("ETMONEY",Account_Data[[#This Row],[Details]])),ISNUMBER(SEARCH("PGIM",Account_Data[[#This Row],[Details]])),ISNUMBER(SEARCH("CANARA",Account_Data[[#This Row],[Details]])))),"Investment (Outflow)", IF(AND(Account_Data[[#This Row],[Credit]]>0,OR(ISNUMBER(SEARCH("PGIM",Account_Data[[#This Row],[Details]])),ISNUMBER(SEARCH("CANARA",Account_Data[[#This Row],[Details]])),ISNUMBER(SEARCH("MUTUAL",Account_Data[[#This Row],[Details]])))),"Investment Return", IF(OR(ISNUMBER(SEARCH("LOAN",Account_Data[[#This Row],[Details]])),ISNUMBER(SEARCH("RECOVERY",Account_Data[[#This Row],[Details]]))),"Loan Payment", IF(OR(ISNUMBER(SEARCH("SALARY",Account_Data[[#This Row],[Details]])),ISNUMBER(SEARCH("EMPLOYER DEP",Account_Data[[#This Row],[Details]]))),"Income", IF(OR(ISNUMBER(SEARCH("ACH",Account_Data[[#This Row],[Details]])),ISNUMBER(SEARCH("DIRECT DR",Account_Data[[#This Row],[Details]]))),"EMI", IF(ISNUMBER(SEARCH("ATM",Account_Data[[#This Row],[Details]])),"Cash", IF(ISNUMBER(SEARCH("UPI",Account_Data[[#This Row],[Details]])),"UPI Expense",IF(ISNUMBER(SEARCH("W TFR",Account_Data[[#This Row],[Details]])),"Transfer","Other"))))))))) -> Income | I2: =Account_Data[[#This Row],[Credit]]-Account_Data[[#This Row],[Debit]] -> 114008 | J2: =EOMONTH(Account_Data[[#This Row],[Date]],0) -> 45777 | K2: =ABS(Account_Data[[#This Row],[Amount]]) -> 114008
A3: 45749 | B3: DEBIT ACHDr YESB TP ACH INDIANE | C3: 2000 | E3: 113118.18 | F3: =TEXT(Account_Data[[#This Row],[Date]],"mmm-yyyy") -> Apr-2025 | G3: =IF(Account_Data[[#This Row],[Credit]]>0,"Income","Expense") -> Expense | H3: =IF(AND(Account_Data[[#This Row],[Credit]]>0,ISNUMBER(SEARCH("TFR",Account_Data[[#This Row],[Details]])),Account_Data[[#This Row],[Credit]]>=200000),"Loan Taken", IF(AND(Account_Data[[#This Row],[Debit]]>0,OR(ISNUMBER(SEARCH("ETMONEY",Account_Data[[#This Row],[Details]])),ISNUMBER(SEARCH("PGIM",Account_Data[[#This Row],[Details]])),ISNUMBER(SEARCH("CANARA",Account_Data[[#This Row],[Details]])))),"Investment (Outflow)", IF(AND(Account_Data[[#This Row],[Credit]]>0,OR(ISNUMBER(SEARCH("PGIM",Account_Data[[#This Row],[Details]])),ISNUMBER(SEARCH("CANARA",Account_Data[[#This Row],[Details]])),ISNUMBER(SEARCH("MUTUAL",Account_Data[[#This Row],[Details]])))),"Investment Return", IF(OR(ISNUMBER(SEARCH("LOAN",Account_Data[[#This Row],[Details]])),ISNUMBER(SEARCH("RECOVERY",Account_Data[[#This Row],[Details]]))),"Loan Payment", IF(OR(ISNUMBER(SEARCH("SALARY",Account_Data[[#This Row],[Details]])),ISNUMBER(SEARCH("EMPLOYER DEP",Account_Data[[#This Row],[Details]]))),"Income", IF(OR(ISNUMBER(SEARCH("ACH",Account_Data[[#This Row],[Details]])),ISNUMBER(SEARCH("DIRECT DR",Account_Data[[#This Row],[Details]]))),"EMI", IF(ISNUMBER(SEARCH("ATM",Account_Data[[#This Row],[Details]])),"Cash", IF(ISNUMBER(SEARCH("UPI",Account_Data[[#This Row],[Details]])),"UPI Expense",IF(ISNUMBER(SEARCH("W TFR",Account_Data[[#This Row],[Details]])),"Transfer","Other"))))))))) -> EMI | I3: =Account_Data[[#This Row],[Credit]]-Account_Data[[#This Row],[Debit]] -> -2000 | J3: =EOMONTH(Account_Data[[#This Row],[Date]],0) -> 45777 | K3: =ABS(Account_Data[[#This Row],[Amount]]) -> 2000
A4: 45749 | B4: DEBIT ACHDr YESB TP ACH INDIANE | C4: 2000 | E4: 111118.18 | F4: =TEXT(Account_Data[[#This Row],[Date]],"mmm-yyyy") -> Apr-2025 | G4: =IF(Account_Data[[#This Row],[Credit]]>0,"Income","Expense") -> Expense | H4: =IF(AND(Account_Data[[#This Row],[Credit]]>0,ISNUMBER(SEARCH("TFR",Account_Data[[#This Row],[Details]])),Account_Data[[#This Row],[Credit]]>=200000),"Loan Taken", IF(AND(Account_Data[[#This Row],[Debit]]>0,OR(ISNUMBER(SEARCH("ETMONEY",Account_Data[[#This Row],[Details]])),ISNUMBER(SEARCH("PGIM",Account_Data[[#This Row],[Details]])),ISNUMBER(SEARCH("CANARA",Account_Data[[#This Row],[Details]])))),"Investment (Outflow)", IF(AND(Account_Data[[#This Row],[Credit]]>0,OR(ISNUMBER(SEARCH("PGIM",Account_Data[[#This Row],[Details]])),ISNUMBER(SEARCH("CANARA",Account_Data[[#This Row],[Details]])),ISNUMBER(SEARCH("MUTUAL",Account_Data[[#This Row],[Details]])))),"Investment Return", IF(OR(ISNUMBER(SEARCH("LOAN",Account_Data[[#This Row],[Details]])),ISNUMBER(SEARCH("RECOVERY",Account_Data[[#This Row],[Details]]))),"Loan Payment", IF(OR(ISNUMBER(SEARCH("SALARY",Account_Data[[#This Row],[Details]])),ISNUMBER(SEARCH("EMPLOYER DEP",Account_Data[[#This Row],[Details]]))),"Income", IF(OR(ISNUMBER(SEARCH("ACH",Account_Data[[#This Row],[Details]])),ISNUMBER(SEARCH("DIRECT DR",Account_Data[[#This Row],[Details]]))),"EMI", IF(ISNUMBER(SEARCH("ATM",Account_Data[[#This Row],[Details]])),"Cash", IF(ISNUMBER(SEARCH("UPI",Account_Data[[#This Row],[Details]])),"UPI Expense",IF(ISNUMBER(SEARCH("W TFR",Account_Data[[#This Row],[Details]])),"Transfer","Other"))))))))) -> EMI | I4: =Account_Data[[#This Row],[Credit]]-Account_Data[[#This Row],[Debit]] -> -2000 | J4: =EOMONTH(Account_Data[[#This Row],[Date]],0) -> 45777 | K4: =ABS(Account_Data[[#This Row],[Amount]]) -> 2000
A5: 45749 | B5: DEBIT ACHDr YESB TP ACH INDIANE | C5: 3000 | E5: 108118.18 | F5: =TEXT(Account_Data[[#This Row],[Date]],"mmm-yyyy") -> Apr-2025 | G5: =IF(Account_Data[[#This Row],[Credit]]>0,"Income","Expense") -> Expense | H5: =IF(AND(Account_Data[[#This Row],[Credit]]>0,ISNUMBER(SEARCH("TFR",Account_Data[[#This Row],[Details]])),Account_Data[[#This Row],[Credit]]>=200000),"Loan Taken", IF(AND(Account_Data[[#This Row],[Debit]]>0,OR(ISNUMBER(SEARCH("ETMONEY",Account_Data[[#This Row],[Details]])),ISNUMBER(SEARCH("PGIM",Account_Data[[#This Row],[Details]])),ISNUMBER(SEARCH("CANARA",Account_Data[[#This Row],[Details]])))),"Investment (Outflow)", IF(AND(Account_Data[[#This Row],[Credit]]>0,OR(ISNUMBER(SEARCH("PGIM",Account_Data[[#This Row],[Details]])),ISNUMBER(SEARCH("CANARA",Account_Data[[#This Row],[Details]])),ISNUMBER(SEARCH("MUTUAL",Account_Data[[#This Row],[Details]])))),"Investment Return", IF(OR(ISNUMBER(SEARCH("LOAN",Account_Data[[#This Row],[Details]])),ISNUMBER(SEARCH("RECOVERY",Account_Data[[#This Row],[Details]]))),"Loan Payment", IF(OR(ISNUMBER(SEARCH("SALARY",Account_Data[[#This Row],[Details]])),ISNUMBER(SEARCH("EMPLOYER DEP",Account_Data[[#This Row],[Details]]))),"Income", IF(OR(ISNUMBER(SEARCH("ACH",Account_Data[[#This Row],[Details]])),ISNUMBER(SEARCH("DIRECT DR",Account_Data[[#This Row],[Details]]))),"EMI", IF(ISNUMBER(SEARCH("ATM",Account_Data[[#This Row],[Details]])),"Cash", IF(ISNUMBER(SEARCH("UPI",Account_Data[[#This Row],[Details]])),"UPI Expense",IF(ISNUMBER(SEARCH("W TFR",Account_Data[[#This Row],[Details]])),"Transfer","Other"))))))))) -> EMI | I5: =Account_Data[[#This Row],[Credit]]-Account_Data[[#This Row],[Debit]] -> -3000 | J5: =EOMONTH(Account_Data[[#This Row],[Date]],0) -> 45777 | K5: =ABS(Account_Data[[#This Row],[Amount]]) -> 3000
A6: 45749 | B6: DEBIT ACHDr YESB TP ACH INDIANE | C6: 2000 | E6: 106118.18 | F6: =TEXT(Account_Data[[#This Row],[Date]],"mmm-yyyy") -> Apr-2025 | G6: =IF(Account_Data[[#This Row],[Credit]]>0,"Income","Expense") -> Expense | H6: =IF(AND(Account_Data[[#This Row],[Credit]]>0,ISNUMBER(SEARCH("TFR",Account_Data[[#This Row],[Details]])),Account_Data[[#This Row],[Credit]]>=200000),"Loan Taken", IF(AND(Account_Data[[#This Row],[Debit]]>0,OR(ISNUMBER(SEARCH("ETMONEY",Account_Data[[#This Row],[Details]])),ISNUMBER(SEARCH("PGIM",Account_Data[[#This Row],[Details]])),ISNUMBER(SEARCH("CANARA",Account_Data[[#This Row],[Details]])))),"Investment (Outflow)", IF(AND(Account_Data[[#This Row],[Credit]]>0,OR(ISNUMBER(SEARCH("PGIM",Account_Data[[#This Row],[Details]])),ISNUMBER(SEARCH("CANARA",Account_Data[[#This Row],[Details]])),ISNUMBER(SEARCH("MUTUAL",Account_Data[[#This Row],[Details]])))),"Investment Return", IF(OR(ISNUMBER(SEARCH("LOAN",Account_Data[[#This Row],[Details]])),ISNUMBER(SEARCH("RECOVERY",Account_Data[[#This Row],[Details]]))),"Loan Payment", IF(OR(ISNUMBER(SEARCH("SALARY",Account_Data[[#This Row],[Details]])),ISNUMBER(SEARCH("EMPLOYER DEP",Account_Data[[#This Row],[Details]]))),"Income", IF(OR(ISNUMBER(SEARCH("ACH",Account_Data[[#This Row],[Details]])),ISNUMBER(SEARCH("DIRECT DR",Account_Data[[#This Row],[Details]]))),"EMI", IF(ISNUMBER(SEARCH("ATM",Account_Data[[#This Row],[Details]])),"Cash", IF(ISNUMBER(SEARCH("UPI",Account_Data[[#This Row],[Details]])),"UPI Expense",IF(ISNUMBER(SEARCH("W TFR",Account_Data[[#This Row],[Details]])),"Transfer","Other"))))))))) -> EMI | I6: =Account_Data[[#This Row],[Credit]]-Account_Data[[#This Row],[Debit]] -> -2000 | J6: =EOMONTH(Account_Data[[#This Row],[Date]],0) -> 45777 | K6: =ABS(Account_Data[[#This Row],[Amount]]) -> 2000
A7: 45749 | B7: DEBIT ACHDr YESB TP ACH INDIANE | C7: 5000 | E7: 101118.18 | F7: =TEXT(Account_Data[[#This Row],[Date]],"mmm-yyyy") -> Apr-2025 | G7: =IF(Account_Data[[#This Row],[Credit]]>0,"Income","Expense") -> Expense | H7: =IF(AND(Account_Data[[#This Row],[Credit]]>0,ISNUMBER(SEARCH("TFR",Account_Data[[#This Row],[Details]])),Account_Data[[#This Row],[Credit]]>=200000),"Loan Taken", IF(AND(Account_Data[[#This Row],[Debit]]>0,OR(ISNUMBER(SEARCH("ETMONEY",Account_Data[[#This Row],[Details]])),ISNUMBER(SEARCH("PGIM",Account_Data[[#This Row],[Details]])),ISNUMBER(SEARCH("CANARA",Account_Data[[#This Row],[Details]])))),"Investment (Outflow)", IF(AND(Account_Data[[#This Row],[Credit]]>0,OR(ISNUMBER(SEARCH("PGIM",Account_Data[[#This Row],[Details]])),ISNUMBER(SEARCH("CANARA",Account_Data[[#This Row],[Details]])),ISNUMBER(SEARCH("MUTUAL",Account_Data[[#This Row],[Details]])))),"Investment Return", IF(OR(ISNUMBER(SEARCH("LOAN",Account_Data[[#This Row],[Details]])),ISNUMBER(SEARCH("RECOVERY",Account_Data[[#This Row],[Details]]))),"Loan Payment", IF(OR(ISNUMBER(SEARCH("SALARY",Account_Data[[#This Row],[Details]])),ISNUMBER(SEARCH("EMPLOYER DEP",Account_Data[[#This Row],[Details]]))),"Income", IF(OR(ISNUMBER(SEARCH("ACH",Account_Data[[#This Row],[Details]])),ISNUMBER(SEARCH("DIRECT DR",Account_Data[[#This Row],[Details]]))),"EMI", IF(ISNUMBER(SEARCH("ATM",Account_Data[[#This Row],[Details]])),"Cash", IF(ISNUMBER(SEARCH("UPI",Account_Data[[#This Row],[Details]])),"UPI Expense",IF(ISNUMBER(SEARCH("W TFR",Account_Data[[#This Row],[Details]])),"Transfer","Other"))))))))) -> EMI | I7: =Account_Data[[#This Row],[Credit]]-Account_Data[[#This Row],[Debit]] -> -5000 | J7: =EOMONTH(Account_Data[[#This Row],[Date]],0) -> 45777 | K7: =ABS(Account_Data[[#This Row],[Amount]]) -> 5000
A8: 45749 | B8: DEBIT ACHDr YESB TP ACH INDIANE | C8: 5000 | E8: 96118.18 | F8: =TEXT(Account_Data[[#This Row],[Date]],"mmm-yyyy") -> Apr-2025 | G8: =IF(Account_Data[[#This Row],[Credit]]>0,"Income","Expense") -> Expense | H8: =IF(AND(Account_Data[[#This Row],[Credit]]>0,ISNUMBER(SEARCH("TFR",Account_Data[[#This Row],[Details]])),Account_Data[[#This Row],[Credit]]>=200000),"Loan Taken", IF(AND(Account_Data[[#This Row],[Debit]]>0,OR(ISNUMBER(SEARCH("ETMONEY",Account_Data[[#This Row],[Details]])),ISNUMBER(SEARCH("PGIM",Account_Data[[#This Row],[Details]])),ISNUMBER(SEARCH("CANARA",Account_Data[[#This Row],[Details]])))),"Investment (Outflow)", IF(AND(Account_Data[[#This Row],[Credit]]>0,OR(ISNUMBER(SEARCH("PGIM",Account_Data[[#This Row],[Details]])),ISNUMBER(SEARCH("CANARA",Account_Data[[#This Row],[Details]])),ISNUMBER(SEARCH("MUTUAL",Account_Data[[#This Row],[Details]])))),"Investment Return", IF(OR(ISNUMBER(SEARCH("LOAN",Account_Data[[#This Row],[Details]])),ISNUMBER(SEARCH("RECOVERY",Account_Data[[#This Row],[Details]]))),"Loan Payment", IF(OR(ISNUMBER(SEARCH("SALARY",Account_Data[[#This Row],[Details]])),ISNUMBER(SEARCH("EMPLOYER DEP",Account_Data[[#This Row],[Details]]))),"Income", IF(OR(ISNUMBER(SEARCH("ACH",Account_Data[[#This Row],[Details]])),ISNUMBER(SEARCH("DIRECT DR",Account_Data[[#This Row],[Details]]))),"EMI", IF(ISNUMBER(SEARCH("ATM",Account_Data[[#This Row],[Details]])),"Cash", IF(ISNUMBER(SEARCH("UPI",Account_Data[[#This Row],[Details]])),"UPI Expense",IF(ISNUMBER(SEARCH("W TFR",Account_Data[[#This Row],[Details]])),"Transfer","Other"))))))))) -> EMI | I8: =Account_Data[[#This Row],[Credit]]-Account_Data[[#This Row],[Debit]] -> -5000 | J8: =EOMONTH(Account_Data[[#This Row],[Date]],0) -> 45777 | K8: =ABS(Account_Data[[#This Row],[Amount]]) -> 5000
A9: 45749 | B9: DEBIT ACHDr NACH ETMONEY | C9: 1500 | E9: 94618.18 | F9: =TEXT(Account_Data[[#This Row],[Date]],"mmm-yyyy") -> Apr-2025 | G9: =IF(Account_Data[[#This Row],[Credit]]>0,"Income","Expense") -> Expense | H9: =IF(AND(Account_Data[[#This Row],[Credit]]>0,ISNUMBER(SEARCH("TFR",Account_Data[[#This Row],[Details]])),Account_Data[[#This Row],[Credit]]>=200000),"Loan Taken", IF(AND(Account_Data[[#This Row],[Debit]]>0,OR(ISNUMBER(SEARCH("ETMONEY",Account_Data[[#This Row],[Details]])),ISNUMBER(SEARCH("PGIM",Account_Data[[#This Row],[Details]])),ISNUMBER(SEARCH("CANARA",Account_Data[[#This Row],[Details]])))),"Investment (Outflow)", IF(AND(Account_Data[[#This Row],[Credit]]>0,OR(ISNUMBER(SEARCH("PGIM",Account_Data[[#This Row],[Details]])),ISNUMBER(SEARCH("CANARA",Account_Data[[#This Row],[Details]])),ISNUMBER(SEARCH("MUTUAL",Account_Data[[#This Row],[Details]])))),"Investment Return", IF(OR(ISNUMBER(SEARCH("LOAN",Account_Data[[#This Row],[Details]])),ISNUMBER(SEARCH("RECOVERY",Account_Data[[#This Row],[Details]]))),"Loan Payment", IF(OR(ISNUMBER(SEARCH("SALARY",Account_Data[[#This Row],[Details]])),ISNUMBER(SEARCH("EMPLOYER DEP",Account_Data[[#This Row],[Details]]))),"Income", IF(OR(ISNUMBER(SEARCH("ACH",Account_Data[[#This Row],[Details]])),ISNUMBER(SEARCH("DIRECT DR",Account_Data[[#This Row],[Details]]))),"EMI", IF(ISNUMBER(SEARCH("ATM",Account_Data[[#This Row],[Details]])),"Cash", IF(ISNUMBER(SEARCH("UPI",Account_Data[[#This Row],[Details]])),"UPI Expense",IF(ISNUMBER(SEARCH("W TFR",Account_Data[[#This Row],[Details]])),"Transfer","Other"))))))))) -> Investment (Outflow) | I9: =Account_Data[[#This Row],[Credit]]-Account_Data[[#This Row],[Debit]] -> -1500 | J9: =EOMONTH(Account_Data[[#This Row],[Date]],0) -> 45777 | K9: =ABS(Account_Data[[#This Row],[Amount]]) -> 1500
A10: 45749 | B10: DEBIT ACHDr NACH ETMONEY | C10: 1000 | E10: 93618.18 | F10: =TEXT(Account_Data[[#This Row],[Date]],"mmm-yyyy") -> Apr-2025 | G10: =IF(Account_Data[[#This Row],[Credit]]>0,"Income","Expense") -> Expense | H10: =IF(AND(Account_Data[[#This Row],[Credit]]>0,ISNUMBER(SEARCH("TFR",Account_Data[[#This Row],[Details]])),Account_Data[[#This Row],[Credit]]>=200000),"Loan Taken", IF(AND(Account_Data[[#This Row],[Debit]]>0,OR(ISNUMBER(SEARCH("ETMONEY",Account_Data[[#This Row],[Details]])),ISNUMBER(SEARCH("PGIM",Account_Data[[#This Row],[Details]])),ISNUMBER(SEARCH("CANARA",Account_Data[[#This Row],[Details]])))),"Investment (Outflow)", IF(AND(Account_Data[[#This Row],[Credit]]>0,OR(ISNUMBER(SEARCH("PGIM",Account_Data[[#This Row],[Details]])),ISNUMBER(SEARCH("CANARA",Account_Data[[#This Row],[Details]])),ISNUMBER(SEARCH("MUTUAL",Account_Data[[#This Row],[Details]])))),"Investment Return", IF(OR(ISNUMBER(SEARCH("LOAN",Account_Data[[#This Row],[Details]])),ISNUMBER(SEARCH("RECOVERY",Account_Data[[#This Row],[Details]]))),"Loan Payment", IF(OR(ISNUMBER(SEARCH("SALARY",Account_Data[[#This Row],[Details]])),ISNUMBER(SEARCH("EMPLOYER DEP",Account_Data[[#This Row],[Details]]))),"Income", IF(OR(ISNUMBER(SEARCH("ACH",Account_Data[[#This Row],[Details]])),ISNUMBER(SEARCH("DIRECT DR",Account_Data[[#This Row],[Details]]))),"EMI", IF(ISNUMBER(SEARCH("ATM",Account_Data[[#This Row],[Details]])),"Cash", IF(ISNUMBER(SEARCH("UPI",Account_Data[[#This Row],[Details]])),"UPI Expense",IF(ISNUMBER(SEARCH("W TFR",Account_Data[[#This Row],[Details]])),"Transfer","Other"))))))))) -> Investment (Outflow) | I10: =Account_Data[[#This Row],[Credit]]-Account_Data[[#This Row],[Debit]] -> -1000 | J10: =EOMONTH(Account_Data[[#This Row],[Date]],0) -> 45777 | K10: =ABS(Account_Data[[#This Row],[Amount]]) -> 1000
A11: 45751 | B11: DIRECT DR OF Mr. XYZ ABC H AT | C11: 6280 | E11: 87338.18 | F11: =TEXT(Account_Data[[#This Row],[Date]],"mmm-yyyy") -> Apr-2025 | G11: =IF(Account_Data[[#This Row],[Credit]]>0,"Income","Expense") -> Expense | H11: =IF(AND(Account_Data[[#This Row],[Credit]]>0,ISNUMBER(SEARCH("TFR",Account_Data[[#This Row],[Details]])),Account_Data[[#This Row],[Credit]]>=200000),"Loan Taken", IF(AND(Account_Data[[#This Row],[Debit]]>0,OR(ISNUMBER(SEARCH("ETMONEY",Account_Data[[#This Row],[Details]])),ISNUMBER(SEARCH("PGIM",Account_Data[[#This Row],[Details]])),ISNUMBER(SEARCH("CANARA",Account_Data[[#This Row],[Details]])))),"Investment (Outflow)", IF(AND(Account_Data[[#This Row],[Credit]]>0,OR(ISNUMBER(SEARCH("PGIM",Account_Data[[#This Row],[Details]])),ISNUMBER(SEARCH("CANARA",Account_Data[[#This Row],[Details]])),ISNUMBER(SEARCH("MUTUAL",Account_Data[[#This Row],[Details]])))),"Investment Return", IF(OR(ISNUMBER(SEARCH("LOAN",Account_Data[[#This Row],[Details]])),ISNUMBER(SEARCH("RECOVERY",Account_Data[[#This Row],[Details]]))),"Loan Payment", IF(OR(ISNUMBER(SEARCH("SALARY",Account_Data[[#This Row],[Details]])),ISNUMBER(SEARCH("EMPLOYER DEP",Account_Data[[#This Row],[Details]]))),"Income", IF(OR(ISNUMBER(SEARCH("ACH",Account_Data[[#This Row],[Details]])),ISNUMBER(SEARCH("DIRECT DR",Account_Data[[#This Row],[Details]]))),"EMI", IF(ISNUMBER(SEARCH("ATM",Account_Data[[#This Row],[Details]])),"Cash", IF(ISNUMBER(SEARCH("UPI",Account_Data[[#This Row],[Details]])),"UPI Expense",IF(ISNUMBER(SEARCH("W TFR",Account_Data[[#This Row],[Details]])),"Transfer","Other"))))))))) -> EMI | I11: =Account_Data[[#This Row],[Credit]]-Account_Data[[#This Row],[Debit]] -> -6280 | J11: =EOMONTH(Account_Data[[#This Row],[Date]],0) -> 45777 | K11: =ABS(Account_Data[[#This Row],[Amount]]) -> 6280
A12: 45751 | B12: W TFR UPI/DR//SHAMBHAV/KKBK//P aym AT | C12: 25000 | E12: 62338.18 | F12: =TEXT(Account_Data[[#This Row],[Date]],"mmm-yyyy") -> Apr-2025 | G12: =IF(Account_Data[[#This Row],[Credit]]>0,"Income","Expense") -> Expense | H12: =IF(AND(Account_Data[[#This Row],[Credit]]>0,ISNUMBER(SEARCH("TFR",Account_Data[[#This Row],[Details]])),Account_Data[[#This Row],[Credit]]>=200000),"Loan Taken", IF(AND(Account_Data[[#This Row],[Debit]]>0,OR(ISNUMBER(SEARCH("ETMONEY",Account_Data[[#This Row],[Details]])),ISNUMBER(SEARCH("PGIM",Account_Data[[#This Row],[Details]])),ISNUMBER(SEARCH("CANARA",Account_Data[[#This Row],[Details]])))),"Investment (Outflow)", IF(AND(Account_Data[[#This Row],[Credit]]>0,OR(ISNUMBER(SEARCH("PGIM",Account_Data[[#This Row],[Details]])),ISNUMBER(SEARCH("CANARA",Account_Data[[#This Row],[Details]])),ISNUMBER(SEARCH("MUTUAL",Account_Data[[#This Row],[Details]])))),"Investment Return", IF(OR(ISNUMBER(SEARCH("LOAN",Account_Data[[#This Row],[Details]])),ISNUMBER(SEARCH("RECOVERY",Account_Data[[#This Row],[Details]]))),"Loan Payment", IF(OR(ISNUMBER(SEARCH("SALARY",Account_Data[[#This Row],[Details]])),ISNUMBER(SEARCH("EMPLOYER DEP",Account_Data[[#This Row],[Details]]))),"Income", IF(OR(ISNUMBER(SEARCH("ACH",Account_Data[[#This Row],[Details]])),ISNUMBER(SEARCH("DIRECT DR",Account_Data[[#This Row],[Details]]))),"EMI", IF(ISNUMBER(SEARCH("ATM",Account_Data[[#This Row],[Details]])),"Cash", IF(ISNUMBER(SEARCH("UPI",Account_Data[[#This Row],[Details]])),"UPI Expense",IF(ISNUMBER(SEARCH("W TFR",Account_Data[[#This Row],[Details]])),"Transfer","Other"))))))))) -> UPI Expense | I12: =Account_Data[[#This Row],[Credit]]-Account_Data[[#This Row],[Debit]] -> -25000 | J12: =EOMONTH(Account_Data[[#This Row],[Date]],0) -> 45777 | K12: =ABS(Account_Data[[#This Row],[Amount]]) -> 25000
A13: 45752 | B13: W TFR UPI/DR//Ketto On/YESB/paytm-/O idO AT | C13: 50 | E13: 62288.18 | F13: =TEXT(Account_Data[[#This Row],[Date]],"mmm-yyyy") -> Apr-2025 | G13: =IF(Account_Data[[#This Row],[Credit]]>0,"Income","Expense") -> Expense | H13: =IF(AND(Account_Data[[#This Row],[Credit]]>0,ISNUMBER(SEARCH("TFR",Account_Data[[#This Row],[Details]])),Account_Data[[#This Row],[Credit]]>=200000),"Loan Taken", IF(AND(Account_Data[[#This Row],[Debit]]>0,OR(ISNUMBER(SEARCH("ETMONEY",Account_Data[[#This Row],[Details]])),ISNUMBER(SEARCH("PGIM",Account_Data[[#This Row],[Details]])),ISNUMBER(SEARCH("CANARA",Account_Data[[#This Row],[Details]])))),"Investment (Outflow)", IF(AND(Account_Data[[#This Row],[Credit]]>0,OR(ISNUMBER(SEARCH("PGIM",Account_Data[[#This Row],[Details]])),ISNUMBER(SEARCH("CANARA",Account_Data[[#This Row],[Details]])),ISNUMBER(SEARCH("MUTUAL",Account_Data[[#This Row],[Details]])))),"Investment Return", IF(OR(ISNUMBER(SEARCH("LOAN",Account_Data[[#This Row],[Details]])),ISNUMBER(SEARCH("RECOVERY",Account_Data[[#This Row],[Details]]))),"Loan Payment", IF(OR(ISNUMBER(SEARCH("SALARY",Account_Data[[#This Row],[Details]])),ISNUMBER(SEARCH("EMPLOYER DEP",Account_Data[[#This Row],[Details]]))),"Income", IF(OR(ISNUMBER(SEARCH("ACH",Account_Data[[#This Row],[Details]])),ISNUMBER(SEARCH("DIRECT DR",Account_Data[[#This Row],[Details]]))),"EMI", IF(ISNUMBER(SEARCH("ATM",Account_Data[[#This Row],[Details]])),"Cash", IF(ISNUMBER(SEARCH("UPI",Account_Data[[#This Row],[Details]])),"UPI Expense",IF(ISNUMBER(SEARCH("W TFR",Account_Data[[#This Row],[Details]])),"Transfer","Other"))))))))) -> UPI Expense | I13: =Account_Data[[#This Row],[Credit]]-Account_Data[[#This Row],[Debit]] -> -50 | J13: =EOMONTH(Account_Data[[#This Row],[Date]],0) -> 45777 | K13: =ABS(Account_Data[[#This Row],[Amount]]) -> 50
A14: 45752 | B14: DEBIT ACHDr NACH INSTITUTE FEE | C14: 25394.71 | E14: 36893.47 | F14: =TEXT(Account_Data[[#This Row],[Date]],"mmm-yyyy") -> Apr-2025 | G14: =IF(Account_Data[[#This Row],[Credit]]>0,"Income","Expense") -> Expense | H14: =IF(AND(Account_Data[[#This Row],[Credit]]>0,ISNUMBER(SEARCH("TFR",Account_Data[[#This Row],[Details]])),Account_Data[[#This Row],[Credit]]>=200000),"Loan Taken", IF(AND(Account_Data[[#This Row],[Debit]]>0,OR(ISNUMBER(SEARCH("ETMONEY",Account_Data[[#This Row],[Details]])),ISNUMBER(SEARCH("PGIM",Account_Data[[#This Row],[Details]])),ISNUMBER(SEARCH("CANARA",Account_Data[[#This Row],[Details]])))),"Investment (Outflow)", IF(AND(Account_Data[[#This Row],[Credit]]>0,OR(ISNUMBER(SEARCH("PGIM",Account_Data[[#This Row],[Details]])),ISNUMBER(SEARCH("CANARA",Account_Data[[#This Row],[Details]])),ISNUMBER(SEARCH("MUTUAL",Account_Data[[#This Row],[Details]])))),"Investment Return", IF(OR(ISNUMBER(SEARCH("LOAN",Account_Data[[#This Row],[Details]])),ISNUMBER(SEARCH("RECOVERY",Account_Data[[#This Row],[Details]]))),"Loan Payment", IF(OR(ISNUMBER(SEARCH("SALARY",Account_Data[[#This Row],[Details]])),ISNUMBER(SEARCH("EMPLOYER DEP",Account_Data[[#This Row],[Details]]))),"Income", IF(OR(ISNUMBER(SEARCH("ACH",Account_Data[[#This Row],[Details]])),ISNUMBER(SEARCH("DIRECT DR",Account_Data[[#This Row],[Details]]))),"EMI", IF(ISNUMBER(SEARCH("ATM",Account_Data[[#This Row],[Details]])),"Cash", IF(ISNUMBER(SEARCH("UPI",Account_Data[[#This Row],[Details]])),"UPI Expense",IF(ISNUMBER(SEARCH("W TFR",Account_Data[[#This Row],[Details]])),"Transfer","Other"))))))))) -> EMI | I14: =Account_Data[[#This Row],[Credit]]-Account_Data[[#This Row],[Debit]] -> -25394.71 | J14: =EOMONTH(Account_Data[[#This Row],[Date]],0) -> 45777 | K14: =ABS(Account_Data[[#This Row],[Amount]]) -> 25394.71
A15: 45754 | B15: DIRECT DR OF Mr. XYZ ABC H AT | C15: 8704 | E15: 28189.47 | F15: =TEXT(Account_Data[[#This Row],[Date]],"mmm-yyyy") -> Apr-2025 | G15: =IF(Account_Data[[#This Row],[Credit]]>0,"Income","Expense") -> Expense | H15: =IF(AND(Account_Data[[#This Row],[Credit]]>0,ISNUMBER(SEARCH("TFR",Account_Data[[#This Row],[Details]])),Account_Data[[#This Row],[Credit]]>=200000),"Loan Taken", IF(AND(Account_Data[[#This Row],[Debit]]>0,OR(ISNUMBER(SEARCH("ETMONEY",Account_Data[[#This Row],[Details]])),ISNUMBER(SEARCH("PGIM",Account_Data[[#This Row],[Details]])),ISNUMBER(SEARCH("CANARA",Account_Data[[#This Row],[Details]])))),"Investment (Outflow)", IF(AND(Account_Data[[#This Row],[Credit]]>0,OR(ISNUMBER(SEARCH("PGIM",Account_Data[[#This Row],[Details]])),ISNUMBER(SEARCH("CANARA",Account_Data[[#This Row],[Details]])),ISNUMBER(SEARCH("MUTUAL",Account_Data[[#This Row],[Details]])))),"Investment Return", IF(OR(ISNUMBER(SEARCH("LOAN",Account_Data[[#This Row],[Details]])),ISNUMBER(SEARCH("RECOVERY",Account_Data[[#This Row],[Details]]))),"Loan Payment", IF(OR(ISNUMBER(SEARCH("SALARY",Account_Data[[#This Row],[Details]])),ISNUMBER(SEARCH("EMPLOYER DEP",Account_Data[[#This Row],[Details]]))),"Income", IF(OR(ISNUMBER(SEARCH("ACH",Account_Data[[#This Row],[Details]])),ISNUMBER(SEARCH("DIRECT DR",Account_Data[[#This Row],[Details]]))),"EMI", IF(ISNUMBER(SEARCH("ATM",Account_Data[[#This Row],[Details]])),"Cash", IF(ISNUMBER(SEARCH("UPI",Account_Data[[#This Row],[Details]])),"UPI Expense",IF(ISNUMBER(SEARCH("W TFR",Account_Data[[#This Row],[Details]])),"Transfer","Other"))))))))) -> EMI | I15: =Account_Data[[#This Row],[Credit]]-Account_Data[[#This Row],[Debit]] -> -8704 | J15: =EOMONTH(Account_Data[[#This Row],[Date]],0) -> 45777 | K15: =ABS(Account_Data[[#This Row],[Amount]]) -> 8704
A16: 45754 | B16: DEP TFR NEFT*SCBL*SCBLH*PGIM INDIA M UTU AT | D16: 44060.27 | E16: 72249.74 | F16: =TEXT(Account_Data[[#This Row],[Date]],"mmm-yyyy") -> Apr-2025 | G16: =IF(Account_Data[[#This Row],[Credit]]>0,"Income","Expense") -> Income | H16: =IF(AND(Account_Data[[#This Row],[Credit]]>0,ISNUMBER(SEARCH("TFR",Account_Data[[#This Row],[Details]])),Account_Data[[#This Row],[Credit]]>=200000),"Loan Taken", IF(AND(Account_Data[[#This Row],[Debit]]>0,OR(ISNUMBER(SEARCH("ETMONEY",Account_Data[[#This Row],[Details]])),ISNUMBER(SEARCH("PGIM",Account_Data[[#This Row],[Details]])),ISNUMBER(SEARCH("CANARA",Account_Data[[#This Row],[Details]])))),"Investment (Outflow)", IF(AND(Account_Data[[#This Row],[Credit]]>0,OR(ISNUMBER(SEARCH("PGIM",Account_Data[[#This Row],[Details]])),ISNUMBER(SEARCH("CANARA",Account_Data[[#This Row],[Details]])),ISNUMBER(SEARCH("MUTUAL",Account_Data[[#This Row],[Details]])))),"Investment Return", IF(OR(ISNUMBER(SEARCH("LOAN",Account_Data[[#This Row],[Details]])),ISNUMBER(SEARCH("RECOVERY",Account_Data[[#This Row],[Details]]))),"Loan Payment", IF(OR(ISNUMBER(SEARCH("SALARY",Account_Data[[#This Row],[Details]])),ISNUMBER(SEARCH("EMPLOYER DEP",Account_Data[[#This Row],[Details]]))),"Income", IF(OR(ISNUMBER(SEARCH("ACH",Account_Data[[#This Row],[Details]])),ISNUMBER(SEARCH("DIRECT DR",Account_Data[[#This Row],[Details]]))),"EMI", IF(ISNUMBER(SEARCH("ATM",Account_Data[[#This Row],[Details]])),"Cash", IF(ISNUMBER(SEARCH("UPI",Account_Data[[#This Row],[Details]])),"UPI Expense",IF(ISNUMBER(SEARCH("W TFR",Account_Data[[#This Row],[Details]])),"Transfer","Other"))))))))) -> Investment Return | I16: =Account_Data[[#This Row],[Credit]]-Account_Data[[#This Row],[Debit]] -> 44060.27 | J16: =EOMONTH(Account_Data[[#This Row],[Date]],0) -> 45777 | K16: =ABS(Account_Data[[#This Row],[Amount]]) -> 44060.27
A17: 45754 | B17: DEP TFR NEFT*HDFC*HDFCH*CANARA ROBEC O M AT | D17: 30864.21 | E17: 103113.95 | F17: =TEXT(Account_Data[[#This Row],[Date]],"mmm-yyyy") -> Apr-2025 | G17: =IF(Account_Data[[#This Row],[Credit]]>0,"Income","Expense") -> Income | H17: =IF(AND(Account_Data[[#This Row],[Credit]]>0,ISNUMBER(SEARCH("TFR",Account_Data[[#This Row],[Details]])),Account_Data[[#This Row],[Credit]]>=200000),"Loan Taken", IF(AND(Account_Data[[#This Row],[Debit]]>0,OR(ISNUMBER(SEARCH("ETMONEY",Account_Data[[#This Row],[Details]])),ISNUMBER(SEARCH("PGIM",Account_Data[[#This Row],[Details]])),ISNUMBER(SEARCH("CANARA",Account_Data[[#This Row],[Details]])))),"Investment (Outflow)", IF(AND(Account_Data[[#This Row],[Credit]]>0,OR(ISNUMBER(SEARCH("PGIM",Account_Data[[#This Row],[Details]])),ISNUMBER(SEARCH("CANARA",Account_Data[[#This Row],[Details]])),ISNUMBER(SEARCH("MUTUAL",Account_Data[[#This Row],[Details]])))),"Investment Return", IF(OR(ISNUMBER(SEARCH("LOAN",Account_Data[[#This Row],[Details]])),ISNUMBER(SEARCH("RECOVERY",Account_Data[[#This Row],[Details]]))),"Loan Payment", IF(OR(ISNUMBER(SEARCH("SALARY",Account_Data[[#This Row],[Details]])),ISNUMBER(SEARCH("EMPLOYER DEP",Account_Data[[#This Row],[Details]]))),"Income", IF(OR(ISNUMBER(SEARCH("ACH",Account_Data[[#This Row],[Details]])),ISNUMBER(SEARCH("DIRECT DR",Account_Data[[#This Row],[Details]]))),"EMI", IF(ISNUMBER(SEARCH("ATM",Account_Data[[#This Row],[Details]])),"Cash", IF(ISNUMBER(SEARCH("UPI",Account_Data[[#This Row],[Details]])),"UPI Expense",IF(ISNUMBER(SEARCH("W TFR",Account_Data[[#This Row],[Details]])),"Transfer","Other"))))))))) -> Investment Return | I17: =Account_Data[[#This Row],[Credit]]-Account_Data[[#This Row],[Debit]] -> 30864.21 | J17: =EOMONTH(Account_Data[[#This Row],[Date]],0) -> 45777 | K17: =ABS(Account_Data[[#This Row],[Amount]]) -> 30864.21
A18: 45755 | B18: W TFR SMA OVERDUE RECOVERY OF Mr. XYZ AT | C18: 16329 | E18: 86784.95 | F18: =TEXT(Account_Data[[#This Row],[Date]],"mmm-yyyy") -> Apr-2025 | G18: =IF(Account_Data[[#This Row],[Credit]]>0,"Income","Expense") -> Expense | H18: =IF(AND(Account_Data[[#This Row],[Credit]]>0,ISNUMBER(SEARCH("TFR",Account_Data[[#This Row],[Details]])),Account_Data[[#This Row],[Credit]]>=200000),"Loan Taken", IF(AND(Account_Data[[#This Row],[Debit]]>0,OR(ISNUMBER(SEARCH("ETMONEY",Account_Data[[#This Row],[Details]])),ISNUMBER(SEARCH("PGIM",Account_Data[[#This Row],[Details]])),ISNUMBER(SEARCH("CANARA",Account_Data[[#This Row],[Details]])))),"Investment (Outflow)", IF(AND(Account_Data[[#This Row],[Credit]]>0,OR(ISNUMBER(SEARCH("PGIM",Account_Data[[#This Row],[Details]])),ISNUMBER(SEARCH("CANARA",Account_Data[[#This Row],[Details]])),ISNUMBER(SEARCH("MUTUAL",Account_Data[[#This Row],[Details]])))),"Investment Return", IF(OR(ISNUMBER(SEARCH("LOAN",Account_Data[[#This Row],[Details]])),ISNUMBER(SEARCH("RECOVERY",Account_Data[[#This Row],[Details]]))),"Loan Payment", IF(OR(ISNUMBER(SEARCH("SALARY",Account_Data[[#This Row],[Details]])),ISNUMBER(SEARCH("EMPLOYER DEP",Account_Data[[#This Row],[Details]]))),"Income", IF(OR(ISNUMBER(SEARCH("ACH",Account_Data[[#This Row],[Details]])),ISNUMBER(SEARCH("DIRECT DR",Account_Data[[#This Row],[Details]]))),"EMI", IF(ISNUMBER(SEARCH("ATM",Account_Data[[#This Row],[Details]])),"Cash", IF(ISNUMBER(SEARCH("UPI",Account_Data[[#This Row],[Details]])),"UPI Expense",IF(ISNUMBER(SEARCH("W TFR",Account_Data[[#This Row],[Details]])),"Transfer","Other"))))))))) -> Loan Payment | I18: =Account_Data[[#This Row],[Credit]]-Account_Data[[#This Row],[Debit]] -> -16329 | J18: =EOMONTH(Account_Data[[#This Row],[Date]],0) -> 45777 | K18: =ABS(Account_Data[[#This Row],[Amount]]) -> 16329
A19: 45756 | B19: W TFR UPI/DR//SOMAN T/YESB/paytmqrx/Pa yme AT | C19: 450 | E19: 86334.95 | F19: =TEXT(Account_Data[[#This Row],[Date]],"mmm-yyyy") -> Apr-2025 | G19: =IF(Account_Data[[#This Row],[Credit]]>0,"Income","Expense") -> Expense | H19: =IF(AND(Account_Data[[#This Row],[Credit]]>0,ISNUMBER(SEARCH("TFR",Account_Data[[#This Row],[Details]])),Account_Data[[#This Row],[Credit]]>=200000),"Loan Taken", IF(AND(Account_Data[[#This Row],[Debit]]>0,OR(ISNUMBER(SEARCH("ETMONEY",Account_Data[[#This Row],[Details]])),ISNUMBER(SEARCH("PGIM",Account_Data[[#This Row],[Details]])),ISNUMBER(SEARCH("CANARA",Account_Data[[#This Row],[Details]])))),"Investment (Outflow)", IF(AND(Account_Data[[#This Row],[Credit]]>0,OR(ISNUMBER(SEARCH("PGIM",Account_Data[[#This Row],[Details]])),ISNUMBER(SEARCH("CANARA",Account_Data[[#This Row],[Details]])),ISNUMBER(SEARCH("MUTUAL",Account_Data[[#This Row],[Details]])))),"Investment Return", IF(OR(ISNUMBER(SEARCH("LOAN",Account_Data[[#This Row],[Details]])),ISNUMBER(SEARCH("RECOVERY",Account_Data[[#This Row],[Details]]))),"Loan Payment", IF(OR(ISNUMBER(SEARCH("SALARY",Account_Data[[#This Row],[Details]])),ISNUMBER(SEARCH("EMPLOYER DEP",Account_Data[[#This Row],[Details]]))),"Income", IF(OR(ISNUMBER(SEARCH("ACH",Account_Data[[#This Row],[Details]])),ISNUMBER(SEARCH("DIRECT DR",Account_Data[[#This Row],[Details]]))),"EMI", IF(ISNUMBER(SEARCH("ATM",Account_Data[[#This Row],[Details]])),"Cash", IF(ISNUMBER(SEARCH("UPI",Account_Data[[#This Row],[Details]])),"UPI Expense",IF(ISNUMBER(SEARCH("W TFR",Account_Data[[#This Row],[Details]])),"Transfer","Other"))))))))) -> UPI Expense | I19: =Account_Data[[#This Row],[Credit]]-Account_Data[[#This Row],[Debit]] -> -450 | J19: =EOMONTH(Account_Data[[#This Row],[Date]],0) -> 45777 | K19: =ABS(Account_Data[[#This Row],[Amount]]) -> 450
A20: 45757 | B20: W TFR UPI/DR//Bank Acc/BARB//P aym AT | C20: 66500 | E20: 19834.95 | F20: =TEXT(Account_Data[[#This Row],[Date]],"mmm-yyyy") -> Apr-2025 | G20: =IF(Account_Data[[#This Row],[Credit]]>0,"Income","Expense") -> Expense | H20: =IF(AND(Account_Data[[#This Row],[Credit]]>0,ISNUMBER(SEARCH("TFR",Account_Data[[#This Row],[Details]])),Account_Data[[#This Row],[Credit]]>=200000),"Loan Taken", IF(AND(Account_Data[[#This Row],[Debit]]>0,OR(ISNUMBER(SEARCH("ETMONEY",Account_Data[[#This Row],[Details]])),ISNUMBER(SEARCH("PGIM",Account_Data[[#This Row],[Details]])),ISNUMBER(SEARCH("CANARA",Account_Data[[#This Row],[Details]])))),"Investment (Outflow)", IF(AND(Account_Data[[#This Row],[Credit]]>0,OR(ISNUMBER(SEARCH("PGIM",Account_Data[[#This Row],[Details]])),ISNUMBER(SEARCH("CANARA",Account_Data[[#This Row],[Details]])),ISNUMBER(SEARCH("MUTUAL",Account_Data[[#This Row],[Details]])))),"Investment Return", IF(OR(ISNUMBER(SEARCH("LOAN",Account_Data[[#This Row],[Details]])),ISNUMBER(SEARCH("RECOVERY",Account_Data[[#This Row],[Details]]))),"Loan Payment", IF(OR(ISNUMBER(SEARCH("SALARY",Account_Data[[#This Row],[Details]])),ISNUMBER(SEARCH("EMPLOYER DEP",Account_Data[[#This Row],[Details]]))),"Income", IF(OR(ISNUMBER(SEARCH("ACH",Account_Data[[#This Row],[Details]])),ISNUMBER(SEARCH("DIRECT DR",Account_Data[[#This Row],[Details]]))),"EMI", IF(ISNUMBER(SEARCH("ATM",Account_Data[[#This Row],[Details]])),"Cash", IF(ISNUMBER(SEARCH("UPI",Account_Data[[#This Row],[Details]])),"UPI Expense",IF(ISNUMBER(SEARCH("W TFR",Account_Data[[#This Row],[Details]])),"Transfer","Other"))))))))) -> UPI Expense | I20: =Account_Data[[#This Row],[Credit]]-Account_Data[[#This Row],[Debit]] -> -66500 | J20: =EOMONTH(Account_Data[[#This Row],[Date]],0) -> 45777 | K20: =ABS(Account_Data[[#This Row],[Amount]]) -> 66500
A21: 45758 | B21: DEP TFR PABFC IOCL LPG SUBSIDY IOAPD AT | D21: 59.52 | E21: 19894.47 | F21: =TEXT(Account_Data[[#This Row],[Date]],"mmm-yyyy") -> Apr-2025 | G21: =IF(Account_Data[[#This Row],[Credit]]>0,"Income","Expense") -> Income | H21: =IF(AND(Account_Data[[#This Row],[Credit]]>0,ISNUMBER(SEARCH("TFR",Account_Data[[#This Row],[Details]])),Account_Data[[#This Row],[Credit]]>=200000),"Loan Taken", IF(AND(Account_Data[[#This Row],[Debit]]>0,OR(ISNUMBER(SEARCH("ETMONEY",Account_Data[[#This Row],[Details]])),ISNUMBER(SEARCH("PGIM",Account_Data[[#This Row],[Details]])),ISNUMBER(SEARCH("CANARA",Account_Data[[#This Row],[Details]])))),"Investment (Outflow)", IF(AND(Account_Data[[#This Row],[Credit]]>0,OR(ISNUMBER(SEARCH("PGIM",Account_Data[[#This Row],[Details]])),ISNUMBER(SEARCH("CANARA",Account_Data[[#This Row],[Details]])),ISNUMBER(SEARCH("MUTUAL",Account_Data[[#This Row],[Details]])))),"Investment Return", IF(OR(ISNUMBER(SEARCH("LOAN",Account_Data[[#This Row],[Details]])),ISNUMBER(SEARCH("RECOVERY",Account_Data[[#This Row],[Details]]))),"Loan Payment", IF(OR(ISNUMBER(SEARCH("SALARY",Account_Data[[#This Row],[Details]])),ISNUMBER(SEARCH("EMPLOYER DEP",Account_Data[[#This Row],[Details]]))),"Income", IF(OR(ISNUMBER(SEARCH("ACH",Account_Data[[#This Row],[Details]])),ISNUMBER(SEARCH("DIRECT DR",Account_Data[[#This Row],[Details]]))),"EMI", IF(ISNUMBER(SEARCH("ATM",Account_Data[[#This Row],[Details]])),"Cash", IF(ISNUMBER(SEARCH("UPI",Account_Data[[#This Row],[Details]])),"UPI Expense",IF(ISNUMBER(SEARCH("W TFR",Account_Data[[#This Row],[Details]])),"Transfer","Other"))))))))) -> Other | I21: =Account_Data[[#This Row],[Credit]]-Account_Data[[#This Row],[Debit]] -> 59.52 | J21: =EOMONTH(Account_Data[[#This Row],[Date]],0) -> 45777 | K21: =ABS(Account_Data[[#This Row],[Amount]]) -> 59.52
A22: 45758 | B22: W TFR UPI/DR//Pranjal /SBIN/pranjalsin/P aym AT | C22: 1219 | E22: 18675.47 | F22: =TEXT(Account_Data[[#This Row],[Date]],"mmm-yyyy") -> Apr-2025 | G22: =IF(Account_Data[[#This Row],[Credit]]>0,"Income","Expense") -> Expense | H22: =IF(AND(Account_Data[[#This Row],[Credit]]>0,ISNUMBER(SEARCH("TFR",Account_Data[[#This Row],[Details]])),Account_Data[[#This Row],[Credit]]>=200000),"Loan Taken", IF(AND(Account_Data[[#This Row],[Debit]]>0,OR(ISNUMBER(SEARCH("ETMONEY",Account_Data[[#This Row],[Details]])),ISNUMBER(SEARCH("PGIM",Account_Data[[#This Row],[Details]])),ISNUMBER(SEARCH("CANARA",Account_Data[[#This Row],[Details]])))),"Investment (Outflow)", IF(AND(Account_Data[[#This Row],[Credit]]>0,OR(ISNUMBER(SEARCH("PGIM",Account_Data[[#This Row],[Details]])),ISNUMBER(SEARCH("CANARA",Account_Data[[#This Row],[Details]])),ISNUMBER(SEARCH("MUTUAL",Account_Data[[#This Row],[Details]])))),"Investment Return", IF(OR(ISNUMBER(SEARCH("LOAN",Account_Data[[#This Row],[Details]])),ISNUMBER(SEARCH("RECOVERY",Account_Data[[#This Row],[Details]]))),"Loan Payment", IF(OR(ISNUMBER(SEARCH("SALARY",Account_Data[[#This Row],[Details]])),ISNUMBER(SEARCH("EMPLOYER DEP",Account_Data[[#This Row],[Details]]))),"Income", IF(OR(ISNUMBER(SEARCH("ACH",Account_Data[[#This Row],[Details]])),ISNUMBER(SEARCH("DIRECT DR",Account_Data[[#This Row],[Details]]))),"EMI", IF(ISNUMBER(SEARCH("ATM",Account_Data[[#This Row],[Details]])),"Cash", IF(ISNUMBER(SEARCH("UPI",Account_Data[[#This Row],[Details]])),"UPI Expense",IF(ISNUMBER(SEARCH("W TFR",Account_Data[[#This Row],[Details]])),"Transfer","Other"))))))))) -> UPI Expense | I22: =Account_Data[[#This Row],[Credit]]-Account_Data[[#This Row],[Debit]] -> -1219 | J22: =EOMONTH(Account_Data[[#This Row],[Date]],0) -> 45777 | K22: =ABS(Account_Data[[#This Row],[Amount]]) -> 1219
A23: 45758 | B23: W TFR UPI/DR//SOMAN T/YESB/paytmqrx/Pa yme AT | C23: 260 | E23: 18415.47 | F23: =TEXT(Account_Data[[#This Row],[Date]],"mmm-yyyy") -> Apr-2025 | G23: =IF(Account_Data[[#This Row],[Credit]]>0,"Income","Expense") -> Expense | H23: =IF(AND(Account_Data[[#This Row],[Credit]]>0,ISNUMBER(SEARCH("TFR",Account_Data[[#This Row],[Details]])),Account_Data[[#This Row],[Credit]]>=200000),"Loan Taken", IF(AND(Account_Data[[#This Row],[Debit]]>0,OR(ISNUMBER(SEARCH("ETMONEY",Account_Data[[#This Row],[Details]])),ISNUMBER(SEARCH("PGIM",Account_Data[[#This Row],[Details]])),ISNUMBER(SEARCH("CANARA",Account_Data[[#This Row],[Details]])))),"Investment (Outflow)", IF(AND(Account_Data[[#This Row],[Credit]]>0,OR(ISNUMBER(SEARCH("PGIM",Account_Data[[#This Row],[Details]])),ISNUMBER(SEARCH("CANARA",Account_Data[[#This Row],[Details]])),ISNUMBER(SEARCH("MUTUAL",Account_Data[[#This Row],[Details]])))),"Investment Return", IF(OR(ISNUMBER(SEARCH("LOAN",Account_Data[[#This Row],[Details]])),ISNUMBER(SEARCH("RECOVERY",Account_Data[[#This Row],[Details]]))),"Loan Payment", IF(OR(ISNUMBER(SEARCH("SALARY",Account_Data[[#This Row],[Details]])),ISNUMBER(SEARCH("EMPLOYER DEP",Account_Data[[#This Row],[Details]]))),"Income", IF(OR(ISNUMBER(SEARCH("ACH",Account_Data[[#This Row],[Details]])),ISNUMBER(SEARCH("DIRECT DR",Account_Data[[#This Row],[Details]]))),"EMI", IF(ISNUMBER(SEARCH("ATM",Account_Data[[#This Row],[Details]])),"Cash", IF(ISNUMBER(SEARCH("UPI",Account_Data[[#This Row],[Details]])),"UPI Expense",IF(ISNUMBER(SEARCH("W TFR",Account_Data[[#This Row],[Details]])),"Transfer","Other"))))))))) -> UPI Expense | I23: =Account_Data[[#This Row],[Credit]]-Account_Data[[#This Row],[Debit]] -> -260 | J23: =EOMONTH(Account_Data[[#This Row],[Date]],0) -> 45777 | K23: =ABS(Account_Data[[#This Row],[Amount]]) -> 260
A24: 45758 | B24: W TFR UPI/DR//DHIRENDR/SBIN//P aym AT | C24: 350 | E24: 18065.47 | F24: =TEXT(Account_Data[[#This Row],[Date]],"mmm-yyyy") -> Apr-2025 | G24: =IF(Account_Data[[#This Row],[Credit]]>0,"Income","Expense") -> Expense | H24: =IF(AND(Account_Data[[#This Row],[Credit]]>0,ISNUMBER(SEARCH("TFR",Account_Data[[#This Row],[Details]])),Account_Data[[#This Row],[Credit]]>=200000),"Loan Taken", IF(AND(Account_Data[[#This Row],[Debit]]>0,OR(ISNUMBER(SEARCH("ETMONEY",Account_Data[[#This Row],[Details]])),ISNUMBER(SEARCH("PGIM",Account_Data[[#This Row],[Details]])),ISNUMBER(SEARCH("CANARA",Account_Data[[#This Row],[Details]])))),"Investment (Outflow)", IF(AND(Account_Data[[#This Row],[Credit]]>0,OR(ISNUMBER(SEARCH("PGIM",Account_Data[[#This Row],[Details]])),ISNUMBER(SEARCH("CANARA",Account_Data[[#This Row],[Details]])),ISNUMBER(SEARCH("MUTUAL",Account_Data[[#This Row],[Details]])))),"Investment Return", IF(OR(ISNUMBER(SEARCH("LOAN",Account_Data[[#This Row],[Details]])),ISNUMBER(SEARCH("RECOVERY",Account_Data[[#This Row],[Details]]))),"Loan Payment", IF(OR(ISNUMBER(SEARCH("SALARY",Account_Data[[#This Row],[Details]])),ISNUMBER(SEARCH("EMPLOYER DEP",Account_Data[[#This Row],[Details]]))),"Income", IF(OR(ISNUMBER(SEARCH("ACH",Account_Data[[#This Row],[Details]])),ISNUMBER(SEARCH("DIRECT DR",Account_Data[[#This Row],[Details]]))),"EMI", IF(ISNUMBER(SEARCH("ATM",Account_Data[[#This Row],[Details]])),"Cash", IF(ISNUMBER(SEARCH("UPI",Account_Data[[#This Row],[Details]])),"UPI Expense",IF(ISNUMBER(SEARCH("W TFR",Account_Data[[#This Row],[Details]])),"Transfer","Other"))))))))) -> UPI Expense | I24: =Account_Data[[#This Row],[Credit]]-Account_Data[[#This Row],[Debit]] -> -350 | J24: =EOMONTH(Account_Data[[#This Row],[Date]],0) -> 45777 | K24: =ABS(Account_Data[[#This Row],[Amount]]) -> 350
A25: 45759 | B25: W TFR UPI/DR//PANKAJ K/SBIN/pankajmish/ PAY AT | C25: 500 | E25: 17565.47 | F25: =TEXT(Account_Data[[#This Row],[Date]],"mmm-yyyy") -> Apr-2025 | G25: =IF(Account_Data[[#This Row],[Credit]]>0,"Income","Expense") -> Expense | H25: =IF(AND(Account_Data[[#This Row],[Credit]]>0,ISNUMBER(SEARCH("TFR",Account_Data[[#This Row],[Details]])),Account_Data[[#This Row],[Credit]]>=200000),"Loan Taken", IF(AND(Account_Data[[#This Row],[Debit]]>0,OR(ISNUMBER(SEARCH("ETMONEY",Account_Data[[#This Row],[Details]])),ISNUMBER(SEARCH("PGIM",Account_Data[[#This Row],[Details]])),ISNUMBER(SEARCH("CANARA",Account_Data[[#This Row],[Details]])))),"Investment (Outflow)", IF(AND(Account_Data[[#This Row],[Credit]]>0,OR(ISNUMBER(SEARCH("PGIM",Account_Data[[#This Row],[Details]])),ISNUMBER(SEARCH("CANARA",Account_Data[[#This Row],[Details]])),ISNUMBER(SEARCH("MUTUAL",Account_Data[[#This Row],[Details]])))),"Investment Return", IF(OR(ISNUMBER(SEARCH("LOAN",Account_Data[[#This Row],[Details]])),ISNUMBER(SEARCH("RECOVERY",Account_Data[[#This Row],[Details]]))),"Loan Payment", IF(OR(ISNUMBER(SEARCH("SALARY",Account_Data[[#This Row],[Details]])),ISNUMBER(SEARCH("EMPLOYER DEP",Account_Data[[#This Row],[Details]]))),"Income", IF(OR(ISNUMBER(SEARCH("ACH",Account_Data[[#This Row],[Details]])),ISNUMBER(SEARCH("DIRECT DR",Account_Data[[#This Row],[Details]]))),"EMI", IF(ISNUMBER(SEARCH("ATM",Account_Data[[#This Row],[Details]])),"Cash", IF(ISNUMBER(SEARCH("UPI",Account_Data[[#This Row],[Details]])),"UPI Expense",IF(ISNUMBER(SEARCH("W TFR",Account_Data[[#This Row],[Details]])),"Transfer","Other"))))))))) -> UPI Expense | I25: =Account_Data[[#This Row],[Credit]]-Account_Data[[#This Row],[Debit]] -> -500 | J25: =EOMONTH(Account_Data[[#This Row],[Date]],0) -> 45777 | K25: =ABS(Account_Data[[#This Row],[Amount]]) -> 500
A26: 45759 | B26: W TFR UPI/DR//AFJALANS/YESB/Q/P aym AT | C26: 5 | E26: 17560.47 | F26: =TEXT(Account_Data[[#This Row],[Date]],"mmm-yyyy") -> Apr-2025 | G26: =IF(Account_Data[[#This Row],[Credit]]>0,"Income","Expense") -> Expense | H26: =IF(AND(Account_Data[[#This Row],[Credit]]>0,ISNUMBER(SEARCH("TFR",Account_Data[[#This Row],[Details]])),Account_Data[[#This Row],[Credit]]>=200000),"Loan Taken", IF(AND(Account_Data[[#This Row],[Debit]]>0,OR(ISNUMBER(SEARCH("ETMONEY",Account_Data[[#This Row],[Details]])),ISNUMBER(SEARCH("PGIM",Account_Data[[#This Row],[Details]])),ISNUMBER(SEARCH("CANARA",Account_Data[[#This Row],[Details]])))),"Investment (Outflow)", IF(AND(Account_Data[[#This Row],[Credit]]>0,OR(ISNUMBER(SEARCH("PGIM",Account_Data[[#This Row],[Details]])),ISNUMBER(SEARCH("CANARA",Account_Data[[#This Row],[Details]])),ISNUMBER(SEARCH("MUTUAL",Account_Data[[#This Row],[Details]])))),"Investment Return", IF(OR(ISNUMBER(SEARCH("LOAN",Account_Data[[#This Row],[Details]])),ISNUMBER(SEARCH("RECOVERY",Account_Data[[#This Row],[Details]]))),"Loan Payment", IF(OR(ISNUMBER(SEARCH("SALARY",Account_Data[[#This Row],[Details]])),ISNUMBER(SEARCH("EMPLOYER DEP",Account_Data[[#This Row],[Details]]))),"Income", IF(OR(ISNUMBER(SEARCH("ACH",Account_Data[[#This Row],[Details]])),ISNUMBER(SEARCH("DIRECT DR",Account_Data[[#This Row],[Details]]))),"EMI", IF(ISNUMBER(SEARCH("ATM",Account_Data[[#This Row],[Details]])),"Cash", IF(ISNUMBER(SEARCH("UPI",Account_Data[[#This Row],[Details]])),"UPI Expense",IF(ISNUMBER(SEARCH("W TFR",Account_Data[[#This Row],[Details]])),"Transfer","Other"))))))))) -> UPI Expense | I26: =Account_Data[[#This Row],[Credit]]-Account_Data[[#This Row],[Debit]] -> -5 | J26: =EOMONTH(Account_Data[[#This Row],[Date]],0) -> 45777 | K26: =ABS(Account_Data[[#This Row],[Amount]]) -> 5
A27: 45760 | B27: W TFR UPI/DR//NALIN SI/DBSS/nalinbisen/ PAY AT | C27: 424 | E27: 17136.47 | F27: =TEXT(Account_Data[[#This Row],[Date]],"mmm-yyyy") -> Apr-2025 | G27: =IF(Account_Data[[#This Row],[Credit]]>0,"Income","Expense") -> Expense | H27: =IF(AND(Account_Data[[#This Row],[Credit]]>0,ISNUMBER(SEARCH("TFR",Account_Data[[#This Row],[Details]])),Account_Data[[#This Row],[Credit]]>=200000),"Loan Taken", IF(AND(Account_Data[[#This Row],[Debit]]>0,OR(ISNUMBER(SEARCH("ETMONEY",Account_Data[[#This Row],[Details]])),ISNUMBER(SEARCH("PGIM",Account_Data[[#This Row],[Details]])),ISNUMBER(SEARCH("CANARA",Account_Data[[#This Row],[Details]])))),"Investment (Outflow)", IF(AND(Account_Data[[#This Row],[Credit]]>0,OR(ISNUMBER(SEARCH("PGIM",Account_Data[[#This Row],[Details]])),ISNUMBER(SEARCH("CANARA",Account_Data[[#This Row],[Details]])),ISNUMBER(SEARCH("MUTUAL",Account_Data[[#This Row],[Details]])))),"Investment Return", IF(OR(ISNUMBER(SEARCH("LOAN",Account_Data[[#This Row],[Details]])),ISNUMBER(SEARCH("RECOVERY",Account_Data[[#This Row],[Details]]))),"Loan Payment", IF(OR(ISNUMBER(SEARCH("SALARY",Account_Data[[#This Row],[Details]])),ISNUMBER(SEARCH("EMPLOYER DEP",Account_Data[[#This Row],[Details]]))),"Income", IF(OR(ISNUMBER(SEARCH("ACH",Account_Data[[#This Row],[Details]])),ISNUMBER(SEARCH("DIRECT DR",Account_Data[[#This Row],[Details]]))),"EMI", IF(ISNUMBER(SEARCH("ATM",Account_Data[[#This Row],[Details]])),"Cash", IF(ISNUMBER(SEARCH("UPI",Account_Data[[#This Row],[Details]])),"UPI Expense",IF(ISNUMBER(SEARCH("W TFR",Account_Data[[#This Row],[Details]])),"Transfer","Other"))))))))) -> UPI Expense | I27: =Account_Data[[#This Row],[Credit]]-Account_Data[[#This Row],[Debit]] -> -424 | J27: =EOMONTH(Account_Data[[#This Row],[Date]],0) -> 45777 | K27: =ABS(Account_Data[[#This Row],[Amount]]) -> 424
A28: 45760 | B28: W TFR UPI/DR//KESHAVA /YESB/paytmqr/P aym AT | C28: 2000 | E28: 15136.47 | F28: =TEXT(Account_Data[[#This Row],[Date]],"mmm-yyyy") -> Apr-2025 | G28: =IF(Account_Data[[#This Row],[Credit]]>0,"Income","Expense") -> Expense | H28: =IF(AND(Account_Data[[#This Row],[Credit]]>0,ISNUMBER(SEARCH("TFR",Account_Data[[#This Row],[Details]])),Account_Data[[#This Row],[Credit]]>=200000),"Loan Taken", IF(AND(Account_Data[[#This Row],[Debit]]>0,OR(ISNUMBER(SEARCH("ETMONEY",Account_Data[[#This Row],[Details]])),ISNUMBER(SEARCH("PGIM",Account_Data[[#This Row],[Details]])),ISNUMBER(SEARCH("CANARA",Account_Data[[#This Row],[Details]])))),"Investment (Outflow)", IF(AND(Account_Data[[#This Row],[Credit]]>0,OR(ISNUMBER(SEARCH("PGIM",Account_Data[[#This Row],[Details]])),ISNUMBER(SEARCH("CANARA",Account_Data[[#This Row],[Details]])),ISNUMBER(SEARCH("MUTUAL",Account_Data[[#This Row],[Details]])))),"Investment Return", IF(OR(ISNUMBER(SEARCH("LOAN",Account_Data[[#This Row],[Details]])),ISNUMBER(SEARCH("RECOVERY",Account_Data[[#This Row],[Details]]))),"Loan Payment", IF(OR(ISNUMBER(SEARCH("SALARY",Account_Data[[#This Row],[Details]])),ISNUMBER(SEARCH("EMPLOYER DEP",Account_Data[[#This Row],[Details]]))),"Income", IF(OR(ISNUMBER(SEARCH("ACH",Account_Data[[#This Row],[Details]])),ISNUMBER(SEARCH("DIRECT DR",Account_Data[[#This Row],[Details]]))),"EMI", IF(ISNUMBER(SEARCH("ATM",Account_Data[[#This Row],[Details]])),"Cash", IF(ISNUMBER(SEARCH("UPI",Account_Data[[#This Row],[Details]])),"UPI Expense",IF(ISNUMBER(SEARCH("W TFR",Account_Data[[#This Row],[Details]])),"Transfer","Other"))))))))) -> UPI Expense | I28: =Account_Data[[#This Row],[Credit]]-Account_Data[[#This Row],[Debit]] -> -2000 | J28: =EOMONTH(Account_Data[[#This Row],[Date]],0) -> 45777 | K28: =ABS(Account_Data[[#This Row],[Amount]]) -> 2000
A29: 45760 | B29: W TFR UPI/DR//Apex hea/UTIB/gpay-/P aym AT | C29: 400 | E29: 14736.47 | F29: =TEXT(Account_Data[[#This Row],[Date]],"mmm-yyyy") -> Apr-2025 | G29: =IF(Account_Data[[#This Row],[Credit]]>0,"Income","Expense") -> Expense | H29: =IF(AND(Account_Data[[#This Row],[Credit]]>0,ISNUMBER(SEARCH("TFR",Account_Data[[#This Row],[Details]])),Account_Data[[#This Row],[Credit]]>=200000),"Loan Taken", IF(AND(Account_Data[[#This Row],[Debit]]>0,OR(ISNUMBER(SEARCH("ETMONEY",Account_Data[[#This Row],[Details]])),ISNUMBER(SEARCH("PGIM",Account_Data[[#This Row],[Details]])),ISNUMBER(SEARCH("CANARA",Account_Data[[#This Row],[Details]])))),"Investment (Outflow)", IF(AND(Account_Data[[#This Row],[Credit]]>0,OR(ISNUMBER(SEARCH("PGIM",Account_Data[[#This Row],[Details]])),ISNUMBER(SEARCH("CANARA",Account_Data[[#This Row],[Details]])),ISNUMBER(SEARCH("MUTUAL",Account_Data[[#This Row],[Details]])))),"Investment Return", IF(OR(ISNUMBER(SEARCH("LOAN",Account_Data[[#This Row],[Details]])),ISNUMBER(SEARCH("RECOVERY",Account_Data[[#This Row],[Details]]))),"Loan Payment", IF(OR(ISNUMBER(SEARCH("SALARY",Account_Data[[#This Row],[Details]])),ISNUMBER(SEARCH("EMPLOYER DEP",Account_Data[[#This Row],[Details]]))),"Income", IF(OR(ISNUMBER(SEARCH("ACH",Account_Data[[#This Row],[Details]])),ISNUMBER(SEARCH("DIRECT DR",Account_Data[[#This Row],[Details]]))),"EMI", IF(ISNUMBER(SEARCH("ATM",Account_Data[[#This Row],[Details]])),"Cash", IF(ISNUMBER(SEARCH("UPI",Account_Data[[#This Row],[Details]])),"UPI Expense",IF(ISNUMBER(SEARCH("W TFR",Account_Data[[#This Row],[Details]])),"Transfer","Other"))))))))) -> UPI Expense | I29: =Account_Data[[#This Row],[Credit]]-Account_Data[[#This Row],[Debit]] -> -400 | J29: =EOMONTH(Account_Data[[#This Row],[Date]],0) -> 45777 | K29: =ABS(Account_Data[[#This Row],[Amount]]) -> 400
A30: 45760 | B30: W TFR UPI/DR//Apex hea/UTIB/gpay-/P aym AT | C30: 252 | E30: 14484.47 | F30: =TEXT(Account_Data[[#This Row],[Date]],"mmm-yyyy") -> Apr-2025 | G30: =IF(Account_Data[[#This Row],[Credit]]>0,"Income","Expense") -> Expense | H30: =IF(AND(Account_Data[[#This Row],[Credit]]>0,ISNUMBER(SEARCH("TFR",Account_Data[[#This Row],[Details]])),Account_Data[[#This Row],[Credit]]>=200000),"Loan Taken", IF(AND(Account_Data[[#This Row],[Debit]]>0,OR(ISNUMBER(SEARCH("ETMONEY",Account_Data[[#This Row],[Details]])),ISNUMBER(SEARCH("PGIM",Account_Data[[#This Row],[Details]])),ISNUMBER(SEARCH("CANARA",Account_Data[[#This Row],[Details]])))),"Investment (Outflow)", IF(AND(Account_Data[[#This Row],[Credit]]>0,OR(ISNUMBER(SEARCH("PGIM",Account_Data[[#This Row],[Details]])),ISNUMBER(SEARCH("CANARA",Account_Data[[#This Row],[Details]])),ISNUMBER(SEARCH("MUTUAL",Account_Data[[#This Row],[Details]])))),"Investment Return", IF(OR(ISNUMBER(SEARCH("LOAN",Account_Data[[#This Row],[Details]])),ISNUMBER(SEARCH("RECOVERY",Account_Data[[#This Row],[Details]]))),"Loan Payment", IF(OR(ISNUMBER(SEARCH("SALARY",Account_Data[[#This Row],[Details]])),ISNUMBER(SEARCH("EMPLOYER DEP",Account_Data[[#This Row],[Details]]))),"Income", IF(OR(ISNUMBER(SEARCH("ACH",Account_Data[[#This Row],[Details]])),ISNUMBER(SEARCH("DIRECT DR",Account_Data[[#This Row],[Details]]))),"EMI", IF(ISNUMBER(SEARCH("ATM",Account_Data[[#This Row],[Details]])),"Cash", IF(ISNUMBER(SEARCH("UPI",Account_Data[[#This Row],[Details]])),"UPI Expense",IF(ISNUMBER(SEARCH("W TFR",Account_Data[[#This Row],[Details]])),"Transfer","Other"))))))))) -> UPI Expense | I30: =Account_Data[[#This Row],[Credit]]-Account_Data[[#This Row],[Debit]] -> -252 | J30: =EOMONTH(Account_Data[[#This Row],[Date]],0) -> 45777 | K30: =ABS(Account_Data[[#This Row],[Amount]]) -> 252
A31: 45761 | B31: ATM W ATM CASH ATM SADAR PRATAPGARH | C31: 7000 | E31: 7484.47 | F31: =TEXT(Account_Data[[#This Row],[Date]],"mmm-yyyy") -> Apr-2025 | G31: =IF(Account_Data[[#This Row],[Credit]]>0,"Income","Expense") -> Expense | H31: =IF(AND(Account_Data[[#This Row],[Credit]]>0,ISNUMBER(SEARCH("TFR",Account_Data[[#This Row],[Details]])),Account_Data[[#This Row],[Credit]]>=200000),"Loan Taken", IF(AND(Account_Data[[#This Row],[Debit]]>0,OR(ISNUMBER(SEARCH("ETMONEY",Account_Data[[#This Row],[Details]])),ISNUMBER(SEARCH("PGIM",Account_Data[[#This Row],[Details]])),ISNUMBER(SEARCH("CANARA",Account_Data[[#This Row],[Details]])))),"Investment (Outflow)", IF(AND(Account_Data[[#This Row],[Credit]]>0,OR(ISNUMBER(SEARCH("PGIM",Account_Data[[#This Row],[Details]])),ISNUMBER(SEARCH("CANARA",Account_Data[[#This Row],[Details]])),ISNUMBER(SEARCH("MUTUAL",Account_Data[[#This Row],[Details]])))),"Investment Return", IF(OR(ISNUMBER(SEARCH("LOAN",Account_Data[[#This Row],[Details]])),ISNUMBER(SEARCH("RECOVERY",Account_Data[[#This Row],[Details]]))),"Loan Payment", IF(OR(ISNUMBER(SEARCH("SALARY",Account_Data[[#This Row],[Details]])),ISNUMBER(SEARCH("EMPLOYER DEP",Account_Data[[#This Row],[Details]]))),"Income", IF(OR(ISNUMBER(SEARCH("ACH",Account_Data[[#This Row],[Details]])),ISNUMBER(SEARCH("DIRECT DR",Account_Data[[#This Row],[Details]]))),"EMI", IF(ISNUMBER(SEARCH("ATM",Account_Data[[#This Row],[Details]])),"Cash", IF(ISNUMBER(SEARCH("UPI",Account_Data[[#This Row],[Details]])),"UPI Expense",IF(ISNUMBER(SEARCH("W TFR",Account_Data[[#This Row],[Details]])),"Transfer","Other"))))))))) -> Cash | I31: =Account_Data[[#This Row],[Credit]]-Account_Data[[#This Row],[Debit]] -> -7000 | J31: =EOMONTH(Account_Data[[#This Row],[Date]],0) -> 45777 | K31: =ABS(Account_Data[[#This Row],[Amount]]) -> 7000
A32: 45761 | B32: W TFR UPI/DR//PRAKASH /YESB/paytmqrr/P aym AT | C32: 851 | E32: 6633.47 | F32: =TEXT(Account_Data[[#This Row],[Date]],"mmm-yyyy") -> Apr-2025 | G32: =IF(Account_Data[[#This Row],[Credit]]>0,"Income","Expense") -> Expense | H32: =IF(AND(Account_Data[[#This Row],[Credit]]>0,ISNUMBER(SEARCH("TFR",Account_Data[[#This Row],[Details]])),Account_Data[[#This Row],[Credit]]>=200000),"Loan Taken", IF(AND(Account_Data[[#This Row],[Debit]]>0,OR(ISNUMBER(SEARCH("ETMONEY",Account_Data[[#This Row],[Details]])),ISNUMBER(SEARCH("PGIM",Account_Data[[#This Row],[Details]])),ISNUMBER(SEARCH("CANARA",Account_Data[[#This Row],[Details]])))),"Investment (Outflow)", IF(AND(Account_Data[[#This Row],[Credit]]>0,OR(ISNUMBER(SEARCH("PGIM",Account_Data[[#This Row],[Details]])),ISNUMBER(SEARCH("CANARA",Account_Data[[#This Row],[Details]])),ISNUMBER(SEARCH("MUTUAL",Account_Data[[#This Row],[Details]])))),"Investment Return", IF(OR(ISNUMBER(SEARCH("LOAN",Account_Data[[#This Row],[Details]])),ISNUMBER(SEARCH("RECOVERY",Account_Data[[#This Row],[Details]]))),"Loan Payment", IF(OR(ISNUMBER(SEARCH("SALARY",Account_Data[[#This Row],[Details]])),ISNUMBER(SEARCH("EMPLOYER DEP",Account_Data[[#This Row],[Details]]))),"Income", IF(OR(ISNUMBER(SEARCH("ACH",Account_Data[[#This Row],[Details]])),ISNUMBER(SEARCH("DIRECT DR",Account_Data[[#This Row],[Details]]))),"EMI", IF(ISNUMBER(SEARCH("ATM",Account_Data[[#This Row],[Details]])),"Cash", IF(ISNUMBER(SEARCH("UPI",Account_Data[[#This Row],[Details]])),"UPI Expense",IF(ISNUMBER(SEARCH("W TFR",Account_Data[[#This Row],[Details]])),"Transfer","Other"))))))))) -> UPI Expense | I32: =Account_Data[[#This Row],[Credit]]-Account_Data[[#This Row],[Debit]] -> -851 | J32: =EOMONTH(Account_Data[[#This Row],[Date]],0) -> 45777 | K32: =ABS(Account_Data[[#This Row],[Amount]]) -> 851
A33: 45761 | B33: W TFR UPI/DR//SHABANA /UBIN/asgark/P aym AT | C33: 1000 | E33: 5633.47 | F33: =TEXT(Account_Data[[#This Row],[Date]],"mmm-yyyy") -> Apr-2025 | G33: =IF(Account_Data[[#This Row],[Credit]]>0,"Income","Expense") -> Expense | H33: =IF(AND(Account_Data[[#This Row],[Credit]]>0,ISNUMBER(SEARCH("TFR",Account_Data[[#This Row],[Details]])),Account_Data[[#This Row],[Credit]]>=200000),"Loan Taken", IF(AND(Account_Data[[#This Row],[Debit]]>0,OR(ISNUMBER(SEARCH("ETMONEY",Account_Data[[#This Row],[Details]])),ISNUMBER(SEARCH("PGIM",Account_Data[[#This Row],[Details]])),ISNUMBER(SEARCH("CANARA",Account_Data[[#This Row],[Details]])))),"Investment (Outflow)", IF(AND(Account_Data[[#This Row],[Credit]]>0,OR(ISNUMBER(SEARCH("PGIM",Account_Data[[#This Row],[Details]])),ISNUMBER(SEARCH("CANARA",Account_Data[[#This Row],[Details]])),ISNUMBER(SEARCH("MUTUAL",Account_Data[[#This Row],[Details]])))),"Investment Return", IF(OR(ISNUMBER(SEARCH("LOAN",Account_Data[[#This Row],[Details]])),ISNUMBER(SEARCH("RECOVERY",Account_Data[[#This Row],[Details]]))),"Loan Payment", IF(OR(ISNUMBER(SEARCH("SALARY",Account_Data[[#This Row],[Details]])),ISNUMBER(SEARCH("EMPLOYER DEP",Account_Data[[#This Row],[Details]]))),"Income", IF(OR(ISNUMBER(SEARCH("ACH",Account_Data[[#This Row],[Details]])),ISNUMBER(SEARCH("DIRECT DR",Account_Data[[#This Row],[Details]]))),"EMI", IF(ISNUMBER(SEARCH("ATM",Account_Data[[#This Row],[Details]])),"Cash", IF(ISNUMBER(SEARCH("UPI",Account_Data[[#This Row],[Details]])),"UPI Expense",IF(ISNUMBER(SEARCH("W TFR",Account_Data[[#This Row],[Details]])),"Transfer","Other"))))))))) -> UPI Expense | I33: =Account_Data[[#This Row],[Credit]]-Account_Data[[#This Row],[Debit]] -> -1000 | J33: =EOMONTH(Account_Data[[#This Row],[Date]],0) -> 45777 | K33: =ABS(Account_Data[[#This Row],[Amount]]) -> 1000
... A37: 45763 | B37: W TFR UPI/DR//dotpe/UTIB/dotpe.payu/Orde rId AT | C37: 480 | E37: 3403.47 | F37: =TEXT(Account_Data[[#This Row],[Date]],"mmm-yyyy") -> Apr-2025 | G37: =IF(Account_Data[[#This Row],[Credit]]>0,"Income","Expense") -> Expense | H37: =IF(AND(Account_Data[[#This Row],[Credit]]>0,ISNUMBER(SEARCH("TFR",Account_Data[[#This Row],[Details]])),Account_Data[[#This Row],[Credit]]>=200000),"Loan Taken", IF(AND(Account_Data[[#This Row],[Debit]]>0,OR(ISNUMBER(SEARCH("ETMONEY",Account_Data[[#This Row],[Details]])),ISNUMBER(SEARCH("PGIM",Account_Data[[#This Row],[Details]])),ISNUMBER(SEARCH("CANARA",Account_Data[[#This Row],[Details]])))),"Investment (Outflow)", IF(AND(Account_Data[[#This Row],[Credit]]>0,OR(ISNUMBER(SEARCH("PGIM",Account_Data[[#This Row],[Details]])),ISNUMBER(SEARCH("CANARA",Account_Data[[#This Row],[Details]])),ISNUMBER(SEARCH("MUTUAL",Account_Data[[#This Row],[Details]])))),"Investment Return", IF(OR(ISNUMBER(SEARCH("LOAN",Account_Data[[#This Row],[Details]])),ISNUMBER(SEARCH("RECOVERY",Account_Data[[#This Row],[Details]]))),"Loan Payment", IF(OR(ISNUMBER(SEARCH("SALARY",Account_Data[[#This Row],[Details]])),ISNUMBER(SEARCH("EMPLOYER DEP",Account_Data[[#This Row],[Details]]))),"Income", IF(OR(ISNUMBER(SEARCH("ACH",Account_Data[[#This Row],[Details]])),ISNUMBER(SEARCH("DIRECT DR",Account_Data[[#This Row],[Details]]))),"EMI", IF(ISNUMBER(SEARCH("ATM",Account_Data[[#This Row],[Details]])),"Cash", IF(ISNUMBER(SEARCH("UPI",Account_Data[[#This Row],[Details]])),"UPI Expense",IF(ISNUMBER(SEARCH("W TFR",Account_Data[[#This Row],[Details]])),"Transfer","Other"))))))))) -> UPI Expense | I37: =Account_Data[[#This Row],[Credit]]-Account_Data[[#This Row],[Debit]] -> -480 | J37: =EOMONTH(Account_Data[[#This Row],[Date]],0) -> 45777 | K37: =ABS(Account_Data[[#This Row],[Amount]]) -> 480
A38: 45764 | B38: DEP TFR UPI/CR//dotpe/UTIB/dotpe.payu/payU Ref AT | D38: 480 | E38: 3883.47 | F38: =TEXT(Account_Data[[#This Row],[Date]],"mmm-yyyy") -> Apr-2025 | G38: =IF(Account_Data[[#This Row],[Credit]]>0,"Income","Expense") -> Income | H38: =IF(AND(Account_Data[[#This Row],[Credit]]>0,ISNUMBER(SEARCH("TFR",Account_Data[[#This Row],[Details]])),Account_Data[[#This Row],[Credit]]>=200000),"Loan Taken", IF(AND(Account_Data[[#This Row],[Debit]]>0,OR(ISNUMBER(SEARCH("ETMONEY",Account_Data[[#This Row],[Details]])),ISNUMBER(SEARCH("PGIM",Account_Data[[#This Row],[Details]])),ISNUMBER(SEARCH("CANARA",Account_Data[[#This Row],[Details]])))),"Investment (Outflow)", IF(AND(Account_Data[[#This Row],[Credit]]>0,OR(ISNUMBER(SEARCH("PGIM",Account_Data[[#This Row],[Details]])),ISNUMBER(SEARCH("CANARA",Account_Data[[#This Row],[Details]])),ISNUMBER(SEARCH("MUTUAL",Account_Data[[#This Row],[Details]])))),"Investment Return", IF(OR(ISNUMBER(SEARCH("LOAN",Account_Data[[#This Row],[Details]])),ISNUMBER(SEARCH("RECOVERY",Account_Data[[#This Row],[Details]]))),"Loan Payment", IF(OR(ISNUMBER(SEARCH("SALARY",Account_Data[[#This Row],[Details]])),ISNUMBER(SEARCH("EMPLOYER DEP",Account_Data[[#This Row],[Details]]))),"Income", IF(OR(ISNUMBER(SEARCH("ACH",Account_Data[[#This Row],[Details]])),ISNUMBER(SEARCH("DIRECT DR",Account_Data[[#This Row],[Details]]))),"EMI", IF(ISNUMBER(SEARCH("ATM",Account_Data[[#This Row],[Details]])),"Cash", IF(ISNUMBER(SEARCH("UPI",Account_Data[[#This Row],[Details]])),"UPI Expense",IF(ISNUMBER(SEARCH("W TFR",Account_Data[[#This Row],[Details]])),"Transfer","Other"))))))))) -> UPI Expense | I38: =Account_Data[[#This Row],[Credit]]-Account_Data[[#This Row],[Debit]] -> 480 | J38: =EOMONTH(Account_Data[[#This Row],[Date]],0) -> 45777 | K38: =ABS(Account_Data[[#This Row],[Amount]]) -> 480
A39: 45764 | B39: W TFR UPI/DR//AMAZON S/HDFC/amazonsell/P aym AT | C39: 857 | E39: 3026.47 | F39: =TEXT(Account_Data[[#This Row],[Date]],"mmm-yyyy") -> Apr-2025 | G39: =IF(Account_Data[[#This Row],[Credit]]>0,"Income","Expense") -> Expense | H39: =IF(AND(Account_Data[[#This Row],[Credit]]>0,ISNUMBER(SEARCH("TFR",Account_Data[[#This Row],[Details]])),Account_Data[[#This Row],[Credit]]>=200000),"Loan Taken", IF(AND(Account_Data[[#This Row],[Debit]]>0,OR(ISNUMBER(SEARCH("ETMONEY",Account_Data[[#This Row],[Details]])),ISNUMBER(SEARCH("PGIM",Account_Data[[#This Row],[Details]])),ISNUMBER(SEARCH("CANARA",Account_Data[[#This Row],[Details]])))),"Investment (Outflow)", IF(AND(Account_Data[[#This Row],[Credit]]>0,OR(ISNUMBER(SEARCH("PGIM",Account_Data[[#This Row],[Details]])),ISNUMBER(SEARCH("CANARA",Account_Data[[#This Row],[Details]])),ISNUMBER(SEARCH("MUTUAL",Account_Data[[#This Row],[Details]])))),"Investment Return", IF(OR(ISNUMBER(SEARCH("LOAN",Account_Data[[#This Row],[Details]])),ISNUMBER(SEARCH("RECOVERY",Account_Data[[#This Row],[Details]]))),"Loan Payment", IF(OR(ISNUMBER(SEARCH("SALARY",Account_Data[[#This Row],[Details]])),ISNUMBER(SEARCH("EMPLOYER DEP",Account_Data[[#This Row],[Details]]))),"Income", IF(OR(ISNUMBER(SEARCH("ACH",Account_Data[[#This Row],[Details]])),ISNUMBER(SEARCH("DIRECT DR",Account_Data[[#This Row],[Details]]))),"EMI", IF(ISNUMBER(SEARCH("ATM",Account_Data[[#This Row],[Details]])),"Cash", IF(ISNUMBER(SEARCH("UPI",Account_Data[[#This Row],[Details]])),"UPI Expense",IF(ISNUMBER(SEARCH("W TFR",Account_Data[[#This Row],[Details]])),"Transfer","Other"))))))))) -> UPI Expense | I39: =Account_Data[[#This Row],[Credit]]-Account_Data[[#This Row],[Debit]] -> -857 | J39: =EOMONTH(Account_Data[[#This Row],[Date]],0) -> 45777 | K39: =ABS(Account_Data[[#This Row],[Amount]]) -> 857
A40: 45764 | B40: W TFR UPI/DR//Blinkit/YESB/paytm-blin/Bl ink AT | C40: 124 | E40: 2902.47 | F40: =TEXT(Account_Data[[#This Row],[Date]],"mmm-yyyy") -> Apr-2025 | G40: =IF(Account_Data[[#This Row],[Credit]]>0,"Income","Expense") -> Expense | H40: =IF(AND(Account_Data[[#This Row],[Credit]]>0,ISNUMBER(SEARCH("TFR",Account_Data[[#This Row],[Details]])),Account_Data[[#This Row],[Credit]]>=200000),"Loan Taken", IF(AND(Account_Data[[#This Row],[Debit]]>0,OR(ISNUMBER(SEARCH("ETMONEY",Account_Data[[#This Row],[Details]])),ISNUMBER(SEARCH("PGIM",Account_Data[[#This Row],[Details]])),ISNUMBER(SEARCH("CANARA",Account_Data[[#This Row],[Details]])))),"Investment (Outflow)", IF(AND(Account_Data[[#This Row],[Credit]]>0,OR(ISNUMBER(SEARCH("PGIM",Account_Data[[#This Row],[Details]])),ISNUMBER(SEARCH("CANARA",Account_Data[[#This Row],[Details]])),ISNUMBER(SEARCH("MUTUAL",Account_Data[[#This Row],[Details]])))),"Investment Return", IF(OR(ISNUMBER(SEARCH("LOAN",Account_Data[[#This Row],[Details]])),ISNUMBER(SEARCH("RECOVERY",Account_Data[[#This Row],[Details]]))),"Loan Payment", IF(OR(ISNUMBER(SEARCH("SALARY",Account_Data[[#This Row],[Details]])),ISNUMBER(SEARCH("EMPLOYER DEP",Account_Data[[#This Row],[Details]]))),"Income", IF(OR(ISNUMBER(SEARCH("ACH",Account_Data[[#This Row],[Details]])),ISNUMBER(SEARCH("DIRECT DR",Account_Data[[#This Row],[Details]]))),"EMI", IF(ISNUMBER(SEARCH("ATM",Account_Data[[#This Row],[Details]])),"Cash", IF(ISNUMBER(SEARCH("UPI",Account_Data[[#This Row],[Details]])),"UPI Expense",IF(ISNUMBER(SEARCH("W TFR",Account_Data[[#This Row],[Details]])),"Transfer","Other"))))))))) -> UPI Expense | I40: =Account_Data[[#This Row],[Credit]]-Account_Data[[#This Row],[Debit]] -> -124 | J40: =EOMONTH(Account_Data[[#This Row],[Date]],0) -> 45777 | K40: =ABS(Account_Data[[#This Row],[Amount]]) -> 124
A41: 45765 | B41: W TFR UPI/DR//ZOMATO/HDFC/payzomato@/Col lec AT | C41: 229.44 | E41: 2673.03 | F41: =TEXT(Account_Data[[#This Row],[Date]],"mmm-yyyy") -> Apr-2025 | G41: =IF(Account_Data[[#This Row],[Credit]]>0,"Income","Expense") -> Expense | H41: =IF(AND(Account_Data[[#This Row],[Credit]]>0,ISNUMBER(SEARCH("TFR",Account_Data[[#This Row],[Details]])),Account_Data[[#This Row],[Credit]]>=200000),"Loan Taken", IF(AND(Account_Data[[#This Row],[Debit]]>0,OR(ISNUMBER(SEARCH("ETMONEY",Account_Data[[#This Row],[Details]])),ISNUMBER(SEARCH("PGIM",Account_Data[[#This Row],[Details]])),ISNUMBER(SEARCH("CANARA",Account_Data[[#This Row],[Details]])))),"Investment (Outflow)", IF(AND(Account_Data[[#This Row],[Credit]]>0,OR(ISNUMBER(SEARCH("PGIM",Account_Data[[#This Row],[Details]])),ISNUMBER(SEARCH("CANARA",Account_Data[[#This Row],[Details]])),ISNUMBER(SEARCH("MUTUAL",Account_Data[[#This Row],[Details]])))),"Investment Return", IF(OR(ISNUMBER(SEARCH("LOAN",Account_Data[[#This Row],[Details]])),ISNUMBER(SEARCH("RECOVERY",Account_Data[[#This Row],[Details]]))),"Loan Payment", IF(OR(ISNUMBER(SEARCH("SALARY",Account_Data[[#This Row],[Details]])),ISNUMBER(SEARCH("EMPLOYER DEP",Account_Data[[#This Row],[Details]]))),"Income", IF(OR(ISNUMBER(SEARCH("ACH",Account_Data[[#This Row],[Details]])),ISNUMBER(SEARCH("DIRECT DR",Account_Data[[#This Row],[Details]]))),"EMI", IF(ISNUMBER(SEARCH("ATM",Account_Data[[#This Row],[Details]])),"Cash", IF(ISNUMBER(SEARCH("UPI",Account_Data[[#This Row],[Details]])),"UPI Expense",IF(ISNUMBER(SEARCH("W TFR",Account_Data[[#This Row],[Details]])),"Transfer","Other"))))))))) -> UPI Expense | I41: =Account_Data[[#This Row],[Credit]]-Account_Data[[#This Row],[Debit]] -> -229.44 | J41: =EOMONTH(Account_Data[[#This Row],[Date]],0) -> 45777 | K41: =ABS(Account_Data[[#This Row],[Amount]]) -> 229.44
A42: 45767 | B42: W TFR UPI/DR//JITENDRA/UBIN//P aym AT | C42: 400 | E42: 2273.03 | F42: =TEXT(Account_Data[[#This Row],[Date]],"mmm-yyyy") -> Apr-2025 | G42: =IF(Account_Data[[#This Row],[Credit]]>0,"Income","Expense") -> Expense | H42: =IF(AND(Account_Data[[#This Row],[Credit]]>0,ISNUMBER(SEARCH("TFR",Account_Data[[#This Row],[Details]])),Account_Data[[#This Row],[Credit]]>=200000),"Loan Taken", IF(AND(Account_Data[[#This Row],[Debit]]>0,OR(ISNUMBER(SEARCH("ETMONEY",Account_Data[[#This Row],[Details]])),ISNUMBER(SEARCH("PGIM",Account_Data[[#This Row],[Details]])),ISNUMBER(SEARCH("CANARA",Account_Data[[#This Row],[Details]])))),"Investment (Outflow)", IF(AND(Account_Data[[#This Row],[Credit]]>0,OR(ISNUMBER(SEARCH("PGIM",Account_Data[[#This Row],[Details]])),ISNUMBER(SEARCH("CANARA",Account_Data[[#This Row],[Details]])),ISNUMBER(SEARCH("MUTUAL",Account_Data[[#This Row],[Details]])))),"Investment Return", IF(OR(ISNUMBER(SEARCH("LOAN",Account_Data[[#This Row],[Details]])),ISNUMBER(SEARCH("RECOVERY",Account_Data[[#This Row],[Details]]))),"Loan Payment", IF(OR(ISNUMBER(SEARCH("SALARY",Account_Data[[#This Row],[Details]])),ISNUMBER(SEARCH("EMPLOYER DEP",Account_Data[[#This Row],[Details]]))),"Income", IF(OR(ISNUMBER(SEARCH("ACH",Account_Data[[#This Row],[Details]])),ISNUMBER(SEARCH("DIRECT DR",Account_Data[[#This Row],[Details]]))),"EMI", IF(ISNUMBER(SEARCH("ATM",Account_Data[[#This Row],[Details]])),"Cash", IF(ISNUMBER(SEARCH("UPI",Account_Data[[#This Row],[Details]])),"UPI Expense",IF(ISNUMBER(SEARCH("W TFR",Account_Data[[#This Row],[Details]])),"Transfer","Other"))))))))) -> UPI Expense | I42: =Account_Data[[#This Row],[Credit]]-Account_Data[[#This Row],[Debit]] -> -400 | J42: =EOMONTH(Account_Data[[#This Row],[Date]],0) -> 45777 | K42: =ABS(Account_Data[[#This Row],[Amount]]) -> 400
A43: 45767 | B43: W TFR UPI/DR//IRCTC Ra/UTIB/IRCTCRAILW/P aym AT | C43: 450 | E43: 1823.03 | F43: =TEXT(Account_Data[[#This Row],[Date]],"mmm-yyyy") -> Apr-2025 | G43: =IF(Account_Data[[#This Row],[Credit]]>0,"Income","Expense") -> Expense | H43: =IF(AND(Account_Data[[#This Row],[Credit]]>0,ISNUMBER(SEARCH("TFR",Account_Data[[#This Row],[Details]])),Account_Data[[#This Row],[Credit]]>=200000),"Loan Taken", IF(AND(Account_Data[[#This Row],[Debit]]>0,OR(ISNUMBER(SEARCH("ETMONEY",Account_Data[[#This Row],[Details]])),ISNUMBER(SEARCH("PGIM",Account_Data[[#This Row],[Details]])),ISNUMBER(SEARCH("CANARA",Account_Data[[#This Row],[Details]])))),"Investment (Outflow)", IF(AND(Account_Data[[#This Row],[Credit]]>0,OR(ISNUMBER(SEARCH("PGIM",Account_Data[[#This Row],[Details]])),ISNUMBER(SEARCH("CANARA",Account_Data[[#This Row],[Details]])),ISNUMBER(SEARCH("MUTUAL",Account_Data[[#This Row],[Details]])))),"Investment Return", IF(OR(ISNUMBER(SEARCH("LOAN",Account_Data[[#This Row],[Details]])),ISNUMBER(SEARCH("RECOVERY",Account_Data[[#This Row],[Details]]))),"Loan Payment", IF(OR(ISNUMBER(SEARCH("SALARY",Account_Data[[#This Row],[Details]])),ISNUMBER(SEARCH("EMPLOYER DEP",Account_Data[[#This Row],[Details]]))),"Income", IF(OR(ISNUMBER(SEARCH("ACH",Account_Data[[#This Row],[Details]])),ISNUMBER(SEARCH("DIRECT DR",Account_Data[[#This Row],[Details]]))),"EMI", IF(ISNUMBER(SEARCH("ATM",Account_Data[[#This Row],[Details]])),"Cash", IF(ISNUMBER(SEARCH("UPI",Account_Data[[#This Row],[Details]])),"UPI Expense",IF(ISNUMBER(SEARCH("W TFR",Account_Data[[#This Row],[Details]])),"Transfer","Other"))))))))) -> UPI Expense | I43: =Account_Data[[#This Row],[Credit]]-Account_Data[[#This Row],[Debit]] -> -450 | J43: =EOMONTH(Account_Data[[#This Row],[Date]],0) -> 45777 | K43: =ABS(Account_Data[[#This Row],[Amount]]) -> 450
A44: 45767 | B44: W TFR UPI/DR//IRCTC Ra/UTIB/IRCTCRAILW/P aym AT | C44: 415 | E44: 1408.03 | F44: =TEXT(Account_Data[[#This Row],[Date]],"mmm-yyyy") -> Apr-2025 | G44: =IF(Account_Data[[#This Row],[Credit]]>0,"Income","Expense") -> Expense | H44: =IF(AND(Account_Data[[#This Row],[Credit]]>0,ISNUMBER(SEARCH("TFR",Account_Data[[#This Row],[Details]])),Account_Data[[#This Row],[Credit]]>=200000),"Loan Taken", IF(AND(Account_Data[[#This Row],[Debit]]>0,OR(ISNUMBER(SEARCH("ETMONEY",Account_Data[[#This Row],[Details]])),ISNUMBER(SEARCH("PGIM",Account_Data[[#This Row],[Details]])),ISNUMBER(SEARCH("CANARA",Account_Data[[#This Row],[Details]])))),"Investment (Outflow)", IF(AND(Account_Data[[#This Row],[Credit]]>0,OR(ISNUMBER(SEARCH("PGIM",Account_Data[[#This Row],[Details]])),ISNUMBER(SEARCH("CANARA",Account_Data[[#This Row],[Details]])),ISNUMBER(SEARCH("MUTUAL",Account_Data[[#This Row],[Details]])))),"Investment Return", IF(OR(ISNUMBER(SEARCH("LOAN",Account_Data[[#This Row],[Details]])),ISNUMBER(SEARCH("RECOVERY",Account_Data[[#This Row],[Details]]))),"Loan Payment", IF(OR(ISNUMBER(SEARCH("SALARY",Account_Data[[#This Row],[Details]])),ISNUMBER(SEARCH("EMPLOYER DEP",Account_Data[[#This Row],[Details]]))),"Income", IF(OR(ISNUMBER(SEARCH("ACH",Account_Data[[#This Row],[Details]])),ISNUMBER(SEARCH("DIRECT DR",Account_Data[[#This Row],[Details]]))),"EMI", IF(ISNUMBER(SEARCH("ATM",Account_Data[[#This Row],[Details]])),"Cash", IF(ISNUMBER(SEARCH("UPI",Account_Data[[#This Row],[Details]])),"UPI Expense",IF(ISNUMBER(SEARCH("W TFR",Account_Data[[#This Row],[Details]])),"Transfer","Other"))))))))) -> UPI Expense | I44: =Account_Data[[#This Row],[Credit]]-Account_Data[[#This Row],[Debit]] -> -415 | J44: =EOMONTH(Account_Data[[#This Row],[Date]],0) -> 45777 | K44: =ABS(Account_Data[[#This Row],[Amount]]) -> 415
A45: 45770 | B45: W TFR LEGAL FEE OF Mr. UDAI PRATAP ABC AT | C45: 1000 | E45: 408.03 | F45: =TEXT(Account_Data[[#This Row],[Date]],"mmm-yyyy") -> Apr-2025 | G45: =IF(Account_Data[[#This Row],[Credit]]>0,"Income","Expense") -> Expense | H45: =IF(AND(Account_Data[[#This Row],[Credit]]>0,ISNUMBER(SEARCH("TFR",Account_Data[[#This Row],[Details]])),Account_Data[[#This Row],[Credit]]>=200000),"Loan Taken", IF(AND(Account_Data[[#This Row],[Debit]]>0,OR(ISNUMBER(SEARCH("ETMONEY",Account_Data[[#This Row],[Details]])),ISNUMBER(SEARCH("PGIM",Account_Data[[#This Row],[Details]])),ISNUMBER(SEARCH("CANARA",Account_Data[[#This Row],[Details]])))),"Investment (Outflow)", IF(AND(Account_Data[[#This Row],[Credit]]>0,OR(ISNUMBER(SEARCH("PGIM",Account_Data[[#This Row],[Details]])),ISNUMBER(SEARCH("CANARA",Account_Data[[#This Row],[Details]])),ISNUMBER(SEARCH("MUTUAL",Account_Data[[#This Row],[Details]])))),"Investment Return", IF(OR(ISNUMBER(SEARCH("LOAN",Account_Data[[#This Row],[Details]])),ISNUMBER(SEARCH("RECOVERY",Account_Data[[#This Row],[Details]]))),"Loan Payment", IF(OR(ISNUMBER(SEARCH("SALARY",Account_Data[[#This Row],[Details]])),ISNUMBER(SEARCH("EMPLOYER DEP",Account_Data[[#This Row],[Details]]))),"Income", IF(OR(ISNUMBER(SEARCH("ACH",Account_Data[[#This Row],[Details]])),ISNUMBER(SEARCH("DIRECT DR",Account_Data[[#This Row],[Details]]))),"EMI", IF(ISNUMBER(SEARCH("ATM",Account_Data[[#This Row],[Details]])),"Cash", IF(ISNUMBER(SEARCH("UPI",Account_Data[[#This Row],[Details]])),"UPI Expense",IF(ISNUMBER(SEARCH("W TFR",Account_Data[[#This Row],[Details]])),"Transfer","Other"))))))))) -> Transfer | I45: =Account_Data[[#This Row],[Credit]]-Account_Data[[#This Row],[Debit]] -> -1000 | J45: =EOMONTH(Account_Data[[#This Row],[Date]],0) -> 45777 | K45: =ABS(Account_Data[[#This Row],[Amount]]) -> 1000
A46: 45770 | B46: W TFR UPI/DR//Monalisa/YESB/paytmqrkn/P aym AT | C46: 280 | E46: 128.03 | F46: =TEXT(Account_Data[[#This Row],[Date]],"mmm-yyyy") -> Apr-2025 | G46: =IF(Account_Data[[#This Row],[Credit]]>0,"Income","Expense") -> Expense | H46: =IF(AND(Account_Data[[#This Row],[Credit]]>0,ISNUMBER(SEARCH("TFR",Account_Data[[#This Row],[Details]])),Account_Data[[#This Row],[Credit]]>=200000),"Loan Taken", IF(AND(Account_Data[[#This Row],[Debit]]>0,OR(ISNUMBER(SEARCH("ETMONEY",Account_Data[[#This Row],[Details]])),ISNUMBER(SEARCH("PGIM",Account_Data[[#This Row],[Details]])),ISNUMBER(SEARCH("CANARA",Account_Data[[#This Row],[Details]])))),"Investment (Outflow)", IF(AND(Account_Data[[#This Row],[Credit]]>0,OR(ISNUMBER(SEARCH("PGIM",Account_Data[[#This Row],[Details]])),ISNUMBER(SEARCH("CANARA",Account_Data[[#This Row],[Details]])),ISNUMBER(SEARCH("MUTUAL",Account_Data[[#This Row],[Details]])))),"Investment Return", IF(OR(ISNUMBER(SEARCH("LOAN",Account_Data[[#This Row],[Details]])),ISNUMBER(SEARCH("RECOVERY",Account_Data[[#This Row],[Details]]))),"Loan Payment", IF(OR(ISNUMBER(SEARCH("SALARY",Account_Data[[#This Row],[Details]])),ISNUMBER(SEARCH("EMPLOYER DEP",Account_Data[[#This Row],[Details]]))),"Income", IF(OR(ISNUMBER(SEARCH("ACH",Account_Data[[#This Row],[Details]])),ISNUMBER(SEARCH("DIRECT DR",Account_Data[[#This Row],[Details]]))),"EMI", IF(ISNUMBER(SEARCH("ATM",Account_Data[[#This Row],[Details]])),"Cash", IF(ISNUMBER(SEARCH("UPI",Account_Data[[#This Row],[Details]])),"UPI Expense",IF(ISNUMBER(SEARCH("W TFR",Account_Data[[#This Row],[Details]])),"Transfer","Other"))))))))) -> UPI Expense | I46: =Account_Data[[#This Row],[Credit]]-Account_Data[[#This Row],[Debit]] -> -280 | J46: =EOMONTH(Account_Data[[#This Row],[Date]],0) -> 45777 | K46: =ABS(Account_Data[[#This Row],[Amount]]) -> 280
A47: 45775 | B47: DEP TFR NEFT*CITI*CITIN*FRANKLIN TEM PLE AT | D47: 12800 | E47: 12928.03 | F47: =TEXT(Account_Data[[#This Row],[Date]],"mmm-yyyy") -> Apr-2025 | G47: =IF(Account_Data[[#This Row],[Credit]]>0,"Income","Expense") -> Income | H47: =IF(AND(Account_Data[[#This Row],[Credit]]>0,ISNUMBER(SEARCH("TFR",Account_Data[[#This Row],[Details]])),Account_Data[[#This Row],[Credit]]>=200000),"Loan Taken", IF(AND(Account_Data[[#This Row],[Debit]]>0,OR(ISNUMBER(SEARCH("ETMONEY",Account_Data[[#This Row],[Details]])),ISNUMBER(SEARCH("PGIM",Account_Data[[#This Row],[Details]])),ISNUMBER(SEARCH("CANARA",Account_Data[[#This Row],[Details]])))),"Investment (Outflow)", IF(AND(Account_Data[[#This Row],[Credit]]>0,OR(ISNUMBER(SEARCH("PGIM",Account_Data[[#This Row],[Details]])),ISNUMBER(SEARCH("CANARA",Account_Data[[#This Row],[Details]])),ISNUMBER(SEARCH("MUTUAL",Account_Data[[#This Row],[Details]])))),"Investment Return", IF(OR(ISNUMBER(SEARCH("LOAN",Account_Data[[#This Row],[Details]])),ISNUMBER(SEARCH("RECOVERY",Account_Data[[#This Row],[Details]]))),"Loan Payment", IF(OR(ISNUMBER(SEARCH("SALARY",Account_Data[[#This Row],[Details]])),ISNUMBER(SEARCH("EMPLOYER DEP",Account_Data[[#This Row],[Details]]))),"Income", IF(OR(ISNUMBER(SEARCH("ACH",Account_Data[[#This Row],[Details]])),ISNUMBER(SEARCH("DIRECT DR",Account_Data[[#This Row],[Details]]))),"EMI", IF(ISNUMBER(SEARCH("ATM",Account_Data[[#This Row],[Details]])),"Cash", IF(ISNUMBER(SEARCH("UPI",Account_Data[[#This Row],[Details]])),"UPI Expense",IF(ISNUMBER(SEARCH("W TFR",Account_Data[[#This Row],[Details]])),"Transfer","Other"))))))))) -> Other | I47: =Account_Data[[#This Row],[Credit]]-Account_Data[[#This Row],[Debit]] -> 12800 | J47: =EOMONTH(Account_Data[[#This Row],[Date]],0) -> 45777 | K47: =ABS(Account_Data[[#This Row],[Amount]]) -> 12800
A48: 45775 | B48: DEP TFR NEFT*HDFC*HDFCH*BAJAJ FLEXI CAP AT | D48: 44000 | E48: 56928.03 | F48: =TEXT(Account_Data[[#This Row],[Date]],"mmm-yyyy") -> Apr-2025 | G48: =IF(Account_Data[[#This Row],[Credit]]>0,"Income","Expense") -> Income | H48: =IF(AND(Account_Data[[#This Row],[Credit]]>0,ISNUMBER(SEARCH("TFR",Account_Data[[#This Row],[Details]])),Account_Data[[#This Row],[Credit]]>=200000),"Loan Taken", IF(AND(Account_Data[[#This Row],[Debit]]>0,OR(ISNUMBER(SEARCH("ETMONEY",Account_Data[[#This Row],[Details]])),ISNUMBER(SEARCH("PGIM",Account_Data[[#This Row],[Details]])),ISNUMBER(SEARCH("CANARA",Account_Data[[#This Row],[Details]])))),"Investment (Outflow)", IF(AND(Account_Data[[#This Row],[Credit]]>0,OR(ISNUMBER(SEARCH("PGIM",Account_Data[[#This Row],[Details]])),ISNUMBER(SEARCH("CANARA",Account_Data[[#This Row],[Details]])),ISNUMBER(SEARCH("MUTUAL",Account_Data[[#This Row],[Details]])))),"Investment Return", IF(OR(ISNUMBER(SEARCH("LOAN",Account_Data[[#This Row],[Details]])),ISNUMBER(SEARCH("RECOVERY",Account_Data[[#This Row],[Details]]))),"Loan Payment", IF(OR(ISNUMBER(SEARCH("SALARY",Account_Data[[#This Row],[Details]])),ISNUMBER(SEARCH("EMPLOYER DEP",Account_Data[[#This Row],[Details]]))),"Income", IF(OR(ISNUMBER(SEARCH("ACH",Account_Data[[#This Row],[Details]])),ISNUMBER(SEARCH("DIRECT DR",Account_Data[[#This Row],[Details]]))),"EMI", IF(ISNUMBER(SEARCH("ATM",Account_Data[[#This Row],[Details]])),"Cash", IF(ISNUMBER(SEARCH("UPI",Account_Data[[#This Row],[Details]])),"UPI Expense",IF(ISNUMBER(SEARCH("W TFR",Account_Data[[#This Row],[Details]])),"Transfer","Other"))))))))) -> Other | I48: =Account_Data[[#This Row],[Credit]]-Account_Data[[#This Row],[Debit]] -> 44000 | J48: =EOMONTH(Account_Data[[#This Row],[Date]],0) -> 45777 | K48: =ABS(Account_Data[[#This Row],[Amount]]) -> 44000
A49: 45775 | B49: DEBIT CMP MANDATE D EBIT AXIS Mutual FUND | C49: 1000 | E49: 55928.03 | F49: =TEXT(Account_Data[[#This Row],[Date]],"mmm-yyyy") -> Apr-2025 | G49: =IF(Account_Data[[#This Row],[Credit]]>0,"Income","Expense") -> Expense | H49: =IF(AND(Account_Data[[#This Row],[Credit]]>0,ISNUMBER(SEARCH("TFR",Account_Data[[#This Row],[Details]])),Account_Data[[#This Row],[Credit]]>=200000),"Loan Taken", IF(AND(Account_Data[[#This Row],[Debit]]>0,OR(ISNUMBER(SEARCH("ETMONEY",Account_Data[[#This Row],[Details]])),ISNUMBER(SEARCH("PGIM",Account_Data[[#This Row],[Details]])),ISNUMBER(SEARCH("CANARA",Account_Data[[#This Row],[Details]])))),"Investment (Outflow)", IF(AND(Account_Data[[#This Row],[Credit]]>0,OR(ISNUMBER(SEARCH("PGIM",Account_Data[[#This Row],[Details]])),ISNUMBER(SEARCH("CANARA",Account_Data[[#This Row],[Details]])),ISNUMBER(SEARCH("MUTUAL",Account_Data[[#This Row],[Details]])))),"Investment Return", IF(OR(ISNUMBER(SEARCH("LOAN",Account_Data[[#This Row],[Details]])),ISNUMBER(SEARCH("RECOVERY",Account_Data[[#This Row],[Details]]))),"Loan Payment", IF(OR(ISNUMBER(SEARCH("SALARY",Account_Data[[#This Row],[Details]])),ISNUMBER(SEARCH("EMPLOYER DEP",Account_Data[[#This Row],[Details]]))),"Income", IF(OR(ISNUMBER(SEARCH("ACH",Account_Data[[#This Row],[Details]])),ISNUMBER(SEARCH("DIRECT DR",Account_Data[[#This Row],[Details]]))),"EMI", IF(ISNUMBER(SEARCH("ATM",Account_Data[[#This Row],[Details]])),"Cash", IF(ISNUMBER(SEARCH("UPI",Account_Data[[#This Row],[Details]])),"UPI Expense",IF(ISNUMBER(SEARCH("W TFR",Account_Data[[#This Row],[Details]])),"Transfer","Other"))))))))) -> Other | I49: =Account_Data[[#This Row],[Credit]]-Account_Data[[#This Row],[Debit]] -> -1000 | J49: =EOMONTH(Account_Data[[#This Row],[Date]],0) -> 45777 | K49: =ABS(Account_Data[[#This Row],[Amount]]) -> 1000
A50: 45775 | B50: EMPLOYER DEP Sa lary of Apr | D50: 122872 | E50: 178800.03 | F50: =TEXT(Account_Data[[#This Row],[Date]],"mmm-yyyy") -> Apr-2025 | G50: =IF(Account_Data[[#This Row],[Credit]]>0,"Income","Expense") -> Income | H50: =IF(AND(Account_Data[[#This Row],[Credit]]>0,ISNUMBER(SEARCH("TFR",Account_Data[[#This Row],[Details]])),Account_Data[[#This Row],[Credit]]>=200000),"Loan Taken", IF(AND(Account_Data[[#This Row],[Debit]]>0,OR(ISNUMBER(SEARCH("ETMONEY",Account_Data[[#This Row],[Details]])),ISNUMBER(SEARCH("PGIM",Account_Data[[#This Row],[Details]])),ISNUMBER(SEARCH("CANARA",Account_Data[[#This Row],[Details]])))),"Investment (Outflow)", IF(AND(Account_Data[[#This Row],[Credit]]>0,OR(ISNUMBER(SEARCH("PGIM",Account_Data[[#This Row],[Details]])),ISNUMBER(SEARCH("CANARA",Account_Data[[#This Row],[Details]])),ISNUMBER(SEARCH("MUTUAL",Account_Data[[#This Row],[Details]])))),"Investment Return", IF(OR(ISNUMBER(SEARCH("LOAN",Account_Data[[#This Row],[Details]])),ISNUMBER(SEARCH("RECOVERY",Account_Data[[#This Row],[Details]]))),"Loan Payment", IF(OR(ISNUMBER(SEARCH("SALARY",Account_Data[[#This Row],[Details]])),ISNUMBER(SEARCH("EMPLOYER DEP",Account_Data[[#This Row],[Details]]))),"Income", IF(OR(ISNUMBER(SEARCH("ACH",Account_Data[[#This Row],[Details]])),ISNUMBER(SEARCH("DIRECT DR",Account_Data[[#This Row],[Details]]))),"EMI", IF(ISNUMBER(SEARCH("ATM",Account_Data[[#This Row],[Details]])),"Cash", IF(ISNUMBER(SEARCH("UPI",Account_Data[[#This Row],[Details]])),"UPI Expense",IF(ISNUMBER(SEARCH("W TFR",Account_Data[[#This Row],[Details]])),"Transfer","Other"))))))))) -> Income | I50: =Account_Data[[#This Row],[Credit]]-Account_Data[[#This Row],[Debit]] -> 122872 | J50: =EOMONTH(Account_Data[[#This Row],[Date]],0) -> 45777 | K50: =ABS(Account_Data[[#This Row],[Amount]]) -> 122872
A51: 45776 | B51: W TFR UPI/DR//BPCL Ufi/YESB/paytmqrh/P aym AT | C51: 500 | E51: 178300.03 | F51: =TEXT(Account_Data[[#This Row],[Date]],"mmm-yyyy") -> Apr-2025 | G51: =IF(Account_Data[[#This Row],[Credit]]>0,"Income","Expense") -> Expense | H51: =IF(AND(Account_Data[[#This Row],[Credit]]>0,ISNUMBER(SEARCH("TFR",Account_Data[[#This Row],[Details]])),Account_Data[[#This Row],[Credit]]>=200000),"Loan Taken", IF(AND(Account_Data[[#This Row],[Debit]]>0,OR(ISNUMBER(SEARCH("ETMONEY",Account_Data[[#This Row],[Details]])),ISNUMBER(SEARCH("PGIM",Account_Data[[#This Row],[Details]])),ISNUMBER(SEARCH("CANARA",Account_Data[[#This Row],[Details]])))),"Investment (Outflow)", IF(AND(Account_Data[[#This Row],[Credit]]>0,OR(ISNUMBER(SEARCH("PGIM",Account_Data[[#This Row],[Details]])),ISNUMBER(SEARCH("CANARA",Account_Data[[#This Row],[Details]])),ISNUMBER(SEARCH("MUTUAL",Account_Data[[#This Row],[Details]])))),"Investment Return", IF(OR(ISNUMBER(SEARCH("LOAN",Account_Data[[#This Row],[Details]])),ISNUMBER(SEARCH("RECOVERY",Account_Data[[#This Row],[Details]]))),"Loan Payment", IF(OR(ISNUMBER(SEARCH("SALARY",Account_Data[[#This Row],[Details]])),ISNUMBER(SEARCH("EMPLOYER DEP",Account_Data[[#This Row],[Details]]))),"Income", IF(OR(ISNUMBER(SEARCH("ACH",Account_Data[[#This Row],[Details]])),ISNUMBER(SEARCH("DIRECT DR",Account_Data[[#This Row],[Details]]))),"EMI", IF(ISNUMBER(SEARCH("ATM",Account_Data[[#This Row],[Details]])),"Cash", IF(ISNUMBER(SEARCH("UPI",Account_Data[[#This Row],[Details]])),"UPI Expense",IF(ISNUMBER(SEARCH("W TFR",Account_Data[[#This Row],[Details]])),"Transfer","Other"))))))))) -> UPI Expense | I51: =Account_Data[[#This Row],[Credit]]-Account_Data[[#This Row],[Debit]] -> -500 | J51: =EOMONTH(Account_Data[[#This Row],[Date]],0) -> 45777 | K51: =ABS(Account_Data[[#This Row],[Amount]]) -> 500
A52: 45776 | B52: W TFR UPI/DR//SEVEN TU/utib/seventurns/ Pay AT | C52: 699 | E52: 177601.03 | F52: =TEXT(Account_Data[[#This Row],[Date]],"mmm-yyyy") -> Apr-2025 | G52: =IF(Account_Data[[#This Row],[Credit]]>0,"Income","Expense") -> Expense | H52: =IF(AND(Account_Data[[#This Row],[Credit]]>0,ISNUMBER(SEARCH("TFR",Account_Data[[#This Row],[Details]])),Account_Data[[#This Row],[Credit]]>=200000),"Loan Taken", IF(AND(Account_Data[[#This Row],[Debit]]>0,OR(ISNUMBER(SEARCH("ETMONEY",Account_Data[[#This Row],[Details]])),ISNUMBER(SEARCH("PGIM",Account_Data[[#This Row],[Details]])),ISNUMBER(SEARCH("CANARA",Account_Data[[#This Row],[Details]])))),"Investment (Outflow)", IF(AND(Account_Data[[#This Row],[Credit]]>0,OR(ISNUMBER(SEARCH("PGIM",Account_Data[[#This Row],[Details]])),ISNUMBER(SEARCH("CANARA",Account_Data[[#This Row],[Details]])),ISNUMBER(SEARCH("MUTUAL",Account_Data[[#This Row],[Details]])))),"Investment Return", IF(OR(ISNUMBER(SEARCH("LOAN",Account_Data[[#This Row],[Details]])),ISNUMBER(SEARCH("RECOVERY",Account_Data[[#This Row],[Details]]))),"Loan Payment", IF(OR(ISNUMBER(SEARCH("SALARY",Account_Data[[#This Row],[Details]])),ISNUMBER(SEARCH("EMPLOYER DEP",Account_Data[[#This Row],[Details]]))),"Income", IF(OR(ISNUMBER(SEARCH("ACH",Account_Data[[#This Row],[Details]])),ISNUMBER(SEARCH("DIRECT DR",Account_Data[[#This Row],[Details]]))),"EMI", IF(ISNUMBER(SEARCH("ATM",Account_Data[[#This Row],[Details]])),"Cash", IF(ISNUMBER(SEARCH("UPI",Account_Data[[#This Row],[Details]])),"UPI Expense",IF(ISNUMBER(SEARCH("W TFR",Account_Data[[#This Row],[Details]])),"Transfer","Other"))))))))) -> UPI Expense | I52: =Account_Data[[#This Row],[Credit]]-Account_Data[[#This Row],[Debit]] -> -699 | J52: =EOMONTH(Account_Data[[#This Row],[Date]],0) -> 45777 | K52: =ABS(Account_Data[[#This Row],[Amount]]) -> 699
A53: 45776 | B53: W TFR UPI/DR//B N S EN/BARB/bnsenglish/V eri AT | C53: 375 | E53: 177226.03 | F53: =TEXT(Account_Data[[#This Row],[Date]],"mmm-yyyy") -> Apr-2025 | G53: =IF(Account_Data[[#This Row],[Credit]]>0,"Income","Expense") -> Expense | H53: =IF(AND(Account_Data[[#This Row],[Credit]]>0,ISNUMBER(SEARCH("TFR",Account_Data[[#This Row],[Details]])),Account_Data[[#This Row],[Credit]]>=200000),"Loan Taken", IF(AND(Account_Data[[#This Row],[Debit]]>0,OR(ISNUMBER(SEARCH("ETMONEY",Account_Data[[#This Row],[Details]])),ISNUMBER(SEARCH("PGIM",Account_Data[[#This Row],[Details]])),ISNUMBER(SEARCH("CANARA",Account_Data[[#This Row],[Details]])))),"Investment (Outflow)", IF(AND(Account_Data[[#This Row],[Credit]]>0,OR(ISNUMBER(SEARCH("PGIM",Account_Data[[#This Row],[Details]])),ISNUMBER(SEARCH("CANARA",Account_Data[[#This Row],[Details]])),ISNUMBER(SEARCH("MUTUAL",Account_Data[[#This Row],[Details]])))),"Investment Return", IF(OR(ISNUMBER(SEARCH("LOAN",Account_Data[[#This Row],[Details]])),ISNUMBER(SEARCH("RECOVERY",Account_Data[[#This Row],[Details]]))),"Loan Payment", IF(OR(ISNUMBER(SEARCH("SALARY",Account_Data[[#This Row],[Details]])),ISNUMBER(SEARCH("EMPLOYER DEP",Account_Data[[#This Row],[Details]]))),"Income", IF(OR(ISNUMBER(SEARCH("ACH",Account_Data[[#This Row],[Details]])),ISNUMBER(SEARCH("DIRECT DR",Account_Data[[#This Row],[Details]]))),"EMI", IF(ISNUMBER(SEARCH("ATM",Account_Data[[#This Row],[Details]])),"Cash", IF(ISNUMBER(SEARCH("UPI",Account_Data[[#This Row],[Details]])),"UPI Expense",IF(ISNUMBER(SEARCH("W TFR",Account_Data[[#This Row],[Details]])),"Transfer","Other"))))))))) -> UPI Expense | I53: =Account_Data[[#This Row],[Credit]]-Account_Data[[#This Row],[Debit]] -> -375 | J53: =EOMONTH(Account_Data[[#This Row],[Date]],0) -> 45777 | K53: =ABS(Account_Data[[#This Row],[Amount]]) -> 375
A54: 45776 | B54: W TFR UPI/DR//ASHWANI /ICIC//P aym AT | C54: 400 | E54: 176826.03 | F54: =TEXT(Account_Data[[#This Row],[Date]],"mmm-yyyy") -> Apr-2025 | G54: =IF(Account_Data[[#This Row],[Credit]]>0,"Income","Expense") -> Expense | H54: =IF(AND(Account_Data[[#This Row],[Credit]]>0,ISNUMBER(SEARCH("TFR",Account_Data[[#This Row],[Details]])),Account_Data[[#This Row],[Credit]]>=200000),"Loan Taken", IF(AND(Account_Data[[#This Row],[Debit]]>0,OR(ISNUMBER(SEARCH("ETMONEY",Account_Data[[#This Row],[Details]])),ISNUMBER(SEARCH("PGIM",Account_Data[[#This Row],[Details]])),ISNUMBER(SEARCH("CANARA",Account_Data[[#This Row],[Details]])))),"Investment (Outflow)", IF(AND(Account_Data[[#This Row],[Credit]]>0,OR(ISNUMBER(SEARCH("PGIM",Account_Data[[#This Row],[Details]])),ISNUMBER(SEARCH("CANARA",Account_Data[[#This Row],[Details]])),ISNUMBER(SEARCH("MUTUAL",Account_Data[[#This Row],[Details]])))),"Investment Return", IF(OR(ISNUMBER(SEARCH("LOAN",Account_Data[[#This Row],[Details]])),ISNUMBER(SEARCH("RECOVERY",Account_Data[[#This Row],[Details]]))),"Loan Payment", IF(OR(ISNUMBER(SEARCH("SALARY",Account_Data[[#This Row],[Details]])),ISNUMBER(SEARCH("EMPLOYER DEP",Account_Data[[#This Row],[Details]]))),"Income", IF(OR(ISNUMBER(SEARCH("ACH",Account_Data[[#This Row],[Details]])),ISNUMBER(SEARCH("DIRECT DR",Account_Data[[#This Row],[Details]]))),"EMI", IF(ISNUMBER(SEARCH("ATM",Account_Data[[#This Row],[Details]])),"Cash", IF(ISNUMBER(SEARCH("UPI",Account_Data[[#This Row],[Details]])),"UPI Expense",IF(ISNUMBER(SEARCH("W TFR",Account_Data[[#This Row],[Details]])),"Transfer","Other"))))))))) -> UPI Expense | I54: =Account_Data[[#This Row],[Credit]]-Account_Data[[#This Row],[Debit]] -> -400 | J54: =EOMONTH(Account_Data[[#This Row],[Date]],0) -> 45777 | K54: =ABS(Account_Data[[#This Row],[Amount]]) -> 400
A55: 45776 | B55: W TFR UPI/DR//Myntra D/UTIB/MYNTRA@axl/P aym AT | C55: 2569 | E55: 174257.03 | F55: =TEXT(Account_Data[[#This Row],[Date]],"mmm-yyyy") -> Apr-2025 | G55: =IF(Account_Data[[#This Row],[Credit]]>0,"Income","Expense") -> Expense | H55: =IF(AND(Account_Data[[#This Row],[Credit]]>0,ISNUMBER(SEARCH("TFR",Account_Data[[#This Row],[Details]])),Account_Data[[#This Row],[Credit]]>=200000),"Loan Taken", IF(AND(Account_Data[[#This Row],[Debit]]>0,OR(ISNUMBER(SEARCH("ETMONEY",Account_Data[[#This Row],[Details]])),ISNUMBER(SEARCH("PGIM",Account_Data[[#This Row],[Details]])),ISNUMBER(SEARCH("CANARA",Account_Data[[#This Row],[Details]])))),"Investment (Outflow)", IF(AND(Account_Data[[#This Row],[Credit]]>0,OR(ISNUMBER(SEARCH("PGIM",Account_Data[[#This Row],[Details]])),ISNUMBER(SEARCH("CANARA",Account_Data[[#This Row],[Details]])),ISNUMBER(SEARCH("MUTUAL",Account_Data[[#This Row],[Details]])))),"Investment Return", IF(OR(ISNUMBER(SEARCH("LOAN",Account_Data[[#This Row],[Details]])),ISNUMBER(SEARCH("RECOVERY",Account_Data[[#This Row],[Details]]))),"Loan Payment", IF(OR(ISNUMBER(SEARCH("SALARY",Account_Data[[#This Row],[Details]])),ISNUMBER(SEARCH("EMPLOYER DEP",Account_Data[[#This Row],[Details]]))),"Income", IF(OR(ISNUMBER(SEARCH("ACH",Account_Data[[#This Row],[Details]])),ISNUMBER(SEARCH("DIRECT DR",Account_Data[[#This Row],[Details]]))),"EMI", IF(ISNUMBER(SEARCH("ATM",Account_Data[[#This Row],[Details]])),"Cash", IF(ISNUMBER(SEARCH("UPI",Account_Data[[#This Row],[Details]])),"UPI Expense",IF(ISNUMBER(SEARCH("W TFR",Account_Data[[#This Row],[Details]])),"Transfer","Other"))))))))) -> UPI Expense | I55: =Account_Data[[#This Row],[Credit]]-Account_Data[[#This Row],[Debit]] -> -2569 | J55: =EOMONTH(Account_Data[[#This Row],[Date]],0) -> 45777 | K55: =ABS(Account_Data[[#This Row],[Amount]]) -> 2569
A56: 45776 | B56: W TFR UPI/DR//Amazon I/RATN/amazon@rap/ You AT | C56: 849 | E56: 173408.03 | F56: =TEXT(Account_Data[[#This Row],[Date]],"mmm-yyyy") -> Apr-2025 | G56: =IF(Account_Data[[#This Row],[Credit]]>0,"Income","Expense") -> Expense | H56: =IF(AND(Account_Data[[#This Row],[Credit]]>0,ISNUMBER(SEARCH("TFR",Account_Data[[#This Row],[Details]])),Account_Data[[#This Row],[Credit]]>=200000),"Loan Taken", IF(AND(Account_Data[[#This Row],[Debit]]>0,OR(ISNUMBER(SEARCH("ETMONEY",Account_Data[[#This Row],[Details]])),ISNUMBER(SEARCH("PGIM",Account_Data[[#This Row],[Details]])),ISNUMBER(SEARCH("CANARA",Account_Data[[#This Row],[Details]])))),"Investment (Outflow)", IF(AND(Account_Data[[#This Row],[Credit]]>0,OR(ISNUMBER(SEARCH("PGIM",Account_Data[[#This Row],[Details]])),ISNUMBER(SEARCH("CANARA",Account_Data[[#This Row],[Details]])),ISNUMBER(SEARCH("MUTUAL",Account_Data[[#This Row],[Details]])))),"Investment Return", IF(OR(ISNUMBER(SEARCH("LOAN",Account_Data[[#This Row],[Details]])),ISNUMBER(SEARCH("RECOVERY",Account_Data[[#This Row],[Details]]))),"Loan Payment", IF(OR(ISNUMBER(SEARCH("SALARY",Account_Data[[#This Row],[Details]])),ISNUMBER(SEARCH("EMPLOYER DEP",Account_Data[[#This Row],[Details]]))),"Income", IF(OR(ISNUMBER(SEARCH("ACH",Account_Data[[#This Row],[Details]])),ISNUMBER(SEARCH("DIRECT DR",Account_Data[[#This Row],[Details]]))),"EMI", IF(ISNUMBER(SEARCH("ATM",Account_Data[[#This Row],[Details]])),"Cash", IF(ISNUMBER(SEARCH("UPI",Account_Data[[#This Row],[Details]])),"UPI Expense",IF(ISNUMBER(SEARCH("W TFR",Account_Data[[#This Row],[Details]])),"Transfer","Other"))))))))) -> UPI Expense | I56: =Account_Data[[#This Row],[Credit]]-Account_Data[[#This Row],[Debit]] -> -849 | J56: =EOMONTH(Account_Data[[#This Row],[Date]],0) -> 45777 | K56: =ABS(Account_Data[[#This Row],[Amount]]) -> 849
A57: 45776 | B57: W TFR UPI/DR//Bank Acc/SBIN//P aym AT | C57: 12000 | E57: 161408.03 | F57: =TEXT(Account_Data[[#This Row],[Date]],"mmm-yyyy") -> Apr-2025 | G57: =IF(Account_Data[[#This Row],[Credit]]>0,"Income","Expense") -> Expense | H57: =IF(AND(Account_Data[[#This Row],[Credit]]>0,ISNUMBER(SEARCH("TFR",Account_Data[[#This Row],[Details]])),Account_Data[[#This Row],[Credit]]>=200000),"Loan Taken", IF(AND(Account_Data[[#This Row],[Debit]]>0,OR(ISNUMBER(SEARCH("ETMONEY",Account_Data[[#This Row],[Details]])),ISNUMBER(SEARCH("PGIM",Account_Data[[#This Row],[Details]])),ISNUMBER(SEARCH("CANARA",Account_Data[[#This Row],[Details]])))),"Investment (Outflow)", IF(AND(Account_Data[[#This Row],[Credit]]>0,OR(ISNUMBER(SEARCH("PGIM",Account_Data[[#This Row],[Details]])),ISNUMBER(SEARCH("CANARA",Account_Data[[#This Row],[Details]])),ISNUMBER(SEARCH("MUTUAL",Account_Data[[#This Row],[Details]])))),"Investment Return", IF(OR(ISNUMBER(SEARCH("LOAN",Account_Data[[#This Row],[Details]])),ISNUMBER(SEARCH("RECOVERY",Account_Data[[#This Row],[Details]]))),"Loan Payment", IF(OR(ISNUMBER(SEARCH("SALARY",Account_Data[[#This Row],[Details]])),ISNUMBER(SEARCH("EMPLOYER DEP",Account_Data[[#This Row],[Details]]))),"Income", IF(OR(ISNUMBER(SEARCH("ACH",Account_Data[[#This Row],[Details]])),ISNUMBER(SEARCH("DIRECT DR",Account_Data[[#This Row],[Details]]))),"EMI", IF(ISNUMBER(SEARCH("ATM",Account_Data[[#This Row],[Details]])),"Cash", IF(ISNUMBER(SEARCH("UPI",Account_Data[[#This Row],[Details]])),"UPI Expense",IF(ISNUMBER(SEARCH("W TFR",Account_Data[[#This Row],[Details]])),"Transfer","Other"))))))))) -> UPI Expense | I57: =Account_Data[[#This Row],[Credit]]-Account_Data[[#This Row],[Debit]] -> -12000 | J57: =EOMONTH(Account_Data[[#This Row],[Date]],0) -> 45777 | K57: =ABS(Account_Data[[#This Row],[Amount]]) -> 12000
A58: 45776 | B58: W TFR TR LOAN AC OF Mr. XYZ ABC AT | C58: 17889 | E58: 143519.03 | F58: =TEXT(Account_Data[[#This Row],[Date]],"mmm-yyyy") -> Apr-2025 | G58: =IF(Account_Data[[#This Row],[Credit]]>0,"Income","Expense") -> Expense | H58: =IF(AND(Account_Data[[#This Row],[Credit]]>0,ISNUMBER(SEARCH("TFR",Account_Data[[#This Row],[Details]])),Account_Data[[#This Row],[Credit]]>=200000),"Loan Taken", IF(AND(Account_Data[[#This Row],[Debit]]>0,OR(ISNUMBER(SEARCH("ETMONEY",Account_Data[[#This Row],[Details]])),ISNUMBER(SEARCH("PGIM",Account_Data[[#This Row],[Details]])),ISNUMBER(SEARCH("CANARA",Account_Data[[#This Row],[Details]])))),"Investment (Outflow)", IF(AND(Account_Data[[#This Row],[Credit]]>0,OR(ISNUMBER(SEARCH("PGIM",Account_Data[[#This Row],[Details]])),ISNUMBER(SEARCH("CANARA",Account_Data[[#This Row],[Details]])),ISNUMBER(SEARCH("MUTUAL",Account_Data[[#This Row],[Details]])))),"Investment Return", IF(OR(ISNUMBER(SEARCH("LOAN",Account_Data[[#This Row],[Details]])),ISNUMBER(SEARCH("RECOVERY",Account_Data[[#This Row],[Details]]))),"Loan Payment", IF(OR(ISNUMBER(SEARCH("SALARY",Account_Data[[#This Row],[Details]])),ISNUMBER(SEARCH("EMPLOYER DEP",Account_Data[[#This Row],[Details]]))),"Income", IF(OR(ISNUMBER(SEARCH("ACH",Account_Data[[#This Row],[Details]])),ISNUMBER(SEARCH("DIRECT DR",Account_Data[[#This Row],[Details]]))),"EMI", IF(ISNUMBER(SEARCH("ATM",Account_Data[[#This Row],[Details]])),"Cash", IF(ISNUMBER(SEARCH("UPI",Account_Data[[#This Row],[Details]])),"UPI Expense",IF(ISNUMBER(SEARCH("W TFR",Account_Data[[#This Row],[Details]])),"Transfer","Other"))))))))) -> Loan Payment | I58: =Account_Data[[#This Row],[Credit]]-Account_Data[[#This Row],[Debit]] -> -17889 | J58: =EOMONTH(Account_Data[[#This Row],[Date]],0) -> 45777 | K58: =ABS(Account_Data[[#This Row],[Amount]]) -> 17889
A59: 45777 | B59: W TFR UPI/DR//Pradeep /BARB/@/P aym AT | C59: 200 | E59: 143319.03 | F59: =TEXT(Account_Data[[#This Row],[Date]],"mmm-yyyy") -> Apr-2025 | G59: =IF(Account_Data[[#This Row],[Credit]]>0,"Income","Expense") -> Expense | H59: =IF(AND(Account_Data[[#This Row],[Credit]]>0,ISNUMBER(SEARCH("TFR",Account_Data[[#This Row],[Details]])),Account_Data[[#This Row],[Credit]]>=200000),"Loan Taken", IF(AND(Account_Data[[#This Row],[Debit]]>0,OR(ISNUMBER(SEARCH("ETMONEY",Account_Data[[#This Row],[Details]])),ISNUMBER(SEARCH("PGIM",Account_Data[[#This Row],[Details]])),ISNUMBER(SEARCH("CANARA",Account_Data[[#This Row],[Details]])))),"Investment (Outflow)", IF(AND(Account_Data[[#This Row],[Credit]]>0,OR(ISNUMBER(SEARCH("PGIM",Account_Data[[#This Row],[Details]])),ISNUMBER(SEARCH("CANARA",Account_Data[[#This Row],[Details]])),ISNUMBER(SEARCH("MUTUAL",Account_Data[[#This Row],[Details]])))),"Investment Return", IF(OR(ISNUMBER(SEARCH("LOAN",Account_Data[[#This Row],[Details]])),ISNUMBER(SEARCH("RECOVERY",Account_Data[[#This Row],[Details]]))),"Loan Payment", IF(OR(ISNUMBER(SEARCH("SALARY",Account_Data[[#This Row],[Details]])),ISNUMBER(SEARCH("EMPLOYER DEP",Account_Data[[#This Row],[Details]]))),"Income", IF(OR(ISNUMBER(SEARCH("ACH",Account_Data[[#This Row],[Details]])),ISNUMBER(SEARCH("DIRECT DR",Account_Data[[#This Row],[Details]]))),"EMI", IF(ISNUMBER(SEARCH("ATM",Account_Data[[#This Row],[Details]])),"Cash", IF(ISNUMBER(SEARCH("UPI",Account_Data[[#This Row],[Details]])),"UPI Expense",IF(ISNUMBER(SEARCH("W TFR",Account_Data[[#This Row],[Details]])),"Transfer","Other"))))))))) -> UPI Expense | I59: =Account_Data[[#This Row],[Credit]]-Account_Data[[#This Row],[Debit]] -> -200 | J59: =EOMONTH(Account_Data[[#This Row],[Date]],0) -> 45777 | K59: =ABS(Account_Data[[#This Row],[Amount]]) -> 200
A60: 45778 | B60: ATM W ATM CASH W | C60: 20000 | E60: 123319.03 | F60: =TEXT(Account_Data[[#This Row],[Date]],"mmm-yyyy") -> May-2025 | G60: =IF(Account_Data[[#This Row],[Credit]]>0,"Income","Expense") -> Expense | H60: =IF(AND(Account_Data[[#This Row],[Credit]]>0,ISNUMBER(SEARCH("TFR",Account_Data[[#This Row],[Details]])),Account_Data[[#This Row],[Credit]]>=200000),"Loan Taken", IF(AND(Account_Data[[#This Row],[Debit]]>0,OR(ISNUMBER(SEARCH("ETMONEY",Account_Data[[#This Row],[Details]])),ISNUMBER(SEARCH("PGIM",Account_Data[[#This Row],[Details]])),ISNUMBER(SEARCH("CANARA",Account_Data[[#This Row],[Details]])))),"Investment (Outflow)", IF(AND(Account_Data[[#This Row],[Credit]]>0,OR(ISNUMBER(SEARCH("PGIM",Account_Data[[#This Row],[Details]])),ISNUMBER(SEARCH("CANARA",Account_Data[[#This Row],[Details]])),ISNUMBER(SEARCH("MUTUAL",Account_Data[[#This Row],[Details]])))),"Investment Return", IF(OR(ISNUMBER(SEARCH("LOAN",Account_Data[[#This Row],[Details]])),ISNUMBER(SEARCH("RECOVERY",Account_Data[[#This Row],[Details]]))),"Loan Payment", IF(OR(ISNUMBER(SEARCH("SALARY",Account_Data[[#This Row],[Details]])),ISNUMBER(SEARCH("EMPLOYER DEP",Account_Data[[#This Row],[Details]]))),"Income", IF(OR(ISNUMBER(SEARCH("ACH",Account_Data[[#This Row],[Details]])),ISNUMBER(SEARCH("DIRECT DR",Account_Data[[#This Row],[Details]]))),"EMI", IF(ISNUMBER(SEARCH("ATM",Account_Data[[#This Row],[Details]])),"Cash", IF(ISNUMBER(SEARCH("UPI",Account_Data[[#This Row],[Details]])),"UPI Expense",IF(ISNUMBER(SEARCH("W TFR",Account_Data[[#This Row],[Details]])),"Transfer","Other"))))))))) -> Cash | I60: =Account_Data[[#This Row],[Credit]]-Account_Data[[#This Row],[Debit]] -> -20000 | J60: =EOMONTH(Account_Data[[#This Row],[Date]],0) -> 45808 | K60: =ABS(Account_Data[[#This Row],[Amount]]) -> 20000
A61: 45778 | B61: REVERSE ATM W | D61: 20000 | E61: 143319.03 | F61: =TEXT(Account_Data[[#This Row],[Date]],"mmm-yyyy") -> May-2025 | G61: =IF(Account_Data[[#This Row],[Credit]]>0,"Income","Expense") -> Income | H61: =IF(AND(Account_Data[[#This Row],[Credit]]>0,ISNUMBER(SEARCH("TFR",Account_Data[[#This Row],[Details]])),Account_Data[[#This Row],[Credit]]>=200000),"Loan Taken", IF(AND(Account_Data[[#This Row],[Debit]]>0,OR(ISNUMBER(SEARCH("ETMONEY",Account_Data[[#This Row],[Details]])),ISNUMBER(SEARCH("PGIM",Account_Data[[#This Row],[Details]])),ISNUMBER(SEARCH("CANARA",Account_Data[[#This Row],[Details]])))),"Investment (Outflow)", IF(AND(Account_Data[[#This Row],[Credit]]>0,OR(ISNUMBER(SEARCH("PGIM",Account_Data[[#This Row],[Details]])),ISNUMBER(SEARCH("CANARA",Account_Data[[#This Row],[Details]])),ISNUMBER(SEARCH("MUTUAL",Account_Data[[#This Row],[Details]])))),"Investment Return", IF(OR(ISNUMBER(SEARCH("LOAN",Account_Data[[#This Row],[Details]])),ISNUMBER(SEARCH("RECOVERY",Account_Data[[#This Row],[Details]]))),"Loan Payment", IF(OR(ISNUMBER(SEARCH("SALARY",Account_Data[[#This Row],[Details]])),ISNUMBER(SEARCH("EMPLOYER DEP",Account_Data[[#This Row],[Details]]))),"Income", IF(OR(ISNUMBER(SEARCH("ACH",Account_Data[[#This Row],[Details]])),ISNUMBER(SEARCH("DIRECT DR",Account_Data[[#This Row],[Details]]))),"EMI", IF(ISNUMBER(SEARCH("ATM",Account_Data[[#This Row],[Details]])),"Cash", IF(ISNUMBER(SEARCH("UPI",Account_Data[[#This Row],[Details]])),"UPI Expense",IF(ISNUMBER(SEARCH("W TFR",Account_Data[[#This Row],[Details]])),"Transfer","Other"))))))))) -> Cash | I61: =Account_Data[[#This Row],[Credit]]-Account_Data[[#This Row],[Debit]] -> 20000 | J61: =EOMONTH(Account_Data[[#This Row],[Date]],0) -> 45808 | K61: =ABS(Account_Data[[#This Row],[Amount]]) -> 20000
A62: 45778 | B62: ATM W ATM CASH W | C62: 10000 | E62: 133319.03 | F62: =TEXT(Account_Data[[#This Row],[Date]],"mmm-yyyy") -> May-2025 | G62: =IF(Account_Data[[#This Row],[Credit]]>0,"Income","Expense") -> Expense | H62: =IF(AND(Account_Data[[#This Row],[Credit]]>0,ISNUMBER(SEARCH("TFR",Account_Data[[#This Row],[Details]])),Account_Data[[#This Row],[Credit]]>=200000),"Loan Taken", IF(AND(Account_Data[[#This Row],[Debit]]>0,OR(ISNUMBER(SEARCH("ETMONEY",Account_Data[[#This Row],[Details]])),ISNUMBER(SEARCH("PGIM",Account_Data[[#This Row],[Details]])),ISNUMBER(SEARCH("CANARA",Account_Data[[#This Row],[Details]])))),"Investment (Outflow)", IF(AND(Account_Data[[#This Row],[Credit]]>0,OR(ISNUMBER(SEARCH("PGIM",Account_Data[[#This Row],[Details]])),ISNUMBER(SEARCH("CANARA",Account_Data[[#This Row],[Details]])),ISNUMBER(SEARCH("MUTUAL",Account_Data[[#This Row],[Details]])))),"Investment Return", IF(OR(ISNUMBER(SEARCH("LOAN",Account_Data[[#This Row],[Details]])),ISNUMBER(SEARCH("RECOVERY",Account_Data[[#This Row],[Details]]))),"Loan Payment", IF(OR(ISNUMBER(SEARCH("SALARY",Account_Data[[#This Row],[Details]])),ISNUMBER(SEARCH("EMPLOYER DEP",Account_Data[[#This Row],[Details]]))),"Income", IF(OR(ISNUMBER(SEARCH("ACH",Account_Data[[#This Row],[Details]])),ISNUMBER(SEARCH("DIRECT DR",Account_Data[[#This Row],[Details]]))),"EMI", IF(ISNUMBER(SEARCH("ATM",Account_Data[[#This Row],[Details]])),"Cash", IF(ISNUMBER(SEARCH("UPI",Account_Data[[#This Row],[Details]])),"UPI Expense",IF(ISNUMBER(SEARCH("W TFR",Account_Data[[#This Row],[Details]])),"Transfer","Other"))))))))) -> Cash | I62: =Account_Data[[#This Row],[Credit]]-Account_Data[[#This Row],[Debit]] -> -10000 | J62: =EOMONTH(Account_Data[[#This Row],[Date]],0) -> 45808 | K62: =ABS(Account_Data[[#This Row],[Amount]]) -> 10000
A63: 45778 | B63: ATM W ATM CASH W | C63: 20000 | E63: 113319.03 | F63: =TEXT(Account_Data[[#This Row],[Date]],"mmm-yyyy") -> May-2025 | G63: =IF(Account_Data[[#This Row],[Credit]]>0,"Income","Expense") -> Expense | H63: =IF(AND(Account_Data[[#This Row],[Credit]]>0,ISNUMBER(SEARCH("TFR",Account_Data[[#This Row],[Details]])),Account_Data[[#This Row],[Credit]]>=200000),"Loan Taken", IF(AND(Account_Data[[#This Row],[Debit]]>0,OR(ISNUMBER(SEARCH("ETMONEY",Account_Data[[#This Row],[Details]])),ISNUMBER(SEARCH("PGIM",Account_Data[[#This Row],[Details]])),ISNUMBER(SEARCH("CANARA",Account_Data[[#This Row],[Details]])))),"Investment (Outflow)", IF(AND(Account_Data[[#This Row],[Credit]]>0,OR(ISNUMBER(SEARCH("PGIM",Account_Data[[#This Row],[Details]])),ISNUMBER(SEARCH("CANARA",Account_Data[[#This Row],[Details]])),ISNUMBER(SEARCH("MUTUAL",Account_Data[[#This Row],[Details]])))),"Investment Return", IF(OR(ISNUMBER(SEARCH("LOAN",Account_Data[[#This Row],[Details]])),ISNUMBER(SEARCH("RECOVERY",Account_Data[[#This Row],[Details]]))),"Loan Payment", IF(OR(ISNUMBER(SEARCH("SALARY",Account_Data[[#This Row],[Details]])),ISNUMBER(SEARCH("EMPLOYER DEP",Account_Data[[#This Row],[Details]]))),"Income", IF(OR(ISNUMBER(SEARCH("ACH",Account_Data[[#This Row],[Details]])),ISNUMBER(SEARCH("DIRECT DR",Account_Data[[#This Row],[Details]]))),"EMI", IF(ISNUMBER(SEARCH("ATM",Account_Data[[#This Row],[Details]])),"Cash", IF(ISNUMBER(SEARCH("UPI",Account_Data[[#This Row],[Details]])),"UPI Expense",IF(ISNUMBER(SEARCH("W TFR",Account_Data[[#This Row],[Details]])),"Transfer","Other"))))))))) -> Cash | I63: =Account_Data[[#This Row],[Credit]]-Account_Data[[#This Row],[Debit]] -> -20000 | J63: =EOMONTH(Account_Data[[#This Row],[Date]],0) -> 45808 | K63: =ABS(Account_Data[[#This Row],[Amount]]) -> 20000
A64: 45778 | B64: W TFR UPI/DR//INDRESH /UTIB/indresht/P aym AT | C64: 150 | E64: 113169.03 | F64: =TEXT(Account_Data[[#This Row],[Date]],"mmm-yyyy") -> May-2025 | G64: =IF(Account_Data[[#This Row],[Credit]]>0,"Income","Expense") -> Expense | H64: =IF(AND(Account_Data[[#This Row],[Credit]]>0,ISNUMBER(SEARCH("TFR",Account_Data[[#This Row],[Details]])),Account_Data[[#This Row],[Credit]]>=200000),"Loan Taken", IF(AND(Account_Data[[#This Row],[Debit]]>0,OR(ISNUMBER(SEARCH("ETMONEY",Account_Data[[#This Row],[Details]])),ISNUMBER(SEARCH("PGIM",Account_Data[[#This Row],[Details]])),ISNUMBER(SEARCH("CANARA",Account_Data[[#This Row],[Details]])))),"Investment (Outflow)", IF(AND(Account_Data[[#This Row],[Credit]]>0,OR(ISNUMBER(SEARCH("PGIM",Account_Data[[#This Row],[Details]])),ISNUMBER(SEARCH("CANARA",Account_Data[[#This Row],[Details]])),ISNUMBER(SEARCH("MUTUAL",Account_Data[[#This Row],[Details]])))),"Investment Return", IF(OR(ISNUMBER(SEARCH("LOAN",Account_Data[[#This Row],[Details]])),ISNUMBER(SEARCH("RECOVERY",Account_Data[[#This Row],[Details]]))),"Loan Payment", IF(OR(ISNUMBER(SEARCH("SALARY",Account_Data[[#This Row],[Details]])),ISNUMBER(SEARCH("EMPLOYER DEP",Account_Data[[#This Row],[Details]]))),"Income", IF(OR(ISNUMBER(SEARCH("ACH",Account_Data[[#This Row],[Details]])),ISNUMBER(SEARCH("DIRECT DR",Account_Data[[#This Row],[Details]]))),"EMI", IF(ISNUMBER(SEARCH("ATM",Account_Data[[#This Row],[Details]])),"Cash", IF(ISNUMBER(SEARCH("UPI",Account_Data[[#This Row],[Details]])),"UPI Expense",IF(ISNUMBER(SEARCH("W TFR",Account_Data[[#This Row],[Details]])),"Transfer","Other"))))))))) -> UPI Expense | I64: =Account_Data[[#This Row],[Credit]]-Account_Data[[#This Row],[Debit]] -> -150 | J64: =EOMONTH(Account_Data[[#This Row],[Date]],0) -> 45808 | K64: =ABS(Account_Data[[#This Row],[Amount]]) -> 150
A65: 45778 | B65: DEBIT SBI CRE DIT CARD PAYMENT | C65: 3991 | E65: 109178.03 | F65: =TEXT(Account_Data[[#This Row],[Date]],"mmm-yyyy") -> May-2025 | G65: =IF(Account_Data[[#This Row],[Credit]]>0,"Income","Expense") -> Expense | H65: =IF(AND(Account_Data[[#This Row],[Credit]]>0,ISNUMBER(SEARCH("TFR",Account_Data[[#This Row],[Details]])),Account_Data[[#This Row],[Credit]]>=200000),"Loan Taken", IF(AND(Account_Data[[#This Row],[Debit]]>0,OR(ISNUMBER(SEARCH("ETMONEY",Account_Data[[#This Row],[Details]])),ISNUMBER(SEARCH("PGIM",Account_Data[[#This Row],[Details]])),ISNUMBER(SEARCH("CANARA",Account_Data[[#This Row],[Details]])))),"Investment (Outflow)", IF(AND(Account_Data[[#This Row],[Credit]]>0,OR(ISNUMBER(SEARCH("PGIM",Account_Data[[#This Row],[Details]])),ISNUMBER(SEARCH("CANARA",Account_Data[[#This Row],[Details]])),ISNUMBER(SEARCH("MUTUAL",Account_Data[[#This Row],[Details]])))),"Investment Return", IF(OR(ISNUMBER(SEARCH("LOAN",Account_Data[[#This Row],[Details]])),ISNUMBER(SEARCH("RECOVERY",Account_Data[[#This Row],[Details]]))),"Loan Payment", IF(OR(ISNUMBER(SEARCH("SALARY",Account_Data[[#This Row],[Details]])),ISNUMBER(SEARCH("EMPLOYER DEP",Account_Data[[#This Row],[Details]]))),"Income", IF(OR(ISNUMBER(SEARCH("ACH",Account_Data[[#This Row],[Details]])),ISNUMBER(SEARCH("DIRECT DR",Account_Data[[#This Row],[Details]]))),"EMI", IF(ISNUMBER(SEARCH("ATM",Account_Data[[#This Row],[Details]])),"Cash", IF(ISNUMBER(SEARCH("UPI",Account_Data[[#This Row],[Details]])),"UPI Expense",IF(ISNUMBER(SEARCH("W TFR",Account_Data[[#This Row],[Details]])),"Transfer","Other"))))))))) -> Other | I65: =Account_Data[[#This Row],[Credit]]-Account_Data[[#This Row],[Debit]] -> -3991 | J65: =EOMONTH(Account_Data[[#This Row],[Date]],0) -> 45808 | K65: =ABS(Account_Data[[#This Row],[Amount]]) -> 3991
A66: 45778 | B66: DEBIT ACHDr NACH ETMONEY | C66: 1000 | E66: 108178.03 | F66: =TEXT(Account_Data[[#This Row],[Date]],"mmm-yyyy") -> May-2025 | G66: =IF(Account_Data[[#This Row],[Credit]]>0,"Income","Expense") -> Expense | H66: =IF(AND(Account_Data[[#This Row],[Credit]]>0,ISNUMBER(SEARCH("TFR",Account_Data[[#This Row],[Details]])),Account_Data[[#This Row],[Credit]]>=200000),"Loan Taken", IF(AND(Account_Data[[#This Row],[Debit]]>0,OR(ISNUMBER(SEARCH("ETMONEY",Account_Data[[#This Row],[Details]])),ISNUMBER(SEARCH("PGIM",Account_Data[[#This Row],[Details]])),ISNUMBER(SEARCH("CANARA",Account_Data[[#This Row],[Details]])))),"Investment (Outflow)", IF(AND(Account_Data[[#This Row],[Credit]]>0,OR(ISNUMBER(SEARCH("PGIM",Account_Data[[#This Row],[Details]])),ISNUMBER(SEARCH("CANARA",Account_Data[[#This Row],[Details]])),ISNUMBER(SEARCH("MUTUAL",Account_Data[[#This Row],[Details]])))),"Investment Return", IF(OR(ISNUMBER(SEARCH("LOAN",Account_Data[[#This Row],[Details]])),ISNUMBER(SEARCH("RECOVERY",Account_Data[[#This Row],[Details]]))),"Loan Payment", IF(OR(ISNUMBER(SEARCH("SALARY",Account_Data[[#This Row],[Details]])),ISNUMBER(SEARCH("EMPLOYER DEP",Account_Data[[#This Row],[Details]]))),"Income", IF(OR(ISNUMBER(SEARCH("ACH",Account_Data[[#This Row],[Details]])),ISNUMBER(SEARCH("DIRECT DR",Account_Data[[#This Row],[Details]]))),"EMI", IF(ISNUMBER(SEARCH("ATM",Account_Data[[#This Row],[Details]])),"Cash", IF(ISNUMBER(SEARCH("UPI",Account_Data[[#This Row],[Details]])),"UPI Expense",IF(ISNUMBER(SEARCH("W TFR",Account_Data[[#This Row],[Details]])),"Transfer","Other"))))))))) -> Investment (Outflow) | I66: =Account_Data[[#This Row],[Credit]]-Account_Data[[#This Row],[Debit]] -> -1000 | J66: =EOMONTH(Account_Data[[#This Row],[Date]],0) -> 45808 | K66: =ABS(Account_Data[[#This Row],[Amount]]) -> 1000
A67: 45779 | B67: DEBIT ACHDr YESB TP ACH INDIANE | C67: 3000 | E67: 105178.03 | F67: =TEXT(Account_Data[[#This Row],[Date]],"mmm-yyyy") -> May-2025 | G67: =IF(Account_Data[[#This Row],[Credit]]>0,"Income","Expense") -> Expense | H67: =IF(AND(Account_Data[[#This Row],[Credit]]>0,ISNUMBER(SEARCH("TFR",Account_Data[[#This Row],[Details]])),Account_Data[[#This Row],[Credit]]>=200000),"Loan Taken", IF(AND(Account_Data[[#This Row],[Debit]]>0,OR(ISNUMBER(SEARCH("ETMONEY",Account_Data[[#This Row],[Details]])),ISNUMBER(SEARCH("PGIM",Account_Data[[#This Row],[Details]])),ISNUMBER(SEARCH("CANARA",Account_Data[[#This Row],[Details]])))),"Investment (Outflow)", IF(AND(Account_Data[[#This Row],[Credit]]>0,OR(ISNUMBER(SEARCH("PGIM",Account_Data[[#This Row],[Details]])),ISNUMBER(SEARCH("CANARA",Account_Data[[#This Row],[Details]])),ISNUMBER(SEARCH("MUTUAL",Account_Data[[#This Row],[Details]])))),"Investment Return", IF(OR(ISNUMBER(SEARCH("LOAN",Account_Data[[#This Row],[Details]])),ISNUMBER(SEARCH("RECOVERY",Account_Data[[#This Row],[Details]]))),"Loan Payment", IF(OR(ISNUMBER(SEARCH("SALARY",Account_Data[[#This Row],[Details]])),ISNUMBER(SEARCH("EMPLOYER DEP",Account_Data[[#This Row],[Details]]))),"Income", IF(OR(ISNUMBER(SEARCH("ACH",Account_Data[[#This Row],[Details]])),ISNUMBER(SEARCH("DIRECT DR",Account_Data[[#This Row],[Details]]))),"EMI", IF(ISNUMBER(SEARCH("ATM",Account_Data[[#This Row],[Details]])),"Cash", IF(ISNUMBER(SEARCH("UPI",Account_Data[[#This Row],[Details]])),"UPI Expense",IF(ISNUMBER(SEARCH("W TFR",Account_Data[[#This Row],[Details]])),"Transfer","Other"))))))))) -> EMI | I67: =Account_Data[[#This Row],[Credit]]-Account_Data[[#This Row],[Debit]] -> -3000 | J67: =EOMONTH(Account_Data[[#This Row],[Date]],0) -> 45808 | K67: =ABS(Account_Data[[#This Row],[Amount]]) -> 3000
A68: 45779 | B68: DEBIT ACHDr YESB TP ACH INDIANE | C68: 2000 | E68: 103178.03 | F68: =TEXT(Account_Data[[#This Row],[Date]],"mmm-yyyy") -> May-2025 | G68: =IF(Account_Data[[#This Row],[Credit]]>0,"Income","Expense") -> Expense | H68: =IF(AND(Account_Data[[#This Row],[Credit]]>0,ISNUMBER(SEARCH("TFR",Account_Data[[#This Row],[Details]])),Account_Data[[#This Row],[Credit]]>=200000),"Loan Taken", IF(AND(Account_Data[[#This Row],[Debit]]>0,OR(ISNUMBER(SEARCH("ETMONEY",Account_Data[[#This Row],[Details]])),ISNUMBER(SEARCH("PGIM",Account_Data[[#This Row],[Details]])),ISNUMBER(SEARCH("CANARA",Account_Data[[#This Row],[Details]])))),"Investment (Outflow)", IF(AND(Account_Data[[#This Row],[Credit]]>0,OR(ISNUMBER(SEARCH("PGIM",Account_Data[[#This Row],[Details]])),ISNUMBER(SEARCH("CANARA",Account_Data[[#This Row],[Details]])),ISNUMBER(SEARCH("MUTUAL",Account_Data[[#This Row],[Details]])))),"Investment Return", IF(OR(ISNUMBER(SEARCH("LOAN",Account_Data[[#This Row],[Details]])),ISNUMBER(SEARCH("RECOVERY",Account_Data[[#This Row],[Details]]))),"Loan Payment", IF(OR(ISNUMBER(SEARCH("SALARY",Account_Data[[#This Row],[Details]])),ISNUMBER(SEARCH("EMPLOYER DEP",Account_Data[[#This Row],[Details]]))),"Income", IF(OR(ISNUMBER(SEARCH("ACH",Account_Data[[#This Row],[Details]])),ISNUMBER(SEARCH("DIRECT DR",Account_Data[[#This Row],[Details]]))),"EMI", IF(ISNUMBER(SEARCH("ATM",Account_Data[[#This Row],[Details]])),"Cash", IF(ISNUMBER(SEARCH("UPI",Account_Data[[#This Row],[Details]])),"UPI Expense",IF(ISNUMBER(SEARCH("W TFR",Account_Data[[#This Row],[Details]])),"Transfer","Other"))))))))) -> EMI | I68: =Account_Data[[#This Row],[Credit]]-Account_Data[[#This Row],[Debit]] -> -2000 | J68: =EOMONTH(Account_Data[[#This Row],[Date]],0) -> 45808 | K68: =ABS(Account_Data[[#This Row],[Amount]]) -> 2000
A69: 45779 | B69: DEBIT ACHDr YESB TP ACH INDIANE | C69: 2000 | E69: 101178.03 | F69: =TEXT(Account_Data[[#This Row],[Date]],"mmm-yyyy") -> May-2025 | G69: =IF(Account_Data[[#This Row],[Credit]]>0,"Income","Expense") -> Expense | H69: =IF(AND(Account_Data[[#This Row],[Credit]]>0,ISNUMBER(SEARCH("TFR",Account_Data[[#This Row],[Details]])),Account_Data[[#This Row],[Credit]]>=200000),"Loan Taken", IF(AND(Account_Data[[#This Row],[Debit]]>0,OR(ISNUMBER(SEARCH("ETMONEY",Account_Data[[#This Row],[Details]])),ISNUMBER(SEARCH("PGIM",Account_Data[[#This Row],[Details]])),ISNUMBER(SEARCH("CANARA",Account_Data[[#This Row],[Details]])))),"Investment (Outflow)", IF(AND(Account_Data[[#This Row],[Credit]]>0,OR(ISNUMBER(SEARCH("PGIM",Account_Data[[#This Row],[Details]])),ISNUMBER(SEARCH("CANARA",Account_Data[[#This Row],[Details]])),ISNUMBER(SEARCH("MUTUAL",Account_Data[[#This Row],[Details]])))),"Investment Return", IF(OR(ISNUMBER(SEARCH("LOAN",Account_Data[[#This Row],[Details]])),ISNUMBER(SEARCH("RECOVERY",Account_Data[[#This Row],[Details]]))),"Loan Payment", IF(OR(ISNUMBER(SEARCH("SALARY",Account_Data[[#This Row],[Details]])),ISNUMBER(SEARCH("EMPLOYER DEP",Account_Data[[#This Row],[Details]]))),"Income", IF(OR(ISNUMBER(SEARCH("ACH",Account_Data[[#This Row],[Details]])),ISNUMBER(SEARCH("DIRECT DR",Account_Data[[#This Row],[Details]]))),"EMI", IF(ISNUMBER(SEARCH("ATM",Account_Data[[#This Row],[Details]])),"Cash", IF(ISNUMBER(SEARCH("UPI",Account_Data[[#This Row],[Details]])),"UPI Expense",IF(ISNUMBER(SEARCH("W TFR",Account_Data[[#This Row],[Details]])),"Transfer","Other"))))))))) -> EMI | I69: =Account_Data[[#This Row],[Credit]]-Account_Data[[#This Row],[Debit]] -> -2000 | J69: =EOMONTH(Account_Data[[#This Row],[Date]],0) -> 45808 | K69: =ABS(Account_Data[[#This Row],[Amount]]) -> 2000
A70: 45779 | B70: DEBIT ACHDr YESB TP ACH INDIANE | C70: 2000 | E70: 99178.03 | F70: =TEXT(Account_Data[[#This Row],[Date]],"mmm-yyyy") -> May-2025 | G70: =IF(Account_Data[[#This Row],[Credit]]>0,"Income","Expense") -> Expense | H70: =IF(AND(Account_Data[[#This Row],[Credit]]>0,ISNUMBER(SEARCH("TFR",Account_Data[[#This Row],[Details]])),Account_Data[[#This Row],[Credit]]>=200000),"Loan Taken", IF(AND(Account_Data[[#This Row],[Debit]]>0,OR(ISNUMBER(SEARCH("ETMONEY",Account_Data[[#This Row],[Details]])),ISNUMBER(SEARCH("PGIM",Account_Data[[#This Row],[Details]])),ISNUMBER(SEARCH("CANARA",Account_Data[[#This Row],[Details]])))),"Investment (Outflow)", IF(AND(Account_Data[[#This Row],[Credit]]>0,OR(ISNUMBER(SEARCH("PGIM",Account_Data[[#This Row],[Details]])),ISNUMBER(SEARCH("CANARA",Account_Data[[#This Row],[Details]])),ISNUMBER(SEARCH("MUTUAL",Account_Data[[#This Row],[Details]])))),"Investment Return", IF(OR(ISNUMBER(SEARCH("LOAN",Account_Data[[#This Row],[Details]])),ISNUMBER(SEARCH("RECOVERY",Account_Data[[#This Row],[Details]]))),"Loan Payment", IF(OR(ISNUMBER(SEARCH("SALARY",Account_Data[[#This Row],[Details]])),ISNUMBER(SEARCH("EMPLOYER DEP",Account_Data[[#This Row],[Details]]))),"Income", IF(OR(ISNUMBER(SEARCH("ACH",Account_Data[[#This Row],[Details]])),ISNUMBER(SEARCH("DIRECT DR",Account_Data[[#This Row],[Details]]))),"EMI", IF(ISNUMBER(SEARCH("ATM",Account_Data[[#This Row],[Details]])),"Cash", IF(ISNUMBER(SEARCH("UPI",Account_Data[[#This Row],[Details]])),"UPI Expense",IF(ISNUMBER(SEARCH("W TFR",Account_Data[[#This Row],[Details]])),"Transfer","Other"))))))))) -> EMI | I70: =Account_Data[[#This Row],[Credit]]-Account_Data[[#This Row],[Debit]] -> -2000 | J70: =EOMONTH(Account_Data[[#This Row],[Date]],0) -> 45808 | K70: =ABS(Account_Data[[#This Row],[Amount]]) -> 2000
A71: 45779 | B71: DEBIT ACHDr YESB TP ACH INDIANE | C71: 5000 | E71: 94178.03 | F71: =TEXT(Account_Data[[#This Row],[Date]],"mmm-yyyy") -> May-2025 | G71: =IF(Account_Data[[#This Row],[Credit]]>0,"Income","Expense") -> Expense | H71: =IF(AND(Account_Data[[#This Row],[Credit]]>0,ISNUMBER(SEARCH("TFR",Account_Data[[#This Row],[Details]])),Account_Data[[#This Row],[Credit]]>=200000),"Loan Taken", IF(AND(Account_Data[[#This Row],[Debit]]>0,OR(ISNUMBER(SEARCH("ETMONEY",Account_Data[[#This Row],[Details]])),ISNUMBER(SEARCH("PGIM",Account_Data[[#This Row],[Details]])),ISNUMBER(SEARCH("CANARA",Account_Data[[#This Row],[Details]])))),"Investment (Outflow)", IF(AND(Account_Data[[#This Row],[Credit]]>0,OR(ISNUMBER(SEARCH("PGIM",Account_Data[[#This Row],[Details]])),ISNUMBER(SEARCH("CANARA",Account_Data[[#This Row],[Details]])),ISNUMBER(SEARCH("MUTUAL",Account_Data[[#This Row],[Details]])))),"Investment Return", IF(OR(ISNUMBER(SEARCH("LOAN",Account_Data[[#This Row],[Details]])),ISNUMBER(SEARCH("RECOVERY",Account_Data[[#This Row],[Details]]))),"Loan Payment", IF(OR(ISNUMBER(SEARCH("SALARY",Account_Data[[#This Row],[Details]])),ISNUMBER(SEARCH("EMPLOYER DEP",Account_Data[[#This Row],[Details]]))),"Income", IF(OR(ISNUMBER(SEARCH("ACH",Account_Data[[#This Row],[Details]])),ISNUMBER(SEARCH("DIRECT DR",Account_Data[[#This Row],[Details]]))),"EMI", IF(ISNUMBER(SEARCH("ATM",Account_Data[[#This Row],[Details]])),"Cash", IF(ISNUMBER(SEARCH("UPI",Account_Data[[#This Row],[Details]])),"UPI Expense",IF(ISNUMBER(SEARCH("W TFR",Account_Data[[#This Row],[Details]])),"Transfer","Other"))))))))) -> EMI | I71: =Account_Data[[#This Row],[Credit]]-Account_Data[[#This Row],[Debit]] -> -5000 | J71: =EOMONTH(Account_Data[[#This Row],[Date]],0) -> 45808 | K71: =ABS(Account_Data[[#This Row],[Amount]]) -> 5000
A72: 45779 | B72: DEBIT ACHDr YESB TP ACH INDIANE | C72: 5000 | E72: 89178.03 | F72: =TEXT(Account_Data[[#This Row],[Date]],"mmm-yyyy") -> May-2025 | G72: =IF(Account_Data[[#This Row],[Credit]]>0,"Income","Expense") -> Expense | H72: =IF(AND(Account_Data[[#This Row],[Credit]]>0,ISNUMBER(SEARCH("TFR",Account_Data[[#This Row],[Details]])),Account_Data[[#This Row],[Credit]]>=200000),"Loan Taken", IF(AND(Account_Data[[#This Row],[Debit]]>0,OR(ISNUMBER(SEARCH("ETMONEY",Account_Data[[#This Row],[Details]])),ISNUMBER(SEARCH("PGIM",Account_Data[[#This Row],[Details]])),ISNUMBER(SEARCH("CANARA",Account_Data[[#This Row],[Details]])))),"Investment (Outflow)", IF(AND(Account_Data[[#This Row],[Credit]]>0,OR(ISNUMBER(SEARCH("PGIM",Account_Data[[#This Row],[Details]])),ISNUMBER(SEARCH("CANARA",Account_Data[[#This Row],[Details]])),ISNUMBER(SEARCH("MUTUAL",Account_Data[[#This Row],[Details]])))),"Investment Return", IF(OR(ISNUMBER(SEARCH("LOAN",Account_Data[[#This Row],[Details]])),ISNUMBER(SEARCH("RECOVERY",Account_Data[[#This Row],[Details]]))),"Loan Payment", IF(OR(ISNUMBER(SEARCH("SALARY",Account_Data[[#This Row],[Details]])),ISNUMBER(SEARCH("EMPLOYER DEP",Account_Data[[#This Row],[Details]]))),"Income", IF(OR(ISNUMBER(SEARCH("ACH",Account_Data[[#This Row],[Details]])),ISNUMBER(SEARCH("DIRECT DR",Account_Data[[#This Row],[Details]]))),"EMI", IF(ISNUMBER(SEARCH("ATM",Account_Data[[#This Row],[Details]])),"Cash", IF(ISNUMBER(SEARCH("UPI",Account_Data[[#This Row],[Details]])),"UPI Expense",IF(ISNUMBER(SEARCH("W TFR",Account_Data[[#This Row],[Details]])),"Transfer","Other"))))))))) -> EMI | I72: =Account_Data[[#This Row],[Credit]]-Account_Data[[#This Row],[Debit]] -> -5000 | J72: =EOMONTH(Account_Data[[#This Row],[Date]],0) -> 45808 | K72: =ABS(Account_Data[[#This Row],[Amount]]) -> 5000
A73: 45779 | B73: DEBIT ACHDr NACH ETMONEY | C73: 1500 | E73: 87678.03 | F73: =TEXT(Account_Data[[#This Row],[Date]],"mmm-yyyy") -> May-2025 | G73: =IF(Account_Data[[#This Row],[Credit]]>0,"Income","Expense") -> Expense | H73: =IF(AND(Account_Data[[#This Row],[Credit]]>0,ISNUMBER(SEARCH("TFR",Account_Data[[#This Row],[Details]])),Account_Data[[#This Row],[Credit]]>=200000),"Loan Taken", IF(AND(Account_Data[[#This Row],[Debit]]>0,OR(ISNUMBER(SEARCH("ETMONEY",Account_Data[[#This Row],[Details]])),ISNUMBER(SEARCH("PGIM",Account_Data[[#This Row],[Details]])),ISNUMBER(SEARCH("CANARA",Account_Data[[#This Row],[Details]])))),"Investment (Outflow)", IF(AND(Account_Data[[#This Row],[Credit]]>0,OR(ISNUMBER(SEARCH("PGIM",Account_Data[[#This Row],[Details]])),ISNUMBER(SEARCH("CANARA",Account_Data[[#This Row],[Details]])),ISNUMBER(SEARCH("MUTUAL",Account_Data[[#This Row],[Details]])))),"Investment Return", IF(OR(ISNUMBER(SEARCH("LOAN",Account_Data[[#This Row],[Details]])),ISNUMBER(SEARCH("RECOVERY",Account_Data[[#This Row],[Details]]))),"Loan Payment", IF(OR(ISNUMBER(SEARCH("SALARY",Account_Data[[#This Row],[Details]])),ISNUMBER(SEARCH("EMPLOYER DEP",Account_Data[[#This Row],[Details]]))),"Income", IF(OR(ISNUMBER(SEARCH("ACH",Account_Data[[#This Row],[Details]])),ISNUMBER(SEARCH("DIRECT DR",Account_Data[[#This Row],[Details]]))),"EMI", IF(ISNUMBER(SEARCH("ATM",Account_Data[[#This Row],[Details]])),"Cash", IF(ISNUMBER(SEARCH("UPI",Account_Data[[#This Row],[Details]])),"UPI Expense",IF(ISNUMBER(SEARCH("W TFR",Account_Data[[#This Row],[Details]])),"Transfer","Other"))))))))) -> Investment (Outflow) | I73: =Account_Data[[#This Row],[Credit]]-Account_Data[[#This Row],[Debit]] -> -1500 | J73: =EOMONTH(Account_Data[[#This Row],[Date]],0) -> 45808 | K73: =ABS(Account_Data[[#This Row],[Amount]]) -> 1500
... A85: 45782 | B85: W TFR UPI/DR//Comfort /UTIB/gpay-/P aym AT | C85: 2135 | E85: 18751.83 | F85: =TEXT(Account_Data[[#This Row],[Date]],"mmm-yyyy") -> May-2025 | G85: =IF(Account_Data[[#This Row],[Credit]]>0,"Income","Expense") -> Expense | H85: =IF(AND(Account_Data[[#This Row],[Credit]]>0,ISNUMBER(SEARCH("TFR",Account_Data[[#This Row],[Details]])),Account_Data[[#This Row],[Credit]]>=200000),"Loan Taken", IF(AND(Account_Data[[#This Row],[Debit]]>0,OR(ISNUMBER(SEARCH("ETMONEY",Account_Data[[#This Row],[Details]])),ISNUMBER(SEARCH("PGIM",Account_Data[[#This Row],[Details]])),ISNUMBER(SEARCH("CANARA",Account_Data[[#This Row],[Details]])))),"Investment (Outflow)", IF(AND(Account_Data[[#This Row],[Credit]]>0,OR(ISNUMBER(SEARCH("PGIM",Account_Data[[#This Row],[Details]])),ISNUMBER(SEARCH("CANARA",Account_Data[[#This Row],[Details]])),ISNUMBER(SEARCH("MUTUAL",Account_Data[[#This Row],[Details]])))),"Investment Return", IF(OR(ISNUMBER(SEARCH("LOAN",Account_Data[[#This Row],[Details]])),ISNUMBER(SEARCH("RECOVERY",Account_Data[[#This Row],[Details]]))),"Loan Payment", IF(OR(ISNUMBER(SEARCH("SALARY",Account_Data[[#This Row],[Details]])),ISNUMBER(SEARCH("EMPLOYER DEP",Account_Data[[#This Row],[Details]]))),"Income", IF(OR(ISNUMBER(SEARCH("ACH",Account_Data[[#This Row],[Details]])),ISNUMBER(SEARCH("DIRECT DR",Account_Data[[#This Row],[Details]]))),"EMI", IF(ISNUMBER(SEARCH("ATM",Account_Data[[#This Row],[Details]])),"Cash", IF(ISNUMBER(SEARCH("UPI",Account_Data[[#This Row],[Details]])),"UPI Expense",IF(ISNUMBER(SEARCH("W TFR",Account_Data[[#This Row],[Details]])),"Transfer","Other"))))))))) -> UPI Expense | I85: =Account_Data[[#This Row],[Credit]]-Account_Data[[#This Row],[Debit]] -> -2135 | J85: =EOMONTH(Account_Data[[#This Row],[Date]],0) -> 45808 | K85: =ABS(Account_Data[[#This Row],[Amount]]) -> 2135
A86: 45782 | B86: DEP TFR NEFT*UTIB*AXISP*LIC* BAT AT | D86: 3960 | E86: 22711.83 | F86: =TEXT(Account_Data[[#This Row],[Date]],"mmm-yyyy") -> May-2025 | G86: =IF(Account_Data[[#This Row],[Credit]]>0,"Income","Expense") -> Income | H86: =IF(AND(Account_Data[[#This Row],[Credit]]>0,ISNUMBER(SEARCH("TFR",Account_Data[[#This Row],[Details]])),Account_Data[[#This Row],[Credit]]>=200000),"Loan Taken", IF(AND(Account_Data[[#This Row],[Debit]]>0,OR(ISNUMBER(SEARCH("ETMONEY",Account_Data[[#This Row],[Details]])),ISNUMBER(SEARCH("PGIM",Account_Data[[#This Row],[Details]])),ISNUMBER(SEARCH("CANARA",Account_Data[[#This Row],[Details]])))),"Investment (Outflow)", IF(AND(Account_Data[[#This Row],[Credit]]>0,OR(ISNUMBER(SEARCH("PGIM",Account_Data[[#This Row],[Details]])),ISNUMBER(SEARCH("CANARA",Account_Data[[#This Row],[Details]])),ISNUMBER(SEARCH("MUTUAL",Account_Data[[#This Row],[Details]])))),"Investment Return", IF(OR(ISNUMBER(SEARCH("LOAN",Account_Data[[#This Row],[Details]])),ISNUMBER(SEARCH("RECOVERY",Account_Data[[#This Row],[Details]]))),"Loan Payment", IF(OR(ISNUMBER(SEARCH("SALARY",Account_Data[[#This Row],[Details]])),ISNUMBER(SEARCH("EMPLOYER DEP",Account_Data[[#This Row],[Details]]))),"Income", IF(OR(ISNUMBER(SEARCH("ACH",Account_Data[[#This Row],[Details]])),ISNUMBER(SEARCH("DIRECT DR",Account_Data[[#This Row],[Details]]))),"EMI", IF(ISNUMBER(SEARCH("ATM",Account_Data[[#This Row],[Details]])),"Cash", IF(ISNUMBER(SEARCH("UPI",Account_Data[[#This Row],[Details]])),"UPI Expense",IF(ISNUMBER(SEARCH("W TFR",Account_Data[[#This Row],[Details]])),"Transfer","Other"))))))))) -> Other | I86: =Account_Data[[#This Row],[Credit]]-Account_Data[[#This Row],[Debit]] -> 3960 | J86: =EOMONTH(Account_Data[[#This Row],[Date]],0) -> 45808 | K86: =ABS(Account_Data[[#This Row],[Amount]]) -> 3960
A87: 45783 | B87: DEP TFR NEFT*HDFC*HDFCH*MIRAE ASSET MF AT | D87: 22191.22 | E87: 44903.05 | F87: =TEXT(Account_Data[[#This Row],[Date]],"mmm-yyyy") -> May-2025 | G87: =IF(Account_Data[[#This Row],[Credit]]>0,"Income","Expense") -> Income | H87: =IF(AND(Account_Data[[#This Row],[Credit]]>0,ISNUMBER(SEARCH("TFR",Account_Data[[#This Row],[Details]])),Account_Data[[#This Row],[Credit]]>=200000),"Loan Taken", IF(AND(Account_Data[[#This Row],[Debit]]>0,OR(ISNUMBER(SEARCH("ETMONEY",Account_Data[[#This Row],[Details]])),ISNUMBER(SEARCH("PGIM",Account_Data[[#This Row],[Details]])),ISNUMBER(SEARCH("CANARA",Account_Data[[#This Row],[Details]])))),"Investment (Outflow)", IF(AND(Account_Data[[#This Row],[Credit]]>0,OR(ISNUMBER(SEARCH("PGIM",Account_Data[[#This Row],[Details]])),ISNUMBER(SEARCH("CANARA",Account_Data[[#This Row],[Details]])),ISNUMBER(SEARCH("MUTUAL",Account_Data[[#This Row],[Details]])))),"Investment Return", IF(OR(ISNUMBER(SEARCH("LOAN",Account_Data[[#This Row],[Details]])),ISNUMBER(SEARCH("RECOVERY",Account_Data[[#This Row],[Details]]))),"Loan Payment", IF(OR(ISNUMBER(SEARCH("SALARY",Account_Data[[#This Row],[Details]])),ISNUMBER(SEARCH("EMPLOYER DEP",Account_Data[[#This Row],[Details]]))),"Income", IF(OR(ISNUMBER(SEARCH("ACH",Account_Data[[#This Row],[Details]])),ISNUMBER(SEARCH("DIRECT DR",Account_Data[[#This Row],[Details]]))),"EMI", IF(ISNUMBER(SEARCH("ATM",Account_Data[[#This Row],[Details]])),"Cash", IF(ISNUMBER(SEARCH("UPI",Account_Data[[#This Row],[Details]])),"UPI Expense",IF(ISNUMBER(SEARCH("W TFR",Account_Data[[#This Row],[Details]])),"Transfer","Other"))))))))) -> Other | I87: =Account_Data[[#This Row],[Credit]]-Account_Data[[#This Row],[Debit]] -> 22191.22 | J87: =EOMONTH(Account_Data[[#This Row],[Date]],0) -> 45808 | K87: =ABS(Account_Data[[#This Row],[Amount]]) -> 22191.22
A88: 45783 | B88: DEP TFR NEFT*UTIB*AXISCN*AXIS MUTUAL FUN AT | D88: 22143.03 | E88: 67046.08 | F88: =TEXT(Account_Data[[#This Row],[Date]],"mmm-yyyy") -> May-2025 | G88: =IF(Account_Data[[#This Row],[Credit]]>0,"Income","Expense") -> Income | H88: =IF(AND(Account_Data[[#This Row],[Credit]]>0,ISNUMBER(SEARCH("TFR",Account_Data[[#This Row],[Details]])),Account_Data[[#This Row],[Credit]]>=200000),"Loan Taken", IF(AND(Account_Data[[#This Row],[Debit]]>0,OR(ISNUMBER(SEARCH("ETMONEY",Account_Data[[#This Row],[Details]])),ISNUMBER(SEARCH("PGIM",Account_Data[[#This Row],[Details]])),ISNUMBER(SEARCH("CANARA",Account_Data[[#This Row],[Details]])))),"Investment (Outflow)", IF(AND(Account_Data[[#This Row],[Credit]]>0,OR(ISNUMBER(SEARCH("PGIM",Account_Data[[#This Row],[Details]])),ISNUMBER(SEARCH("CANARA",Account_Data[[#This Row],[Details]])),ISNUMBER(SEARCH("MUTUAL",Account_Data[[#This Row],[Details]])))),"Investment Return", IF(OR(ISNUMBER(SEARCH("LOAN",Account_Data[[#This Row],[Details]])),ISNUMBER(SEARCH("RECOVERY",Account_Data[[#This Row],[Details]]))),"Loan Payment", IF(OR(ISNUMBER(SEARCH("SALARY",Account_Data[[#This Row],[Details]])),ISNUMBER(SEARCH("EMPLOYER DEP",Account_Data[[#This Row],[Details]]))),"Income", IF(OR(ISNUMBER(SEARCH("ACH",Account_Data[[#This Row],[Details]])),ISNUMBER(SEARCH("DIRECT DR",Account_Data[[#This Row],[Details]]))),"EMI", IF(ISNUMBER(SEARCH("ATM",Account_Data[[#This Row],[Details]])),"Cash", IF(ISNUMBER(SEARCH("UPI",Account_Data[[#This Row],[Details]])),"UPI Expense",IF(ISNUMBER(SEARCH("W TFR",Account_Data[[#This Row],[Details]])),"Transfer","Other"))))))))) -> Investment Return | I88: =Account_Data[[#This Row],[Credit]]-Account_Data[[#This Row],[Debit]] -> 22143.03 | J88: =EOMONTH(Account_Data[[#This Row],[Date]],0) -> 45808 | K88: =ABS(Account_Data[[#This Row],[Amount]]) -> 22143.03
A89: 45784 | B89: DIRECT DR OF Mr. XYZ ABC H AT | C89: 8704 | E89: 58342.08 | F89: =TEXT(Account_Data[[#This Row],[Date]],"mmm-yyyy") -> May-2025 | G89: =IF(Account_Data[[#This Row],[Credit]]>0,"Income","Expense") -> Expense | H89: =IF(AND(Account_Data[[#This Row],[Credit]]>0,ISNUMBER(SEARCH("TFR",Account_Data[[#This Row],[Details]])),Account_Data[[#This Row],[Credit]]>=200000),"Loan Taken", IF(AND(Account_Data[[#This Row],[Debit]]>0,OR(ISNUMBER(SEARCH("ETMONEY",Account_Data[[#This Row],[Details]])),ISNUMBER(SEARCH("PGIM",Account_Data[[#This Row],[Details]])),ISNUMBER(SEARCH("CANARA",Account_Data[[#This Row],[Details]])))),"Investment (Outflow)", IF(AND(Account_Data[[#This Row],[Credit]]>0,OR(ISNUMBER(SEARCH("PGIM",Account_Data[[#This Row],[Details]])),ISNUMBER(SEARCH("CANARA",Account_Data[[#This Row],[Details]])),ISNUMBER(SEARCH("MUTUAL",Account_Data[[#This Row],[Details]])))),"Investment Return", IF(OR(ISNUMBER(SEARCH("LOAN",Account_Data[[#This Row],[Details]])),ISNUMBER(SEARCH("RECOVERY",Account_Data[[#This Row],[Details]]))),"Loan Payment", IF(OR(ISNUMBER(SEARCH("SALARY",Account_Data[[#This Row],[Details]])),ISNUMBER(SEARCH("EMPLOYER DEP",Account_Data[[#This Row],[Details]]))),"Income", IF(OR(ISNUMBER(SEARCH("ACH",Account_Data[[#This Row],[Details]])),ISNUMBER(SEARCH("DIRECT DR",Account_Data[[#This Row],[Details]]))),"EMI", IF(ISNUMBER(SEARCH("ATM",Account_Data[[#This Row],[Details]])),"Cash", IF(ISNUMBER(SEARCH("UPI",Account_Data[[#This Row],[Details]])),"UPI Expense",IF(ISNUMBER(SEARCH("W TFR",Account_Data[[#This Row],[Details]])),"Transfer","Other"))))))))) -> EMI | I89: =Account_Data[[#This Row],[Credit]]-Account_Data[[#This Row],[Debit]] -> -8704 | J89: =EOMONTH(Account_Data[[#This Row],[Date]],0) -> 45808 | K89: =ABS(Account_Data[[#This Row],[Amount]]) -> 8704
A90: 45784 | B90: W TFR UPI/DR//Ms Gauta/YESB/paytm-/P aym AT | C90: 2000 | E90: 56342.08 | F90: =TEXT(Account_Data[[#This Row],[Date]],"mmm-yyyy") -> May-2025 | G90: =IF(Account_Data[[#This Row],[Credit]]>0,"Income","Expense") -> Expense | H90: =IF(AND(Account_Data[[#This Row],[Credit]]>0,ISNUMBER(SEARCH("TFR",Account_Data[[#This Row],[Details]])),Account_Data[[#This Row],[Credit]]>=200000),"Loan Taken", IF(AND(Account_Data[[#This Row],[Debit]]>0,OR(ISNUMBER(SEARCH("ETMONEY",Account_Data[[#This Row],[Details]])),ISNUMBER(SEARCH("PGIM",Account_Data[[#This Row],[Details]])),ISNUMBER(SEARCH("CANARA",Account_Data[[#This Row],[Details]])))),"Investment (Outflow)", IF(AND(Account_Data[[#This Row],[Credit]]>0,OR(ISNUMBER(SEARCH("PGIM",Account_Data[[#This Row],[Details]])),ISNUMBER(SEARCH("CANARA",Account_Data[[#This Row],[Details]])),ISNUMBER(SEARCH("MUTUAL",Account_Data[[#This Row],[Details]])))),"Investment Return", IF(OR(ISNUMBER(SEARCH("LOAN",Account_Data[[#This Row],[Details]])),ISNUMBER(SEARCH("RECOVERY",Account_Data[[#This Row],[Details]]))),"Loan Payment", IF(OR(ISNUMBER(SEARCH("SALARY",Account_Data[[#This Row],[Details]])),ISNUMBER(SEARCH("EMPLOYER DEP",Account_Data[[#This Row],[Details]]))),"Income", IF(OR(ISNUMBER(SEARCH("ACH",Account_Data[[#This Row],[Details]])),ISNUMBER(SEARCH("DIRECT DR",Account_Data[[#This Row],[Details]]))),"EMI", IF(ISNUMBER(SEARCH("ATM",Account_Data[[#This Row],[Details]])),"Cash", IF(ISNUMBER(SEARCH("UPI",Account_Data[[#This Row],[Details]])),"UPI Expense",IF(ISNUMBER(SEARCH("W TFR",Account_Data[[#This Row],[Details]])),"Transfer","Other"))))))))) -> UPI Expense | I90: =Account_Data[[#This Row],[Credit]]-Account_Data[[#This Row],[Debit]] -> -2000 | J90: =EOMONTH(Account_Data[[#This Row],[Date]],0) -> 45808 | K90: =ABS(Account_Data[[#This Row],[Amount]]) -> 2000
A91: 45784 | B91: W TFR UPI/DR//BharsoSy/UTIB/bharsosyst/ Pay AT | C91: 997 | E91: 55345.08 | F91: =TEXT(Account_Data[[#This Row],[Date]],"mmm-yyyy") -> May-2025 | G91: =IF(Account_Data[[#This Row],[Credit]]>0,"Income","Expense") -> Expense | H91: =IF(AND(Account_Data[[#This Row],[Credit]]>0,ISNUMBER(SEARCH("TFR",Account_Data[[#This Row],[Details]])),Account_Data[[#This Row],[Credit]]>=200000),"Loan Taken", IF(AND(Account_Data[[#This Row],[Debit]]>0,OR(ISNUMBER(SEARCH("ETMONEY",Account_Data[[#This Row],[Details]])),ISNUMBER(SEARCH("PGIM",Account_Data[[#This Row],[Details]])),ISNUMBER(SEARCH("CANARA",Account_Data[[#This Row],[Details]])))),"Investment (Outflow)", IF(AND(Account_Data[[#This Row],[Credit]]>0,OR(ISNUMBER(SEARCH("PGIM",Account_Data[[#This Row],[Details]])),ISNUMBER(SEARCH("CANARA",Account_Data[[#This Row],[Details]])),ISNUMBER(SEARCH("MUTUAL",Account_Data[[#This Row],[Details]])))),"Investment Return", IF(OR(ISNUMBER(SEARCH("LOAN",Account_Data[[#This Row],[Details]])),ISNUMBER(SEARCH("RECOVERY",Account_Data[[#This Row],[Details]]))),"Loan Payment", IF(OR(ISNUMBER(SEARCH("SALARY",Account_Data[[#This Row],[Details]])),ISNUMBER(SEARCH("EMPLOYER DEP",Account_Data[[#This Row],[Details]]))),"Income", IF(OR(ISNUMBER(SEARCH("ACH",Account_Data[[#This Row],[Details]])),ISNUMBER(SEARCH("DIRECT DR",Account_Data[[#This Row],[Details]]))),"EMI", IF(ISNUMBER(SEARCH("ATM",Account_Data[[#This Row],[Details]])),"Cash", IF(ISNUMBER(SEARCH("UPI",Account_Data[[#This Row],[Details]])),"UPI Expense",IF(ISNUMBER(SEARCH("W TFR",Account_Data[[#This Row],[Details]])),"Transfer","Other"))))))))) -> UPI Expense | I91: =Account_Data[[#This Row],[Credit]]-Account_Data[[#This Row],[Debit]] -> -997 | J91: =EOMONTH(Account_Data[[#This Row],[Date]],0) -> 45808 | K91: =ABS(Account_Data[[#This Row],[Amount]]) -> 997
A92: 45785 | B92: W TFR UPI/DR//SUMAN S/SBIN//P aym AT | C92: 5000 | E92: 50345.08 | F92: =TEXT(Account_Data[[#This Row],[Date]],"mmm-yyyy") -> May-2025 | G92: =IF(Account_Data[[#This Row],[Credit]]>0,"Income","Expense") -> Expense | H92: =IF(AND(Account_Data[[#This Row],[Credit]]>0,ISNUMBER(SEARCH("TFR",Account_Data[[#This Row],[Details]])),Account_Data[[#This Row],[Credit]]>=200000),"Loan Taken", IF(AND(Account_Data[[#This Row],[Debit]]>0,OR(ISNUMBER(SEARCH("ETMONEY",Account_Data[[#This Row],[Details]])),ISNUMBER(SEARCH("PGIM",Account_Data[[#This Row],[Details]])),ISNUMBER(SEARCH("CANARA",Account_Data[[#This Row],[Details]])))),"Investment (Outflow)", IF(AND(Account_Data[[#This Row],[Credit]]>0,OR(ISNUMBER(SEARCH("PGIM",Account_Data[[#This Row],[Details]])),ISNUMBER(SEARCH("CANARA",Account_Data[[#This Row],[Details]])),ISNUMBER(SEARCH("MUTUAL",Account_Data[[#This Row],[Details]])))),"Investment Return", IF(OR(ISNUMBER(SEARCH("LOAN",Account_Data[[#This Row],[Details]])),ISNUMBER(SEARCH("RECOVERY",Account_Data[[#This Row],[Details]]))),"Loan Payment", IF(OR(ISNUMBER(SEARCH("SALARY",Account_Data[[#This Row],[Details]])),ISNUMBER(SEARCH("EMPLOYER DEP",Account_Data[[#This Row],[Details]]))),"Income", IF(OR(ISNUMBER(SEARCH("ACH",Account_Data[[#This Row],[Details]])),ISNUMBER(SEARCH("DIRECT DR",Account_Data[[#This Row],[Details]]))),"EMI", IF(ISNUMBER(SEARCH("ATM",Account_Data[[#This Row],[Details]])),"Cash", IF(ISNUMBER(SEARCH("UPI",Account_Data[[#This Row],[Details]])),"UPI Expense",IF(ISNUMBER(SEARCH("W TFR",Account_Data[[#This Row],[Details]])),"Transfer","Other"))))))))) -> UPI Expense | I92: =Account_Data[[#This Row],[Credit]]-Account_Data[[#This Row],[Debit]] -> -5000 | J92: =EOMONTH(Account_Data[[#This Row],[Date]],0) -> 45808 | K92: =ABS(Account_Data[[#This Row],[Amount]]) -> 5000
A93: 45786 | B93: W TFR UPI/DR//SHAMBHAV/KKBK//P aym AT | C93: 2300 | E93: 48045.08 | F93: =TEXT(Account_Data[[#This Row],[Date]],"mmm-yyyy") -> May-2025 | G93: =IF(Account_Data[[#This Row],[Credit]]>0,"Income","Expense") -> Expense | H93: =IF(AND(Account_Data[[#This Row],[Credit]]>0,ISNUMBER(SEARCH("TFR",Account_Data[[#This Row],[Details]])),Account_Data[[#This Row],[Credit]]>=200000),"Loan Taken", IF(AND(Account_Data[[#This Row],[Debit]]>0,OR(ISNUMBER(SEARCH("ETMONEY",Account_Data[[#This Row],[Details]])),ISNUMBER(SEARCH("PGIM",Account_Data[[#This Row],[Details]])),ISNUMBER(SEARCH("CANARA",Account_Data[[#This Row],[Details]])))),"Investment (Outflow)", IF(AND(Account_Data[[#This Row],[Credit]]>0,OR(ISNUMBER(SEARCH("PGIM",Account_Data[[#This Row],[Details]])),ISNUMBER(SEARCH("CANARA",Account_Data[[#This Row],[Details]])),ISNUMBER(SEARCH("MUTUAL",Account_Data[[#This Row],[Details]])))),"Investment Return", IF(OR(ISNUMBER(SEARCH("LOAN",Account_Data[[#This Row],[Details]])),ISNUMBER(SEARCH("RECOVERY",Account_Data[[#This Row],[Details]]))),"Loan Payment", IF(OR(ISNUMBER(SEARCH("SALARY",Account_Data[[#This Row],[Details]])),ISNUMBER(SEARCH("EMPLOYER DEP",Account_Data[[#This Row],[Details]]))),"Income", IF(OR(ISNUMBER(SEARCH("ACH",Account_Data[[#This Row],[Details]])),ISNUMBER(SEARCH("DIRECT DR",Account_Data[[#This Row],[Details]]))),"EMI", IF(ISNUMBER(SEARCH("ATM",Account_Data[[#This Row],[Details]])),"Cash", IF(ISNUMBER(SEARCH("UPI",Account_Data[[#This Row],[Details]])),"UPI Expense",IF(ISNUMBER(SEARCH("W TFR",Account_Data[[#This Row],[Details]])),"Transfer","Other"))))))))) -> UPI Expense | I93: =Account_Data[[#This Row],[Credit]]-Account_Data[[#This Row],[Debit]] -> -2300 | J93: =EOMONTH(Account_Data[[#This Row],[Date]],0) -> 45808 | K93: =ABS(Account_Data[[#This Row],[Amount]]) -> 2300
A94: 45786 | B94: W TFR PMSBY RENEWAL SBISB AT | C94: 20 | E94: 48025.08 | F94: =TEXT(Account_Data[[#This Row],[Date]],"mmm-yyyy") -> May-2025 | G94: =IF(Account_Data[[#This Row],[Credit]]>0,"Income","Expense") -> Expense | H94: =IF(AND(Account_Data[[#This Row],[Credit]]>0,ISNUMBER(SEARCH("TFR",Account_Data[[#This Row],[Details]])),Account_Data[[#This Row],[Credit]]>=200000),"Loan Taken", IF(AND(Account_Data[[#This Row],[Debit]]>0,OR(ISNUMBER(SEARCH("ETMONEY",Account_Data[[#This Row],[Details]])),ISNUMBER(SEARCH("PGIM",Account_Data[[#This Row],[Details]])),ISNUMBER(SEARCH("CANARA",Account_Data[[#This Row],[Details]])))),"Investment (Outflow)", IF(AND(Account_Data[[#This Row],[Credit]]>0,OR(ISNUMBER(SEARCH("PGIM",Account_Data[[#This Row],[Details]])),ISNUMBER(SEARCH("CANARA",Account_Data[[#This Row],[Details]])),ISNUMBER(SEARCH("MUTUAL",Account_Data[[#This Row],[Details]])))),"Investment Return", IF(OR(ISNUMBER(SEARCH("LOAN",Account_Data[[#This Row],[Details]])),ISNUMBER(SEARCH("RECOVERY",Account_Data[[#This Row],[Details]]))),"Loan Payment", IF(OR(ISNUMBER(SEARCH("SALARY",Account_Data[[#This Row],[Details]])),ISNUMBER(SEARCH("EMPLOYER DEP",Account_Data[[#This Row],[Details]]))),"Income", IF(OR(ISNUMBER(SEARCH("ACH",Account_Data[[#This Row],[Details]])),ISNUMBER(SEARCH("DIRECT DR",Account_Data[[#This Row],[Details]]))),"EMI", IF(ISNUMBER(SEARCH("ATM",Account_Data[[#This Row],[Details]])),"Cash", IF(ISNUMBER(SEARCH("UPI",Account_Data[[#This Row],[Details]])),"UPI Expense",IF(ISNUMBER(SEARCH("W TFR",Account_Data[[#This Row],[Details]])),"Transfer","Other"))))))))) -> Transfer | I94: =Account_Data[[#This Row],[Credit]]-Account_Data[[#This Row],[Debit]] -> -20 | J94: =EOMONTH(Account_Data[[#This Row],[Date]],0) -> 45808 | K94: =ABS(Account_Data[[#This Row],[Amount]]) -> 20
A95: 45786 | B95: DEP TFR PAF IOCL LPG SUBSIDY IOAPD AT | D95: 59.52 | E95: 48084.6 | F95: =TEXT(Account_Data[[#This Row],[Date]],"mmm-yyyy") -> May-2025 | G95: =IF(Account_Data[[#This Row],[Credit]]>0,"Income","Expense") -> Income | H95: =IF(AND(Account_Data[[#This Row],[Credit]]>0,ISNUMBER(SEARCH("TFR",Account_Data[[#This Row],[Details]])),Account_Data[[#This Row],[Credit]]>=200000),"Loan Taken", IF(AND(Account_Data[[#This Row],[Debit]]>0,OR(ISNUMBER(SEARCH("ETMONEY",Account_Data[[#This Row],[Details]])),ISNUMBER(SEARCH("PGIM",Account_Data[[#This Row],[Details]])),ISNUMBER(SEARCH("CANARA",Account_Data[[#This Row],[Details]])))),"Investment (Outflow)", IF(AND(Account_Data[[#This Row],[Credit]]>0,OR(ISNUMBER(SEARCH("PGIM",Account_Data[[#This Row],[Details]])),ISNUMBER(SEARCH("CANARA",Account_Data[[#This Row],[Details]])),ISNUMBER(SEARCH("MUTUAL",Account_Data[[#This Row],[Details]])))),"Investment Return", IF(OR(ISNUMBER(SEARCH("LOAN",Account_Data[[#This Row],[Details]])),ISNUMBER(SEARCH("RECOVERY",Account_Data[[#This Row],[Details]]))),"Loan Payment", IF(OR(ISNUMBER(SEARCH("SALARY",Account_Data[[#This Row],[Details]])),ISNUMBER(SEARCH("EMPLOYER DEP",Account_Data[[#This Row],[Details]]))),"Income", IF(OR(ISNUMBER(SEARCH("ACH",Account_Data[[#This Row],[Details]])),ISNUMBER(SEARCH("DIRECT DR",Account_Data[[#This Row],[Details]]))),"EMI", IF(ISNUMBER(SEARCH("ATM",Account_Data[[#This Row],[Details]])),"Cash", IF(ISNUMBER(SEARCH("UPI",Account_Data[[#This Row],[Details]])),"UPI Expense",IF(ISNUMBER(SEARCH("W TFR",Account_Data[[#This Row],[Details]])),"Transfer","Other"))))))))) -> Other | I95: =Account_Data[[#This Row],[Credit]]-Account_Data[[#This Row],[Debit]] -> 59.52 | J95: =EOMONTH(Account_Data[[#This Row],[Date]],0) -> 45808 | K95: =ABS(Account_Data[[#This Row],[Amount]]) -> 59.52
A96: 45786 | B96: W TFR UPI/DR//DAL BAHA/BARB/dalbhadurs/P aym AT | C96: 550 | E96: 47534.6 | F96: =TEXT(Account_Data[[#This Row],[Date]],"mmm-yyyy") -> May-2025 | G96: =IF(Account_Data[[#This Row],[Credit]]>0,"Income","Expense") -> Expense | H96: =IF(AND(Account_Data[[#This Row],[Credit]]>0,ISNUMBER(SEARCH("TFR",Account_Data[[#This Row],[Details]])),Account_Data[[#This Row],[Credit]]>=200000),"Loan Taken", IF(AND(Account_Data[[#This Row],[Debit]]>0,OR(ISNUMBER(SEARCH("ETMONEY",Account_Data[[#This Row],[Details]])),ISNUMBER(SEARCH("PGIM",Account_Data[[#This Row],[Details]])),ISNUMBER(SEARCH("CANARA",Account_Data[[#This Row],[Details]])))),"Investment (Outflow)", IF(AND(Account_Data[[#This Row],[Credit]]>0,OR(ISNUMBER(SEARCH("PGIM",Account_Data[[#This Row],[Details]])),ISNUMBER(SEARCH("CANARA",Account_Data[[#This Row],[Details]])),ISNUMBER(SEARCH("MUTUAL",Account_Data[[#This Row],[Details]])))),"Investment Return", IF(OR(ISNUMBER(SEARCH("LOAN",Account_Data[[#This Row],[Details]])),ISNUMBER(SEARCH("RECOVERY",Account_Data[[#This Row],[Details]]))),"Loan Payment", IF(OR(ISNUMBER(SEARCH("SALARY",Account_Data[[#This Row],[Details]])),ISNUMBER(SEARCH("EMPLOYER DEP",Account_Data[[#This Row],[Details]]))),"Income", IF(OR(ISNUMBER(SEARCH("ACH",Account_Data[[#This Row],[Details]])),ISNUMBER(SEARCH("DIRECT DR",Account_Data[[#This Row],[Details]]))),"EMI", IF(ISNUMBER(SEARCH("ATM",Account_Data[[#This Row],[Details]])),"Cash", IF(ISNUMBER(SEARCH("UPI",Account_Data[[#This Row],[Details]])),"UPI Expense",IF(ISNUMBER(SEARCH("W TFR",Account_Data[[#This Row],[Details]])),"Transfer","Other"))))))))) -> UPI Expense | I96: =Account_Data[[#This Row],[Credit]]-Account_Data[[#This Row],[Debit]] -> -550 | J96: =EOMONTH(Account_Data[[#This Row],[Date]],0) -> 45808 | K96: =ABS(Account_Data[[#This Row],[Amount]]) -> 550
A97: 45786 | B97: W TFR UPI/DR//Dhruvah /YESB/paytmqr/P aym AT | C97: 2000 | E97: 45534.6 | F97: =TEXT(Account_Data[[#This Row],[Date]],"mmm-yyyy") -> May-2025 | G97: =IF(Account_Data[[#This Row],[Credit]]>0,"Income","Expense") -> Expense | H97: =IF(AND(Account_Data[[#This Row],[Credit]]>0,ISNUMBER(SEARCH("TFR",Account_Data[[#This Row],[Details]])),Account_Data[[#This Row],[Credit]]>=200000),"Loan Taken", IF(AND(Account_Data[[#This Row],[Debit]]>0,OR(ISNUMBER(SEARCH("ETMONEY",Account_Data[[#This Row],[Details]])),ISNUMBER(SEARCH("PGIM",Account_Data[[#This Row],[Details]])),ISNUMBER(SEARCH("CANARA",Account_Data[[#This Row],[Details]])))),"Investment (Outflow)", IF(AND(Account_Data[[#This Row],[Credit]]>0,OR(ISNUMBER(SEARCH("PGIM",Account_Data[[#This Row],[Details]])),ISNUMBER(SEARCH("CANARA",Account_Data[[#This Row],[Details]])),ISNUMBER(SEARCH("MUTUAL",Account_Data[[#This Row],[Details]])))),"Investment Return", IF(OR(ISNUMBER(SEARCH("LOAN",Account_Data[[#This Row],[Details]])),ISNUMBER(SEARCH("RECOVERY",Account_Data[[#This Row],[Details]]))),"Loan Payment", IF(OR(ISNUMBER(SEARCH("SALARY",Account_Data[[#This Row],[Details]])),ISNUMBER(SEARCH("EMPLOYER DEP",Account_Data[[#This Row],[Details]]))),"Income", IF(OR(ISNUMBER(SEARCH("ACH",Account_Data[[#This Row],[Details]])),ISNUMBER(SEARCH("DIRECT DR",Account_Data[[#This Row],[Details]]))),"EMI", IF(ISNUMBER(SEARCH("ATM",Account_Data[[#This Row],[Details]])),"Cash", IF(ISNUMBER(SEARCH("UPI",Account_Data[[#This Row],[Details]])),"UPI Expense",IF(ISNUMBER(SEARCH("W TFR",Account_Data[[#This Row],[Details]])),"Transfer","Other"))))))))) -> UPI Expense | I97: =Account_Data[[#This Row],[Credit]]-Account_Data[[#This Row],[Debit]] -> -2000 | J97: =EOMONTH(Account_Data[[#This Row],[Date]],0) -> 45808 | K97: =ABS(Account_Data[[#This Row],[Amount]]) -> 2000
A98: 45787 | B98: ATM W ATM CASH SAR AS MOTEL RAEBARELI RAE BARELI | C98: 10000 | E98: 35534.6 | F98: =TEXT(Account_Data[[#This Row],[Date]],"mmm-yyyy") -> May-2025 | G98: =IF(Account_Data[[#This Row],[Credit]]>0,"Income","Expense") -> Expense | H98: =IF(AND(Account_Data[[#This Row],[Credit]]>0,ISNUMBER(SEARCH("TFR",Account_Data[[#This Row],[Details]])),Account_Data[[#This Row],[Credit]]>=200000),"Loan Taken", IF(AND(Account_Data[[#This Row],[Debit]]>0,OR(ISNUMBER(SEARCH("ETMONEY",Account_Data[[#This Row],[Details]])),ISNUMBER(SEARCH("PGIM",Account_Data[[#This Row],[Details]])),ISNUMBER(SEARCH("CANARA",Account_Data[[#This Row],[Details]])))),"Investment (Outflow)", IF(AND(Account_Data[[#This Row],[Credit]]>0,OR(ISNUMBER(SEARCH("PGIM",Account_Data[[#This Row],[Details]])),ISNUMBER(SEARCH("CANARA",Account_Data[[#This Row],[Details]])),ISNUMBER(SEARCH("MUTUAL",Account_Data[[#This Row],[Details]])))),"Investment Return", IF(OR(ISNUMBER(SEARCH("LOAN",Account_Data[[#This Row],[Details]])),ISNUMBER(SEARCH("RECOVERY",Account_Data[[#This Row],[Details]]))),"Loan Payment", IF(OR(ISNUMBER(SEARCH("SALARY",Account_Data[[#This Row],[Details]])),ISNUMBER(SEARCH("EMPLOYER DEP",Account_Data[[#This Row],[Details]]))),"Income", IF(OR(ISNUMBER(SEARCH("ACH",Account_Data[[#This Row],[Details]])),ISNUMBER(SEARCH("DIRECT DR",Account_Data[[#This Row],[Details]]))),"EMI", IF(ISNUMBER(SEARCH("ATM",Account_Data[[#This Row],[Details]])),"Cash", IF(ISNUMBER(SEARCH("UPI",Account_Data[[#This Row],[Details]])),"UPI Expense",IF(ISNUMBER(SEARCH("W TFR",Account_Data[[#This Row],[Details]])),"Transfer","Other"))))))))) -> Cash | I98: =Account_Data[[#This Row],[Credit]]-Account_Data[[#This Row],[Debit]] -> -10000 | J98: =EOMONTH(Account_Data[[#This Row],[Date]],0) -> 45808 | K98: =ABS(Account_Data[[#This Row],[Amount]]) -> 10000
A99: 45787 | B99: ATM W ATM CASH SAR AS MOTEL RAEBARELI RAE BARELI | C99: 1000 | E99: 34534.6 | F99: =TEXT(Account_Data[[#This Row],[Date]],"mmm-yyyy") -> May-2025 | G99: =IF(Account_Data[[#This Row],[Credit]]>0,"Income","Expense") -> Expense | H99: =IF(AND(Account_Data[[#This Row],[Credit]]>0,ISNUMBER(SEARCH("TFR",Account_Data[[#This Row],[Details]])),Account_Data[[#This Row],[Credit]]>=200000),"Loan Taken", IF(AND(Account_Data[[#This Row],[Debit]]>0,OR(ISNUMBER(SEARCH("ETMONEY",Account_Data[[#This Row],[Details]])),ISNUMBER(SEARCH("PGIM",Account_Data[[#This Row],[Details]])),ISNUMBER(SEARCH("CANARA",Account_Data[[#This Row],[Details]])))),"Investment (Outflow)", IF(AND(Account_Data[[#This Row],[Credit]]>0,OR(ISNUMBER(SEARCH("PGIM",Account_Data[[#This Row],[Details]])),ISNUMBER(SEARCH("CANARA",Account_Data[[#This Row],[Details]])),ISNUMBER(SEARCH("MUTUAL",Account_Data[[#This Row],[Details]])))),"Investment Return", IF(OR(ISNUMBER(SEARCH("LOAN",Account_Data[[#This Row],[Details]])),ISNUMBER(SEARCH("RECOVERY",Account_Data[[#This Row],[Details]]))),"Loan Payment", IF(OR(ISNUMBER(SEARCH("SALARY",Account_Data[[#This Row],[Details]])),ISNUMBER(SEARCH("EMPLOYER DEP",Account_Data[[#This Row],[Details]]))),"Income", IF(OR(ISNUMBER(SEARCH("ACH",Account_Data[[#This Row],[Details]])),ISNUMBER(SEARCH("DIRECT DR",Account_Data[[#This Row],[Details]]))),"EMI", IF(ISNUMBER(SEARCH("ATM",Account_Data[[#This Row],[Details]])),"Cash", IF(ISNUMBER(SEARCH("UPI",Account_Data[[#This Row],[Details]])),"UPI Expense",IF(ISNUMBER(SEARCH("W TFR",Account_Data[[#This Row],[Details]])),"Transfer","Other"))))))))) -> Cash | I99: =Account_Data[[#This Row],[Credit]]-Account_Data[[#This Row],[Debit]] -> -1000 | J99: =EOMONTH(Account_Data[[#This Row],[Date]],0) -> 45808 | K99: =ABS(Account_Data[[#This Row],[Amount]]) -> 1000
A100: 45787 | B100: ATM W ATM CASH SAR AS MOTEL SECOND ATMRAE BARELI | C100: 10000 | E100: 24534.6 | F100: =TEXT(Account_Data[[#This Row],[Date]],"mmm-yyyy") -> May-2025 | G100: =IF(Account_Data[[#This Row],[Credit]]>0,"Income","Expense") -> Expense | H100: =IF(AND(Account_Data[[#This Row],[Credit]]>0,ISNUMBER(SEARCH("TFR",Account_Data[[#This Row],[Details]])),Account_Data[[#This Row],[Credit]]>=200000),"Loan Taken", IF(AND(Account_Data[[#This Row],[Debit]]>0,OR(ISNUMBER(SEARCH("ETMONEY",Account_Data[[#This Row],[Details]])),ISNUMBER(SEARCH("PGIM",Account_Data[[#This Row],[Details]])),ISNUMBER(SEARCH("CANARA",Account_Data[[#This Row],[Details]])))),"Investment (Outflow)", IF(AND(Account_Data[[#This Row],[Credit]]>0,OR(ISNUMBER(SEARCH("PGIM",Account_Data[[#This Row],[Details]])),ISNUMBER(SEARCH("CANARA",Account_Data[[#This Row],[Details]])),ISNUMBER(SEARCH("MUTUAL",Account_Data[[#This Row],[Details]])))),"Investment Return", IF(OR(ISNUMBER(SEARCH("LOAN",Account_Data[[#This Row],[Details]])),ISNUMBER(SEARCH("RECOVERY",Account_Data[[#This Row],[Details]]))),"Loan Payment", IF(OR(ISNUMBER(SEARCH("SALARY",Account_Data[[#This Row],[Details]])),ISNUMBER(SEARCH("EMPLOYER DEP",Account_Data[[#This Row],[Details]]))),"Income", IF(OR(ISNUMBER(SEARCH("ACH",Account_Data[[#This Row],[Details]])),ISNUMBER(SEARCH("DIRECT DR",Account_Data[[#This Row],[Details]]))),"EMI", IF(ISNUMBER(SEARCH("ATM",Account_Data[[#This Row],[Details]])),"Cash", IF(ISNUMBER(SEARCH("UPI",Account_Data[[#This Row],[Details]])),"UPI Expense",IF(ISNUMBER(SEARCH("W TFR",Account_Data[[#This Row],[Details]])),"Transfer","Other"))))))))) -> Cash | I100: =Account_Data[[#This Row],[Credit]]-Account_Data[[#This Row],[Debit]] -> -10000 | J100: =EOMONTH(Account_Data[[#This Row],[Date]],0) -> 45808 | K100: =ABS(Account_Data[[#This Row],[Amount]]) -> 10000
A101: 45788 | B101: W TFR UPI/DR//HP Auto /YESB/paytmqrmnh/P aym AT | C101: 1500 | E101: 23034.6 | F101: =TEXT(Account_Data[[#This Row],[Date]],"mmm-yyyy") -> May-2025 | G101: =IF(Account_Data[[#This Row],[Credit]]>0,"Income","Expense") -> Expense | H101: =IF(AND(Account_Data[[#This Row],[Credit]]>0,ISNUMBER(SEARCH("TFR",Account_Data[[#This Row],[Details]])),Account_Data[[#This Row],[Credit]]>=200000),"Loan Taken", IF(AND(Account_Data[[#This Row],[Debit]]>0,OR(ISNUMBER(SEARCH("ETMONEY",Account_Data[[#This Row],[Details]])),ISNUMBER(SEARCH("PGIM",Account_Data[[#This Row],[Details]])),ISNUMBER(SEARCH("CANARA",Account_Data[[#This Row],[Details]])))),"Investment (Outflow)", IF(AND(Account_Data[[#This Row],[Credit]]>0,OR(ISNUMBER(SEARCH("PGIM",Account_Data[[#This Row],[Details]])),ISNUMBER(SEARCH("CANARA",Account_Data[[#This Row],[Details]])),ISNUMBER(SEARCH("MUTUAL",Account_Data[[#This Row],[Details]])))),"Investment Return", IF(OR(ISNUMBER(SEARCH("LOAN",Account_Data[[#This Row],[Details]])),ISNUMBER(SEARCH("RECOVERY",Account_Data[[#This Row],[Details]]))),"Loan Payment", IF(OR(ISNUMBER(SEARCH("SALARY",Account_Data[[#This Row],[Details]])),ISNUMBER(SEARCH("EMPLOYER DEP",Account_Data[[#This Row],[Details]]))),"Income", IF(OR(ISNUMBER(SEARCH("ACH",Account_Data[[#This Row],[Details]])),ISNUMBER(SEARCH("DIRECT DR",Account_Data[[#This Row],[Details]]))),"EMI", IF(ISNUMBER(SEARCH("ATM",Account_Data[[#This Row],[Details]])),"Cash", IF(ISNUMBER(SEARCH("UPI",Account_Data[[#This Row],[Details]])),"UPI Expense",IF(ISNUMBER(SEARCH("W TFR",Account_Data[[#This Row],[Details]])),"Transfer","Other"))))))))) -> UPI Expense | I101: =Account_Data[[#This Row],[Credit]]-Account_Data[[#This Row],[Debit]] -> -1500 | J101: =EOMONTH(Account_Data[[#This Row],[Date]],0) -> 45808 | K101: =ABS(Account_Data[[#This Row],[Amount]]) -> 1500
A102: 45789 | B102: W TFR UPI/DR//IRCTC Ra/UTIB/IRCTCRAILW/P aym AT | C102: 505 | E102: 22529.6 | F102: =TEXT(Account_Data[[#This Row],[Date]],"mmm-yyyy") -> May-2025 | G102: =IF(Account_Data[[#This Row],[Credit]]>0,"Income","Expense") -> Expense | H102: =IF(AND(Account_Data[[#This Row],[Credit]]>0,ISNUMBER(SEARCH("TFR",Account_Data[[#This Row],[Details]])),Account_Data[[#This Row],[Credit]]>=200000),"Loan Taken", IF(AND(Account_Data[[#This Row],[Debit]]>0,OR(ISNUMBER(SEARCH("ETMONEY",Account_Data[[#This Row],[Details]])),ISNUMBER(SEARCH("PGIM",Account_Data[[#This Row],[Details]])),ISNUMBER(SEARCH("CANARA",Account_Data[[#This Row],[Details]])))),"Investment (Outflow)", IF(AND(Account_Data[[#This Row],[Credit]]>0,OR(ISNUMBER(SEARCH("PGIM",Account_Data[[#This Row],[Details]])),ISNUMBER(SEARCH("CANARA",Account_Data[[#This Row],[Details]])),ISNUMBER(SEARCH("MUTUAL",Account_Data[[#This Row],[Details]])))),"Investment Return", IF(OR(ISNUMBER(SEARCH("LOAN",Account_Data[[#This Row],[Details]])),ISNUMBER(SEARCH("RECOVERY",Account_Data[[#This Row],[Details]]))),"Loan Payment", IF(OR(ISNUMBER(SEARCH("SALARY",Account_Data[[#This Row],[Details]])),ISNUMBER(SEARCH("EMPLOYER DEP",Account_Data[[#This Row],[Details]]))),"Income", IF(OR(ISNUMBER(SEARCH("ACH",Account_Data[[#This Row],[Details]])),ISNUMBER(SEARCH("DIRECT DR",Account_Data[[#This Row],[Details]]))),"EMI", IF(ISNUMBER(SEARCH("ATM",Account_Data[[#This Row],[Details]])),"Cash", IF(ISNUMBER(SEARCH("UPI",Account_Data[[#This Row],[Details]])),"UPI Expense",IF(ISNUMBER(SEARCH("W TFR",Account_Data[[#This Row],[Details]])),"Transfer","Other"))))))))) -> UPI Expense | I102: =Account_Data[[#This Row],[Credit]]-Account_Data[[#This Row],[Debit]] -> -505 | J102: =EOMONTH(Account_Data[[#This Row],[Date]],0) -> 45808 | K102: =ABS(Account_Data[[#This Row],[Amount]]) -> 505
A103: 45790 | B103: ECS/ACH RET CH PHYSICSW NACH FA IL INSUF BAL SBIN | C103: 295 | E103: 22234.6 | F103: =TEXT(Account_Data[[#This Row],[Date]],"mmm-yyyy") -> May-2025 | G103: =IF(Account_Data[[#This Row],[Credit]]>0,"Income","Expense") -> Expense | H103: =IF(AND(Account_Data[[#This Row],[Credit]]>0,ISNUMBER(SEARCH("TFR",Account_Data[[#This Row],[Details]])),Account_Data[[#This Row],[Credit]]>=200000),"Loan Taken", IF(AND(Account_Data[[#This Row],[Debit]]>0,OR(ISNUMBER(SEARCH("ETMONEY",Account_Data[[#This Row],[Details]])),ISNUMBER(SEARCH("PGIM",Account_Data[[#This Row],[Details]])),ISNUMBER(SEARCH("CANARA",Account_Data[[#This Row],[Details]])))),"Investment (Outflow)", IF(AND(Account_Data[[#This Row],[Credit]]>0,OR(ISNUMBER(SEARCH("PGIM",Account_Data[[#This Row],[Details]])),ISNUMBER(SEARCH("CANARA",Account_Data[[#This Row],[Details]])),ISNUMBER(SEARCH("MUTUAL",Account_Data[[#This Row],[Details]])))),"Investment Return", IF(OR(ISNUMBER(SEARCH("LOAN",Account_Data[[#This Row],[Details]])),ISNUMBER(SEARCH("RECOVERY",Account_Data[[#This Row],[Details]]))),"Loan Payment", IF(OR(ISNUMBER(SEARCH("SALARY",Account_Data[[#This Row],[Details]])),ISNUMBER(SEARCH("EMPLOYER DEP",Account_Data[[#This Row],[Details]]))),"Income", IF(OR(ISNUMBER(SEARCH("ACH",Account_Data[[#This Row],[Details]])),ISNUMBER(SEARCH("DIRECT DR",Account_Data[[#This Row],[Details]]))),"EMI", IF(ISNUMBER(SEARCH("ATM",Account_Data[[#This Row],[Details]])),"Cash", IF(ISNUMBER(SEARCH("UPI",Account_Data[[#This Row],[Details]])),"UPI Expense",IF(ISNUMBER(SEARCH("W TFR",Account_Data[[#This Row],[Details]])),"Transfer","Other"))))))))) -> EMI | I103: =Account_Data[[#This Row],[Credit]]-Account_Data[[#This Row],[Debit]] -> -295 | J103: =EOMONTH(Account_Data[[#This Row],[Date]],0) -> 45808 | K103: =ABS(Account_Data[[#This Row],[Amount]]) -> 295
A104: 45791 | B104: W TFR UPI/DR//NALIN SI/DBSS/nalinbisen/P aym AT | C104: 424 | E104: 21810.6 | F104: =TEXT(Account_Data[[#This Row],[Date]],"mmm-yyyy") -> May-2025 | G104: =IF(Account_Data[[#This Row],[Credit]]>0,"Income","Expense") -> Expense | H104: =IF(AND(Account_Data[[#This Row],[Credit]]>0,ISNUMBER(SEARCH("TFR",Account_Data[[#This Row],[Details]])),Account_Data[[#This Row],[Credit]]>=200000),"Loan Taken", IF(AND(Account_Data[[#This Row],[Debit]]>0,OR(ISNUMBER(SEARCH("ETMONEY",Account_Data[[#This Row],[Details]])),ISNUMBER(SEARCH("PGIM",Account_Data[[#This Row],[Details]])),ISNUMBER(SEARCH("CANARA",Account_Data[[#This Row],[Details]])))),"Investment (Outflow)", IF(AND(Account_Data[[#This Row],[Credit]]>0,OR(ISNUMBER(SEARCH("PGIM",Account_Data[[#This Row],[Details]])),ISNUMBER(SEARCH("CANARA",Account_Data[[#This Row],[Details]])),ISNUMBER(SEARCH("MUTUAL",Account_Data[[#This Row],[Details]])))),"Investment Return", IF(OR(ISNUMBER(SEARCH("LOAN",Account_Data[[#This Row],[Details]])),ISNUMBER(SEARCH("RECOVERY",Account_Data[[#This Row],[Details]]))),"Loan Payment", IF(OR(ISNUMBER(SEARCH("SALARY",Account_Data[[#This Row],[Details]])),ISNUMBER(SEARCH("EMPLOYER DEP",Account_Data[[#This Row],[Details]]))),"Income", IF(OR(ISNUMBER(SEARCH("ACH",Account_Data[[#This Row],[Details]])),ISNUMBER(SEARCH("DIRECT DR",Account_Data[[#This Row],[Details]]))),"EMI", IF(ISNUMBER(SEARCH("ATM",Account_Data[[#This Row],[Details]])),"Cash", IF(ISNUMBER(SEARCH("UPI",Account_Data[[#This Row],[Details]])),"UPI Expense",IF(ISNUMBER(SEARCH("W TFR",Account_Data[[#This Row],[Details]])),"Transfer","Other"))))))))) -> UPI Expense | I104: =Account_Data[[#This Row],[Credit]]-Account_Data[[#This Row],[Debit]] -> -424 | J104: =EOMONTH(Account_Data[[#This Row],[Date]],0) -> 45808 | K104: =ABS(Account_Data[[#This Row],[Amount]]) -> 424
A105: 45792 | B105: ATM W ATM CASH W | C105: 5000 | E105: 16810.6 | F105: =TEXT(Account_Data[[#This Row],[Date]],"mmm-yyyy") -> May-2025 | G105: =IF(Account_Data[[#This Row],[Credit]]>0,"Income","Expense") -> Expense | H105: =IF(AND(Account_Data[[#This Row],[Credit]]>0,ISNUMBER(SEARCH("TFR",Account_Data[[#This Row],[Details]])),Account_Data[[#This Row],[Credit]]>=200000),"Loan Taken", IF(AND(Account_Data[[#This Row],[Debit]]>0,OR(ISNUMBER(SEARCH("ETMONEY",Account_Data[[#This Row],[Details]])),ISNUMBER(SEARCH("PGIM",Account_Data[[#This Row],[Details]])),ISNUMBER(SEARCH("CANARA",Account_Data[[#This Row],[Details]])))),"Investment (Outflow)", IF(AND(Account_Data[[#This Row],[Credit]]>0,OR(ISNUMBER(SEARCH("PGIM",Account_Data[[#This Row],[Details]])),ISNUMBER(SEARCH("CANARA",Account_Data[[#This Row],[Details]])),ISNUMBER(SEARCH("MUTUAL",Account_Data[[#This Row],[Details]])))),"Investment Return", IF(OR(ISNUMBER(SEARCH("LOAN",Account_Data[[#This Row],[Details]])),ISNUMBER(SEARCH("RECOVERY",Account_Data[[#This Row],[Details]]))),"Loan Payment", IF(OR(ISNUMBER(SEARCH("SALARY",Account_Data[[#This Row],[Details]])),ISNUMBER(SEARCH("EMPLOYER DEP",Account_Data[[#This Row],[Details]]))),"Income", IF(OR(ISNUMBER(SEARCH("ACH",Account_Data[[#This Row],[Details]])),ISNUMBER(SEARCH("DIRECT DR",Account_Data[[#This Row],[Details]]))),"EMI", IF(ISNUMBER(SEARCH("ATM",Account_Data[[#This Row],[Details]])),"Cash", IF(ISNUMBER(SEARCH("UPI",Account_Data[[#This Row],[Details]])),"UPI Expense",IF(ISNUMBER(SEARCH("W TFR",Account_Data[[#This Row],[Details]])),"Transfer","Other"))))))))) -> Cash | I105: =Account_Data[[#This Row],[Credit]]-Account_Data[[#This Row],[Debit]] -> -5000 | J105: =EOMONTH(Account_Data[[#This Row],[Date]],0) -> 45808 | K105: =ABS(Account_Data[[#This Row],[Amount]]) -> 5000
A106: 45792 | B106: W TFR UPI/DR//AFJALANS/YESB/Q/P aym AT | C106: 10 | E106: 16800.6 | F106: =TEXT(Account_Data[[#This Row],[Date]],"mmm-yyyy") -> May-2025 | G106: =IF(Account_Data[[#This Row],[Credit]]>0,"Income","Expense") -> Expense | H106: =IF(AND(Account_Data[[#This Row],[Credit]]>0,ISNUMBER(SEARCH("TFR",Account_Data[[#This Row],[Details]])),Account_Data[[#This Row],[Credit]]>=200000),"Loan Taken", IF(AND(Account_Data[[#This Row],[Debit]]>0,OR(ISNUMBER(SEARCH("ETMONEY",Account_Data[[#This Row],[Details]])),ISNUMBER(SEARCH("PGIM",Account_Data[[#This Row],[Details]])),ISNUMBER(SEARCH("CANARA",Account_Data[[#This Row],[Details]])))),"Investment (Outflow)", IF(AND(Account_Data[[#This Row],[Credit]]>0,OR(ISNUMBER(SEARCH("PGIM",Account_Data[[#This Row],[Details]])),ISNUMBER(SEARCH("CANARA",Account_Data[[#This Row],[Details]])),ISNUMBER(SEARCH("MUTUAL",Account_Data[[#This Row],[Details]])))),"Investment Return", IF(OR(ISNUMBER(SEARCH("LOAN",Account_Data[[#This Row],[Details]])),ISNUMBER(SEARCH("RECOVERY",Account_Data[[#This Row],[Details]]))),"Loan Payment", IF(OR(ISNUMBER(SEARCH("SALARY",Account_Data[[#This Row],[Details]])),ISNUMBER(SEARCH("EMPLOYER DEP",Account_Data[[#This Row],[Details]]))),"Income", IF(OR(ISNUMBER(SEARCH("ACH",Account_Data[[#This Row],[Details]])),ISNUMBER(SEARCH("DIRECT DR",Account_Data[[#This Row],[Details]]))),"EMI", IF(ISNUMBER(SEARCH("ATM",Account_Data[[#This Row],[Details]])),"Cash", IF(ISNUMBER(SEARCH("UPI",Account_Data[[#This Row],[Details]])),"UPI Expense",IF(ISNUMBER(SEARCH("W TFR",Account_Data[[#This Row],[Details]])),"Transfer","Other"))))))))) -> UPI Expense | I106: =Account_Data[[#This Row],[Credit]]-Account_Data[[#This Row],[Debit]] -> -10 | J106: =EOMONTH(Account_Data[[#This Row],[Date]],0) -> 45808 | K106: =ABS(Account_Data[[#This Row],[Amount]]) -> 10
A107: 45793 | B107: CSH DEP (CDM) | D107: 10000 | E107: 26800.6 | F107: =TEXT(Account_Data[[#This Row],[Date]],"mmm-yyyy") -> May-2025 | G107: =IF(Account_Data[[#This Row],[Credit]]>0,"Income","Expense") -> Income | H107: =IF(AND(Account_Data[[#This Row],[Credit]]>0,ISNUMBER(SEARCH("TFR",Account_Data[[#This Row],[Details]])),Account_Data[[#This Row],[Credit]]>=200000),"Loan Taken", IF(AND(Account_Data[[#This Row],[Debit]]>0,OR(ISNUMBER(SEARCH("ETMONEY",Account_Data[[#This Row],[Details]])),ISNUMBER(SEARCH("PGIM",Account_Data[[#This Row],[Details]])),ISNUMBER(SEARCH("CANARA",Account_Data[[#This Row],[Details]])))),"Investment (Outflow)", IF(AND(Account_Data[[#This Row],[Credit]]>0,OR(ISNUMBER(SEARCH("PGIM",Account_Data[[#This Row],[Details]])),ISNUMBER(SEARCH("CANARA",Account_Data[[#This Row],[Details]])),ISNUMBER(SEARCH("MUTUAL",Account_Data[[#This Row],[Details]])))),"Investment Return", IF(OR(ISNUMBER(SEARCH("LOAN",Account_Data[[#This Row],[Details]])),ISNUMBER(SEARCH("RECOVERY",Account_Data[[#This Row],[Details]]))),"Loan Payment", IF(OR(ISNUMBER(SEARCH("SALARY",Account_Data[[#This Row],[Details]])),ISNUMBER(SEARCH("EMPLOYER DEP",Account_Data[[#This Row],[Details]]))),"Income", IF(OR(ISNUMBER(SEARCH("ACH",Account_Data[[#This Row],[Details]])),ISNUMBER(SEARCH("DIRECT DR",Account_Data[[#This Row],[Details]]))),"EMI", IF(ISNUMBER(SEARCH("ATM",Account_Data[[#This Row],[Details]])),"Cash", IF(ISNUMBER(SEARCH("UPI",Account_Data[[#This Row],[Details]])),"UPI Expense",IF(ISNUMBER(SEARCH("W TFR",Account_Data[[#This Row],[Details]])),"Transfer","Other"))))))))) -> Other | I107: =Account_Data[[#This Row],[Credit]]-Account_Data[[#This Row],[Debit]] -> 10000 | J107: =EOMONTH(Account_Data[[#This Row],[Date]],0) -> 45808 | K107: =ABS(Account_Data[[#This Row],[Amount]]) -> 10000
A108: 45793 | B108: CDM CH ARGE DR | C108: 47.2 | E108: 26753.4 | F108: =TEXT(Account_Data[[#This Row],[Date]],"mmm-yyyy") -> May-2025 | G108: =IF(Account_Data[[#This Row],[Credit]]>0,"Income","Expense") -> Expense | H108: =IF(AND(Account_Data[[#This Row],[Credit]]>0,ISNUMBER(SEARCH("TFR",Account_Data[[#This Row],[Details]])),Account_Data[[#This Row],[Credit]]>=200000),"Loan Taken", IF(AND(Account_Data[[#This Row],[Debit]]>0,OR(ISNUMBER(SEARCH("ETMONEY",Account_Data[[#This Row],[Details]])),ISNUMBER(SEARCH("PGIM",Account_Data[[#This Row],[Details]])),ISNUMBER(SEARCH("CANARA",Account_Data[[#This Row],[Details]])))),"Investment (Outflow)", IF(AND(Account_Data[[#This Row],[Credit]]>0,OR(ISNUMBER(SEARCH("PGIM",Account_Data[[#This Row],[Details]])),ISNUMBER(SEARCH("CANARA",Account_Data[[#This Row],[Details]])),ISNUMBER(SEARCH("MUTUAL",Account_Data[[#This Row],[Details]])))),"Investment Return", IF(OR(ISNUMBER(SEARCH("LOAN",Account_Data[[#This Row],[Details]])),ISNUMBER(SEARCH("RECOVERY",Account_Data[[#This Row],[Details]]))),"Loan Payment", IF(OR(ISNUMBER(SEARCH("SALARY",Account_Data[[#This Row],[Details]])),ISNUMBER(SEARCH("EMPLOYER DEP",Account_Data[[#This Row],[Details]]))),"Income", IF(OR(ISNUMBER(SEARCH("ACH",Account_Data[[#This Row],[Details]])),ISNUMBER(SEARCH("DIRECT DR",Account_Data[[#This Row],[Details]]))),"EMI", IF(ISNUMBER(SEARCH("ATM",Account_Data[[#This Row],[Details]])),"Cash", IF(ISNUMBER(SEARCH("UPI",Account_Data[[#This Row],[Details]])),"UPI Expense",IF(ISNUMBER(SEARCH("W TFR",Account_Data[[#This Row],[Details]])),"Transfer","Other"))))))))) -> Other | I108: =Account_Data[[#This Row],[Credit]]-Account_Data[[#This Row],[Debit]] -> -47.2 | J108: =EOMONTH(Account_Data[[#This Row],[Date]],0) -> 45808 | K108: =ABS(Account_Data[[#This Row],[Amount]]) -> 47.2
A109: 45793 | B109: DEP TFR UPI/CR//SUMAN S/SBIN//P aym AT | D109: 1200 | E109: 27953.4 | F109: =TEXT(Account_Data[[#This Row],[Date]],"mmm-yyyy") -> May-2025 | G109: =IF(Account_Data[[#This Row],[Credit]]>0,"Income","Expense") -> Income | H109: =IF(AND(Account_Data[[#This Row],[Credit]]>0,ISNUMBER(SEARCH("TFR",Account_Data[[#This Row],[Details]])),Account_Data[[#This Row],[Credit]]>=200000),"Loan Taken", IF(AND(Account_Data[[#This Row],[Debit]]>0,OR(ISNUMBER(SEARCH("ETMONEY",Account_Data[[#This Row],[Details]])),ISNUMBER(SEARCH("PGIM",Account_Data[[#This Row],[Details]])),ISNUMBER(SEARCH("CANARA",Account_Data[[#This Row],[Details]])))),"Investment (Outflow)", IF(AND(Account_Data[[#This Row],[Credit]]>0,OR(ISNUMBER(SEARCH("PGIM",Account_Data[[#This Row],[Details]])),ISNUMBER(SEARCH("CANARA",Account_Data[[#This Row],[Details]])),ISNUMBER(SEARCH("MUTUAL",Account_Data[[#This Row],[Details]])))),"Investment Return", IF(OR(ISNUMBER(SEARCH("LOAN",Account_Data[[#This Row],[Details]])),ISNUMBER(SEARCH("RECOVERY",Account_Data[[#This Row],[Details]]))),"Loan Payment", IF(OR(ISNUMBER(SEARCH("SALARY",Account_Data[[#This Row],[Details]])),ISNUMBER(SEARCH("EMPLOYER DEP",Account_Data[[#This Row],[Details]]))),"Income", IF(OR(ISNUMBER(SEARCH("ACH",Account_Data[[#This Row],[Details]])),ISNUMBER(SEARCH("DIRECT DR",Account_Data[[#This Row],[Details]]))),"EMI", IF(ISNUMBER(SEARCH("ATM",Account_Data[[#This Row],[Details]])),"Cash", IF(ISNUMBER(SEARCH("UPI",Account_Data[[#This Row],[Details]])),"UPI Expense",IF(ISNUMBER(SEARCH("W TFR",Account_Data[[#This Row],[Details]])),"Transfer","Other"))))))))) -> UPI Expense | I109: =Account_Data[[#This Row],[Credit]]-Account_Data[[#This Row],[Debit]] -> 1200 | J109: =EOMONTH(Account_Data[[#This Row],[Date]],0) -> 45808 | K109: =ABS(Account_Data[[#This Row],[Amount]]) -> 1200
A110: 45794 | B110: DEP TFR UPI/CR//SUMAN S/SBIN//P aym AT | D110: 200 | E110: 28153.4 | F110: =TEXT(Account_Data[[#This Row],[Date]],"mmm-yyyy") -> May-2025 | G110: =IF(Account_Data[[#This Row],[Credit]]>0,"Income","Expense") -> Income | H110: =IF(AND(Account_Data[[#This Row],[Credit]]>0,ISNUMBER(SEARCH("TFR",Account_Data[[#This Row],[Details]])),Account_Data[[#This Row],[Credit]]>=200000),"Loan Taken", IF(AND(Account_Data[[#This Row],[Debit]]>0,OR(ISNUMBER(SEARCH("ETMONEY",Account_Data[[#This Row],[Details]])),ISNUMBER(SEARCH("PGIM",Account_Data[[#This Row],[Details]])),ISNUMBER(SEARCH("CANARA",Account_Data[[#This Row],[Details]])))),"Investment (Outflow)", IF(AND(Account_Data[[#This Row],[Credit]]>0,OR(ISNUMBER(SEARCH("PGIM",Account_Data[[#This Row],[Details]])),ISNUMBER(SEARCH("CANARA",Account_Data[[#This Row],[Details]])),ISNUMBER(SEARCH("MUTUAL",Account_Data[[#This Row],[Details]])))),"Investment Return", IF(OR(ISNUMBER(SEARCH("LOAN",Account_Data[[#This Row],[Details]])),ISNUMBER(SEARCH("RECOVERY",Account_Data[[#This Row],[Details]]))),"Loan Payment", IF(OR(ISNUMBER(SEARCH("SALARY",Account_Data[[#This Row],[Details]])),ISNUMBER(SEARCH("EMPLOYER DEP",Account_Data[[#This Row],[Details]]))),"Income", IF(OR(ISNUMBER(SEARCH("ACH",Account_Data[[#This Row],[Details]])),ISNUMBER(SEARCH("DIRECT DR",Account_Data[[#This Row],[Details]]))),"EMI", IF(ISNUMBER(SEARCH("ATM",Account_Data[[#This Row],[Details]])),"Cash", IF(ISNUMBER(SEARCH("UPI",Account_Data[[#This Row],[Details]])),"UPI Expense",IF(ISNUMBER(SEARCH("W TFR",Account_Data[[#This Row],[Details]])),"Transfer","Other"))))))))) -> UPI Expense | I110: =Account_Data[[#This Row],[Credit]]-Account_Data[[#This Row],[Debit]] -> 200 | J110: =EOMONTH(Account_Data[[#This Row],[Date]],0) -> 45808 | K110: =ABS(Account_Data[[#This Row],[Amount]]) -> 200
A111: 45797 | B111: DEP TFR NEFT*HDFC*HDFCH*MIRAE ASSET MF AT | D111: 4947.65 | E111: 33101.05 | F111: =TEXT(Account_Data[[#This Row],[Date]],"mmm-yyyy") -> May-2025 | G111: =IF(Account_Data[[#This Row],[Credit]]>0,"Income","Expense") -> Income | H111: =IF(AND(Account_Data[[#This Row],[Credit]]>0,ISNUMBER(SEARCH("TFR",Account_Data[[#This Row],[Details]])),Account_Data[[#This Row],[Credit]]>=200000),"Loan Taken", IF(AND(Account_Data[[#This Row],[Debit]]>0,OR(ISNUMBER(SEARCH("ETMONEY",Account_Data[[#This Row],[Details]])),ISNUMBER(SEARCH("PGIM",Account_Data[[#This Row],[Details]])),ISNUMBER(SEARCH("CANARA",Account_Data[[#This Row],[Details]])))),"Investment (Outflow)", IF(AND(Account_Data[[#This Row],[Credit]]>0,OR(ISNUMBER(SEARCH("PGIM",Account_Data[[#This Row],[Details]])),ISNUMBER(SEARCH("CANARA",Account_Data[[#This Row],[Details]])),ISNUMBER(SEARCH("MUTUAL",Account_Data[[#This Row],[Details]])))),"Investment Return", IF(OR(ISNUMBER(SEARCH("LOAN",Account_Data[[#This Row],[Details]])),ISNUMBER(SEARCH("RECOVERY",Account_Data[[#This Row],[Details]]))),"Loan Payment", IF(OR(ISNUMBER(SEARCH("SALARY",Account_Data[[#This Row],[Details]])),ISNUMBER(SEARCH("EMPLOYER DEP",Account_Data[[#This Row],[Details]]))),"Income", IF(OR(ISNUMBER(SEARCH("ACH",Account_Data[[#This Row],[Details]])),ISNUMBER(SEARCH("DIRECT DR",Account_Data[[#This Row],[Details]]))),"EMI", IF(ISNUMBER(SEARCH("ATM",Account_Data[[#This Row],[Details]])),"Cash", IF(ISNUMBER(SEARCH("UPI",Account_Data[[#This Row],[Details]])),"UPI Expense",IF(ISNUMBER(SEARCH("W TFR",Account_Data[[#This Row],[Details]])),"Transfer","Other"))))))))) -> Other | I111: =Account_Data[[#This Row],[Credit]]-Account_Data[[#This Row],[Debit]] -> 4947.65 | J111: =EOMONTH(Account_Data[[#This Row],[Date]],0) -> 45808 | K111: =ABS(Account_Data[[#This Row],[Amount]]) -> 4947.65
A112: 45797 | B112: DEP TFR NEFT*HDFC*HDFCH*HDFC MUTUAL FUN AT | D112: 90774.84 | E112: 123875.89 | F112: =TEXT(Account_Data[[#This Row],[Date]],"mmm-yyyy") -> May-2025 | G112: =IF(Account_Data[[#This Row],[Credit]]>0,"Income","Expense") -> Income | H112: =IF(AND(Account_Data[[#This Row],[Credit]]>0,ISNUMBER(SEARCH("TFR",Account_Data[[#This Row],[Details]])),Account_Data[[#This Row],[Credit]]>=200000),"Loan Taken", IF(AND(Account_Data[[#This Row],[Debit]]>0,OR(ISNUMBER(SEARCH("ETMONEY",Account_Data[[#This Row],[Details]])),ISNUMBER(SEARCH("PGIM",Account_Data[[#This Row],[Details]])),ISNUMBER(SEARCH("CANARA",Account_Data[[#This Row],[Details]])))),"Investment (Outflow)", IF(AND(Account_Data[[#This Row],[Credit]]>0,OR(ISNUMBER(SEARCH("PGIM",Account_Data[[#This Row],[Details]])),ISNUMBER(SEARCH("CANARA",Account_Data[[#This Row],[Details]])),ISNUMBER(SEARCH("MUTUAL",Account_Data[[#This Row],[Details]])))),"Investment Return", IF(OR(ISNUMBER(SEARCH("LOAN",Account_Data[[#This Row],[Details]])),ISNUMBER(SEARCH("RECOVERY",Account_Data[[#This Row],[Details]]))),"Loan Payment", IF(OR(ISNUMBER(SEARCH("SALARY",Account_Data[[#This Row],[Details]])),ISNUMBER(SEARCH("EMPLOYER DEP",Account_Data[[#This Row],[Details]]))),"Income", IF(OR(ISNUMBER(SEARCH("ACH",Account_Data[[#This Row],[Details]])),ISNUMBER(SEARCH("DIRECT DR",Account_Data[[#This Row],[Details]]))),"EMI", IF(ISNUMBER(SEARCH("ATM",Account_Data[[#This Row],[Details]])),"Cash", IF(ISNUMBER(SEARCH("UPI",Account_Data[[#This Row],[Details]])),"UPI Expense",IF(ISNUMBER(SEARCH("W TFR",Account_Data[[#This Row],[Details]])),"Transfer","Other"))))))))) -> Investment Return | I112: =Account_Data[[#This Row],[Credit]]-Account_Data[[#This Row],[Debit]] -> 90774.84 | J112: =EOMONTH(Account_Data[[#This Row],[Date]],0) -> 45808 | K112: =ABS(Account_Data[[#This Row],[Amount]]) -> 90774.84
A113: 45797 | B113: DEP TFR NEFT*UTIB*AXISCN*AXIS MUTUAL FUN AT | D113: 2953.91 | E113: 126829.8 | F113: =TEXT(Account_Data[[#This Row],[Date]],"mmm-yyyy") -> May-2025 | G113: =IF(Account_Data[[#This Row],[Credit]]>0,"Income","Expense") -> Income | H113: =IF(AND(Account_Data[[#This Row],[Credit]]>0,ISNUMBER(SEARCH("TFR",Account_Data[[#This Row],[Details]])),Account_Data[[#This Row],[Credit]]>=200000),"Loan Taken", IF(AND(Account_Data[[#This Row],[Debit]]>0,OR(ISNUMBER(SEARCH("ETMONEY",Account_Data[[#This Row],[Details]])),ISNUMBER(SEARCH("PGIM",Account_Data[[#This Row],[Details]])),ISNUMBER(SEARCH("CANARA",Account_Data[[#This Row],[Details]])))),"Investment (Outflow)", IF(AND(Account_Data[[#This Row],[Credit]]>0,OR(ISNUMBER(SEARCH("PGIM",Account_Data[[#This Row],[Details]])),ISNUMBER(SEARCH("CANARA",Account_Data[[#This Row],[Details]])),ISNUMBER(SEARCH("MUTUAL",Account_Data[[#This Row],[Details]])))),"Investment Return", IF(OR(ISNUMBER(SEARCH("LOAN",Account_Data[[#This Row],[Details]])),ISNUMBER(SEARCH("RECOVERY",Account_Data[[#This Row],[Details]]))),"Loan Payment", IF(OR(ISNUMBER(SEARCH("SALARY",Account_Data[[#This Row],[Details]])),ISNUMBER(SEARCH("EMPLOYER DEP",Account_Data[[#This Row],[Details]]))),"Income", IF(OR(ISNUMBER(SEARCH("ACH",Account_Data[[#This Row],[Details]])),ISNUMBER(SEARCH("DIRECT DR",Account_Data[[#This Row],[Details]]))),"EMI", IF(ISNUMBER(SEARCH("ATM",Account_Data[[#This Row],[Details]])),"Cash", IF(ISNUMBER(SEARCH("UPI",Account_Data[[#This Row],[Details]])),"UPI Expense",IF(ISNUMBER(SEARCH("W TFR",Account_Data[[#This Row],[Details]])),"Transfer","Other"))))))))) -> Investment Return | I113: =Account_Data[[#This Row],[Credit]]-Account_Data[[#This Row],[Debit]] -> 2953.91 | J113: =EOMONTH(Account_Data[[#This Row],[Date]],0) -> 45808 | K113: =ABS(Account_Data[[#This Row],[Amount]]) -> 2953.91
A114: 45798 | B114: W TFR UPI/DR//SOMAN T/SBIN//P aym AT | C114: 300 | E114: 126529.8 | F114: =TEXT(Account_Data[[#This Row],[Date]],"mmm-yyyy") -> May-2025 | G114: =IF(Account_Data[[#This Row],[Credit]]>0,"Income","Expense") -> Expense | H114: =IF(AND(Account_Data[[#This Row],[Credit]]>0,ISNUMBER(SEARCH("TFR",Account_Data[[#This Row],[Details]])),Account_Data[[#This Row],[Credit]]>=200000),"Loan Taken", IF(AND(Account_Data[[#This Row],[Debit]]>0,OR(ISNUMBER(SEARCH("ETMONEY",Account_Data[[#This Row],[Details]])),ISNUMBER(SEARCH("PGIM",Account_Data[[#This Row],[Details]])),ISNUMBER(SEARCH("CANARA",Account_Data[[#This Row],[Details]])))),"Investment (Outflow)", IF(AND(Account_Data[[#This Row],[Credit]]>0,OR(ISNUMBER(SEARCH("PGIM",Account_Data[[#This Row],[Details]])),ISNUMBER(SEARCH("CANARA",Account_Data[[#This Row],[Details]])),ISNUMBER(SEARCH("MUTUAL",Account_Data[[#This Row],[Details]])))),"Investment Return", IF(OR(ISNUMBER(SEARCH("LOAN",Account_Data[[#This Row],[Details]])),ISNUMBER(SEARCH("RECOVERY",Account_Data[[#This Row],[Details]]))),"Loan Payment", IF(OR(ISNUMBER(SEARCH("SALARY",Account_Data[[#This Row],[Details]])),ISNUMBER(SEARCH("EMPLOYER DEP",Account_Data[[#This Row],[Details]]))),"Income", IF(OR(ISNUMBER(SEARCH("ACH",Account_Data[[#This Row],[Details]])),ISNUMBER(SEARCH("DIRECT DR",Account_Data[[#This Row],[Details]]))),"EMI", IF(ISNUMBER(SEARCH("ATM",Account_Data[[#This Row],[Details]])),"Cash", IF(ISNUMBER(SEARCH("UPI",Account_Data[[#This Row],[Details]])),"UPI Expense",IF(ISNUMBER(SEARCH("W TFR",Account_Data[[#This Row],[Details]])),"Transfer","Other"))))))))) -> UPI Expense | I114: =Account_Data[[#This Row],[Credit]]-Account_Data[[#This Row],[Debit]] -> -300 | J114: =EOMONTH(Account_Data[[#This Row],[Date]],0) -> 45808 | K114: =ABS(Account_Data[[#This Row],[Amount]]) -> 300
...

Sheet Dashboard
C1: Personal Finance Dashboard
D5: Total Income | I5: Total Expense | N5: Net Saving | S5: Total Transactions
D6: =SUMIF(Data!H:H,"Income",Data!I:I)+SUMIF(Data!H:H,"Investment Return",Data!I:I) -> 1864603.9 | I6: =SUMIF(Data!H:H,"UPI",Data!K:K)+SUMIF(Data!H:H,"EMI",Data!K:K)+SUMIF(Data!H:H,"Cash",Data!K:K)+SUMIF(Data!H:H,"Transfer",Data!K:K)+SUMIF(Data!H:H,"Others",Data!K:K)+SUMIF(Data!H:H,"Loan Payment",Data!K:K) -> 1906085.6 | N6: =D6-I6 -> -41481.68 | S6: =COUNTA(Data!A:A)-1 -> 908
D7: ="↑ Avg "&TEXT(D6/14,"₹##,##,##0")&"/mo" -> ↑ Avg ₹1,33,186/mo | I7: ="Avg "&TEXT(I6/14,"₹##,##,##0")&"/mo" -> Avg ₹1,36,149/mo | N7: ="Avg "&TEXT(N6/14,"₹##,##,##0")&"/mo" -> Avg -₹2,963/mo | S7: ="Avg "&TEXT(S6/14,"0")&" txns/mo" -> Avg 65 txns/mo
A9: #VALUE!
A11: Home
A12: #VALUE!
A14: Overview
A15: #VALUE!
A17: Income
A18: #VALUE!
A20: Expense
A21: #VALUE!
A23: Trends

Sheet Overview
D1: Financial Overview April 2025 - 2026
E4: Financial Health Score | L4: Key Insights
E5: Saving Rate | G5: =TEXT((Dashboard!N6/Dashboard!D6)*100,"0.0")&"%" -> -2.2% | L5: Deficit Dominance
E6: =REPT("█",MAX(0,MIN(20,ABS(Dashboard!N6/Dashboard!D6)*200))) -> ████ | L6: 11 of 13 months ran a deficit. Only Apr-2025 & Oct-2025 were cash-positive.
E7: Income Stability | G7: =TEXT((Trends!E18/Dashboard!D6)*100,"0.0")&"%" -> 88.8%
A8: #VALUE! | E8: =REPT("█",MAX(0,MIN(20,(Trends!E18/Dashboard!D6)*20))) -> █████████████████ | L8: UPI Expense Dominance
E9: Expense Control | G9: =TEXT(((Dashboard!D6-Dashboard!I6)/Dashboard!D6)*100,"0.0")&"%" -> -2.2% | L9: 53.6% of all expenses are UPI (₹26.03L). Merchant breakdown needed for real control.
A10: Home | E10: =REPT("█",MAX(1,MIN(20,ABS(((Dashboard!D6-Dashboard!I6)/Dashboard!D6)*200)))) -> ████
A11: #VALUE! | E11: Overall Score | G11: =ROUND((MAX(0,ABS(Dashboard!N6/Dashboard!D6)*100)/10+(Trends!E18/Dashboard!D6)*10+MAX(1,ABS(((Dashboard!D6-Dashboard!I6)/Dashboard!D6)*10)))/3,1)&" / 10" -> 3.4 / 10 | L11: Stable Salary Base
L12: Salary stayed between ₹1.09L–₹1.30L consistently (excluding Mar-2026 anomaly). Reason for March 2026 mentioned in Income section.
A13: Overview | E13: Needs Improvement
A14: #VALUE! | L14: Rising EMI burden
L15: New loan in late 2025 pushed Feb–Apr 2026 monthly losses to ₹4.4L–₹5.4L.
A16: Income
A17: #VALUE! | D17: Financial Timeline . Major Events
D18: 45748 | G18: 45778 | J18: 45931 | M18: 45962 | P18: 46082 | S18: 46113
A19: Expense
A20: #VALUE! | D20: Income Spike | G20: Expense Surge | J20: Best Savings | M20: New Loan | P20: Salary Anomaly | S20: Worst Month
D21: ₹3.11L income. Investment return included. | F21: Deficit of ₹2.18L. Expenses spiked. | J21: Only +₹58K positive month. | M21: EMI Burden rises from here | P21: ₹0 salary. Delayed to Apr-2026 | S21: ₹6.83L expense. Deficit ₹4.43L.
A22: Trends

Sheet Income
D1: Income Analysis
D2: Apr 2025 – May 2026 · Total Income: ₹18,64,604 · 2 Sources
D5: Month | F5: Salary Income | H5: Investment Return | I5: Total Income
D6: 45777 | F6: =SUMIFS(Data!I:I,Data!H:H,"Income",Data!J:J,D6) -> 236880 | H6: =SUMIFS(Data!I:I,Data!H:H,"Investment Return",Data!J:J,D6) -> 74924.48 | I6: =F6+H6 -> 311804.48
D7: 45808 | F7: =SUMIFS(Data!I:I,Data!H:H,"Income",Data!J:J,D7) -> 113225 | H7: =SUMIFS(Data!I:I,Data!H:H,"Investment Return",Data!J:J,D7) -> 115871.78 | I7: =F7+H7 -> 229096.78
D8: 45838 | F8: =SUMIFS(Data!I:I,Data!H:H,"Income",Data!J:J,D8) -> 112936 | H8: =SUMIFS(Data!I:I,Data!H:H,"Investment Return",Data!J:J,D8) -> 0 | I8: =F8+H8 -> 112936
A9: #VALUE! | D9: 45869 | F9: =SUMIFS(Data!I:I,Data!H:H,"Income",Data!J:J,D9) -> 112701 | H9: =SUMIFS(Data!I:I,Data!H:H,"Investment Return",Data!J:J,D9) -> 0 | I9: =F9+H9 -> 112701
D10: 45900 | F10: =SUMIFS(Data!I:I,Data!H:H,"Income",Data!J:J,D10) -> 129908 | H10: =SUMIFS(Data!I:I,Data!H:H,"Investment Return",Data!J:J,D10) -> 0 | I10: =F10+H10 -> 129908
A11: Home | D11: 45930 | F11: =SUMIFS(Data!I:I,Data!H:H,"Income",Data!J:J,D11) -> 130474 | H11: =SUMIFS(Data!I:I,Data!H:H,"Investment Return",Data!J:J,D11) -> 17509.62 | I11: =F11+H11 -> 147983.62
A12: #VALUE! | D12: 45961 | F12: =SUMIFS(Data!I:I,Data!H:H,"Income",Data!J:J,D12) -> 125379 | H12: =SUMIFS(Data!I:I,Data!H:H,"Investment Return",Data!J:J,D12) -> 0 | I12: =F12+H12 -> 125379
D13: 45991 | F13: =SUMIFS(Data!I:I,Data!H:H,"Income",Data!J:J,D13) -> 109796 | H13: =SUMIFS(Data!I:I,Data!H:H,"Investment Return",Data!J:J,D13) -> 0 | I13: =F13+H13 -> 109796
A14: Overview | D14: 46022 | F14: =SUMIFS(Data!I:I,Data!H:H,"Income",Data!J:J,D14) -> 114065 | H14: =SUMIFS(Data!I:I,Data!H:H,"Investment Return",Data!J:J,D14) -> 0 | I14: =F14+H14 -> 114065
A15: #VALUE! | D15: 46053 | F15: =SUMIFS(Data!I:I,Data!H:H,"Income",Data!J:J,D15) -> 116002 | H15: =SUMIFS(Data!I:I,Data!H:H,"Investment Return",Data!J:J,D15) -> 0 | I15: =F15+H15 -> 116002
D16: 46081 | F16: =SUMIFS(Data!I:I,Data!H:H,"Income",Data!J:J,D16) -> 114840 | H16: =SUMIFS(Data!I:I,Data!H:H,"Investment Return",Data!J:J,D16) -> 0 | I16: =F16+H16 -> 114840
A17: Income | D17: 46112 | F17: =SUMIFS(Data!I:I,Data!H:H,"Income",Data!J:J,D17) -> 0 | H17: =SUMIFS(Data!I:I,Data!H:H,"Investment Return",Data!J:J,D17) -> 0 | I17: =F17+H17 -> 0
A18: #VALUE! | D18: 46142 | F18: =SUMIFS(Data!I:I,Data!H:H,"Income",Data!J:J,D18) -> 240092 | H18: =SUMIFS(Data!I:I,Data!H:H,"Investment Return",Data!J:J,D18) -> 0 | I18: =F18+H18 -> 240092
D19: 46173 | F19: =SUMIFS(Data!I:I,Data!H:H,"Income",Data!J:J,D19) -> 0 | H19: =SUMIFS(Data!I:I,Data!H:H,"Investment Return",Data!J:J,D19) -> 0 | I19: =F19+H19 -> 0
A20: Expense | D20: Key Insights
A21: #VALUE! | D21: Income Concentration Risk
D22: Salary contributes 88.8% of total income (₹16,56,298), indicating strong dependence on a single income source, while investment returns remain limited at 11.2% and occur in only 3 months — highlighting low passive income generation.
A23: Trends | D23: March 2026 Anomaly
D24: March 2026 shows ₹0 salary income due to a delayed salary credit received in April 2026; excluding this anomaly, monthly salary remained consistently between ₹1.09L and ₹1.30L, indicating stable income throughout the period.

Sheet Expense
D1: Expense Analysis
D2: Apr 2025 – May 2026 · Total Expense: ₹19,06,086 · 7 Categories
D4: Expense Breakdown By Category
D5: Category | F5: Amount | H5: % Share
D6: UPI Expense | F6: =SUMIF(Data!H:H,"UPI Expense",Data!K:K) -> 2603908.6 | H6: =F6/$F$13 -> 0.53628655
A7: #VALUE! | D7: EMI | F7: =SUMIF(Data!H:H,"EMI",Data!K:K) -> 1074150.6 | H7: =F7/$F$13 -> 0.22122608
D8: Cash | F8: =SUMIF(Data!H:H,"Cash",Data!K:K) -> 409000 | H8: =F8/$F$13 -> 0.084235368
A9: Home | D9: Transfer | F9: =SUMIF(Data!H:H,"Transfer",Data!K:K) -> 371006 | H9: =F9/$F$13 -> 0.076410335
A10: #VALUE! | D10: Loan Payment | F10: =SUMIF(Data!H:H,"Loan Payment",Data!K:K) -> 51929 | H10: =F10/$F$13 -> 0.010695008
D11: Investment Outflow | F11: =SUMIF(Data!H:H,"Investment (Outflow)",Data!K:K) -> 35000 | H11: =F11/$F$13 -> 0.0072084056
A12: Overview | D12: Other | F12: =SUMIF(Data!H:H,"Other",Data!K:K) -> 310448.53 | H12: =F12/$F$13 -> 0.063938255
A13: #VALUE! | D13: Total | F13: =SUM(F6:F12) -> 4855442.7
A15: Income | D15: Key Expense Insights
A16: #VALUE! | D16: UPI Expense Dominance
D17: UPI spending is the largest expense category, contributing 53.6% of total outflows (₹26,03,908) — almost twice the EMI burden. The absence of merchant-level categorization limits visibility into actual spending behavior, making this the highest-impact area for cost control and savings improvement.
A18: Expense | D18: EMI and Loan Burden
A19: #VALUE! | D19: EMI and loan payments together contribute 24.9% of total outflows (₹11,26,079), meaning nearly one-fourth of all spending is directed toward debt servicing. Combined with the exceptionally high UPI expenditure, this significantly reduces the capacity for savings and investments. Optimizing repayment strategies — such as consolidating or prepaying high-interest loans — could meaningfully improve monthly cash flow and financial flexibility.
D20: Saving opportunity
A21: Trends | D21: UPI and cash expenses together contribute 62% of total outflows (₹30,12,908); even a 20% reduction in these categories could generate annual savings of approximately ₹6 lakh without affecting fixed obligations.

Sheet Trends
D1: Trends And Analysis
N3: 0 | O3: 0
D4: Month | E4: Income | F4: Expense | G4: Savings | N4: 900000 | O4: 130000
D5: =DATE(2025,4,1) -> 45748 | E5: =SUMIFS(Data!I:I,Data!H:H,"Income",Data!F:F,TEXT(D5,"mmm-yyyy")) -> 236880 | F5: {=SUMPRODUCT(SUMIFS(Data!K:K, Data!H:H, {"Cash","EMI","UPI Expense"}, Data!J:J, ">="&DATE(YEAR(D5),MONTH(D5),1), Data!J:J, "<"&DATE(YEAR(D5),MONTH(D5)+1,1) ))} -> 188697.15 | G5: =E5-F5 -> 48182.85
D6: =EDATE(D5,1) -> 45778 | E6: =SUMIFS(Data!I:I,Data!H:H,"Income",Data!F:F,TEXT(D6,"mmm-yyyy")) -> 113225 | F6: {=SUMPRODUCT(SUMIFS(Data!K:K, Data!H:H, {"Cash","EMI","UPI Expense"}, Data!J:J, ">="&DATE(YEAR(D6),MONTH(D6),1), Data!J:J, "<"&DATE(YEAR(D6),MONTH(D6)+1,1) ))} -> 332130.87 | G6: =E6-F6 -> -218905.87
D7: =EDATE(D6,1) -> 45809 | E7: =SUMIFS(Data!I:I,Data!H:H,"Income",Data!F:F,TEXT(D7,"mmm-yyyy")) -> 112936 | F7: {=SUMPRODUCT(SUMIFS(Data!K:K, Data!H:H, {"Cash","EMI","UPI Expense"}, Data!J:J, ">="&DATE(YEAR(D7),MONTH(D7),1), Data!J:J, "<"&DATE(YEAR(D7),MONTH(D7)+1,1) ))} -> 375161.68 | G7: =E7-F7 -> -262225.68
A8: #VALUE! | D8: =EDATE(D7,1) -> 45839 | E8: =SUMIFS(Data!I:I,Data!H:H,"Income",Data!F:F,TEXT(D8,"mmm-yyyy")) -> 112701 | F8: {=SUMPRODUCT(SUMIFS(Data!K:K, Data!H:H, {"Cash","EMI","UPI Expense"}, Data!J:J, ">="&DATE(YEAR(D8),MONTH(D8),1), Data!J:J, "<"&DATE(YEAR(D8),MONTH(D8)+1,1) ))} -> 173296.15 | G8: =E8-F8 -> -60595.15
D9: =EDATE(D8,1) -> 45870 | E9: =SUMIFS(Data!I:I,Data!H:H,"Income",Data!F:F,TEXT(D9,"mmm-yyyy")) -> 129908 | F9: {=SUMPRODUCT(SUMIFS(Data!K:K, Data!H:H, {"Cash","EMI","UPI Expense"}, Data!J:J, ">="&DATE(YEAR(D9),MONTH(D9),1), Data!J:J, "<"&DATE(YEAR(D9),MONTH(D9)+1,1) ))} -> 170143.15 | G9: =E9-F9 -> -40235.15
A10: Home | D10: =EDATE(D9,1) -> 45901 | E10: =SUMIFS(Data!I:I,Data!H:H,"Income",Data!F:F,TEXT(D10,"mmm-yyyy")) -> 130474 | F10: {=SUMPRODUCT(SUMIFS(Data!K:K, Data!H:H, {"Cash","EMI","UPI Expense"}, Data!J:J, ">="&DATE(YEAR(D10),MONTH(D10),1), Data!J:J, "<"&DATE(YEAR(D10),MONTH(D10)+1,1) ))} -> 248674.3 | G10: =E10-F10 -> -118200.3
A11: #VALUE! | D11: =EDATE(D10,1) -> 45931 | E11: =SUMIFS(Data!I:I,Data!H:H,"Income",Data!F:F,TEXT(D11,"mmm-yyyy")) -> 125379 | F11: {=SUMPRODUCT(SUMIFS(Data!K:K, Data!H:H, {"Cash","EMI","UPI Expense"}, Data!J:J, ">="&DATE(YEAR(D11),MONTH(D11),1), Data!J:J, "<"&DATE(YEAR(D11),MONTH(D11)+1,1) ))} -> 66915 | G11: =E11-F11 -> 58464
D12: =EDATE(D11,1) -> 45962 | E12: =SUMIFS(Data!I:I,Data!H:H,"Income",Data!F:F,TEXT(D12,"mmm-yyyy")) -> 109796 | F12: {=SUMPRODUCT(SUMIFS(Data!K:K, Data!H:H, {"Cash","EMI","UPI Expense"}, Data!J:J, ">="&DATE(YEAR(D12),MONTH(D12),1), Data!J:J, "<"&DATE(YEAR(D12),MONTH(D12)+1,1) ))} -> 110808.1 | G12: =E12-F12 -> -1012.1
A13: Overview | D13: =EDATE(D12,1) -> 45992 | E13: =SUMIFS(Data!I:I,Data!H:H,"Income",Data!F:F,TEXT(D13,"mmm-yyyy")) -> 114065 | F13: {=SUMPRODUCT(SUMIFS(Data!K:K, Data!H:H, {"Cash","EMI","UPI Expense"}, Data!J:J, ">="&DATE(YEAR(D13),MONTH(D13),1), Data!J:J, "<"&DATE(YEAR(D13),MONTH(D13)+1,1) ))} -> 275967 | G13: =E13-F13 -> -161902
A14: #VALUE! | D14: =EDATE(D13,1) -> 46023 | E14: =SUMIFS(Data!I:I,Data!H:H,"Income",Data!F:F,TEXT(D14,"mmm-yyyy")) -> 116002 | F14: {=SUMPRODUCT(SUMIFS(Data!K:K, Data!H:H, {"Cash","EMI","UPI Expense"}, Data!J:J, ">="&DATE(YEAR(D14),MONTH(D14),1), Data!J:J, "<"&DATE(YEAR(D14),MONTH(D14)+1,1) ))} -> 212556 | G14: =E14-F14 -> -96554
D15: =EDATE(D14,1) -> 46054 | E15: =SUMIFS(Data!I:I,Data!H:H,"Income",Data!F:F,TEXT(D15,"mmm-yyyy")) -> 114840 | F15: {=SUMPRODUCT(SUMIFS(Data!K:K, Data!H:H, {"Cash","EMI","UPI Expense"}, Data!J:J, ">="&DATE(YEAR(D15),MONTH(D15),1), Data!J:J, "<"&DATE(YEAR(D15),MONTH(D15)+1,1) ))} -> 563485.3 | G15: =E15-F15 -> -448645.3
A16: Income | D16: =EDATE(D15,1) -> 46082 | E16: =SUMIFS(Data!I:I,Data!H:H,"Income",Data!F:F,TEXT(D16,"mmm-yyyy")) -> 0 | F16: {=SUMPRODUCT(SUMIFS(Data!K:K, Data!H:H, {"Cash","EMI","UPI Expense"}, Data!J:J, ">="&DATE(YEAR(D16),MONTH(D16),1), Data!J:J, "<"&DATE(YEAR(D16),MONTH(D16)+1,1) ))} -> 544664.62 | G16: =E16-F16 -> -544664.62
A17: #VALUE! | D17: =EDATE(D16,1) -> 46113 | E17: =SUMIFS(Data!I:I,Data!H:H,"Income",Data!F:F,TEXT(D17,"mmm-yyyy")) -> 240092 | F17: {=SUMPRODUCT(SUMIFS(Data!K:K, Data!H:H, {"Cash","EMI","UPI Expense"}, Data!J:J, ">="&DATE(YEAR(D17),MONTH(D17),1), Data!J:J, "<"&DATE(YEAR(D17),MONTH(D17)+1,1) ))} -> 683589 | G17: =E17-F17 -> -443497
E18: =SUM(E5:E17) -> 1656298
A19: Expense | D19: Key Insights
A20: #VALUE! | D20: Deficit Dominance
D21: 11 Out of 13 Months Recorded a Deficit: Only Apr-2025 (₹48,182) and Oct-2025 (₹58,464) achieved positive savings. All remaining 11 months ran a deficit, with the worst stretch being Feb–Apr 2026 where monthly losses ranged from ₹4.4L to ₹5.4L — driven by a sharp rise in EMI burden following a new loan taken in late 2025.
A22: Trends | D22: Stable Income but Extremely Fluctuating Expenses
D23: Monthly income remained mostly between ₹1.09L and ₹1.30L with no major growth during the year, while expenses varied drastically from ₹66K to ₹6.83L. Both Apr-2025 and Apr-2026 show unusually high income because March salary was likely credited late and received in April, which also explains the comparatively lower income in the March months.

Sheet BarChart
A4: Monthly Expense by Category
A6: Sum of Amount(Positive) | B6: Column Labels
A7: Row Labels | B7: Expense | C7: Income
A8: 45777 | B8: 226935.15 | C8: 369144
A9: 45808 | B9: 335350.07 | C9: 291655.17
A10: 45838 | B10: 546761.68 | C10: 565361.52
A11: 45869 | B11: 160055.15 | C11: 132557.52
A12: 45900 | B12: 145643.15 | C12: 157967.52
A13: 45930 | B13: 251824.3 | C13: 211233.36
A14: 45961 | B14: 63415 | C14: 132438.52
A15: 45991 | B15: 110011.1 | C15: 1614152.5
A16: 46022 | B16: 291808 | C16: 122396.04
A17: 46053 | B17: 211056 | C17: 121002
A18: 46081 | B18: 786825.3 | C18: 170884.52
A19: 46112 | B19: 572467.62 | C19: 1008449.5
A20: 46142 | B20: 672548 | C20: 254633
A21: 46173 | B21: 143470.82

Sheet PieChart
A2: Expense Breakdown by Category
A4: Type (Income/Expense) | B4: Expense
A6: Row Labels | B6: Sum of Amount(Positive)
A7: UPI Expense | B7: 2468491.6 | G7: UPI Expense | H7: 454143.04
A8: EMI | B8: 1074150.6 | G8: Transfer | H8: 277825
A9: Cash | B9: 380000 | G9: EMI | H9: 195074.41
A10: Transfer | B10: 371006 | G10: Cash | H10: 46500
A11: Other | B11: 137594.2 | G11: Loan Payment | H11: 34218
A12: Loan Payment | B12: 51929 | G12: Investment (Outflow) | H12: 5000
A13: Investment (Outflow) | B13: 35000 | G13: Other | H13: 1000
A14: Grand Total | B14: 4518171.3

Sheet LineChart
A2: Net Saving Trend
A4: Months | B4: Net Saving
A5: 45777 | B5: 142208.85
A6: 45808 | B6: -43694.9
A7: 45838 | B7: 18599.84
A8: 45869 | B8: -27497.63
A9: 45900 | B9: 12324.37
A10: 45930 | B10: -40590.94
A11: 45961 | B11: 69023.52
A12: 45991 | B12: 1504141.4
A13: 46022 | B13: -169411.96
A14: 46053 | B14: -90054
A15: 46081 | B15: -615940.78
A16: 46112 | B16: 435981.9
... A18: 46173 | B18: -143470.82
